<noticeable>2wYpsINud0vEBKxR92cK</noticeable>
<noticeable>BfV7vPblhIFCAuDze7vl</noticeable>
<noticeable>nrSA67zDoULWGVOQhUoR</noticeable>
<noticeable>eOApeYSaIFnTDfmOc1bY</noticeable>
<noticeable>PDX6hjCjMafij8mbuWFV</noticeable>
<noticeable>UPx7lhHSG8OHOvhmSPEQ</noticeable>
<noticeable>AREh8UnXTVjz0A82Jgju</noticeable>
<noticeable>2jXGV2xYTXxxYTfzUE6M</noticeable>
<noticeable>lHiHfrB8uUoo4zIfF6p0</noticeable>
<noticeable>JF7TEBYk2xQMA6G0EcjX</noticeable>
<noticeable>vJ3YafMQIT52A9yxZmtV</noticeable>
<noticeable>DUFDk1dZQqsc8Kh8bRGw</noticeable>
<noticeable>8KRmm8IYeCyw3rxaH0H9</noticeable>
<noticeable>EzaFMp7bA5VUcEREyXJO</noticeable>
<noticeable>zAlJw44zsgF8md25p7ar</noticeable>
<noticeable>NFJqgCUP5lHDHVr4Uv5r</noticeable>
<noticeable>01kQmfOmxhUtR0ayCBvy</noticeable>
<noticeable>l990pNtFU37rEm6clCN3</noticeable>
<noticeable>wSjuASkWsrROOSSke043</noticeable>
<noticeable>jCSUBUHjJmI9ag9yZCI8</noticeable>
<noticeable>qVjli3XxCt02v5UG5nkP</noticeable>
<noticeable>DXICoA9slg6o4q6PF0KJ</noticeable>
<noticeable>zQzYFUKo2bNtaWhoHTHG</noticeable>
<noticeable>QiNUbAwXTHMmY3kcECDd</noticeable>
<noticeable>MTCf49XtZP2lyGPuaDdI</noticeable>
<noticeable>vIP1RV72luJMHuhDA8jb</noticeable>
<noticeable>5AoUmeJxoGAxhchQt2z5</noticeable>
<noticeable>jOhMDAjjiQsvItCSoTlW</noticeable>
<noticeable>20kT9MYKq8bz4O7dwGan</noticeable>
<noticeable>mkHMSWZSFExAVjZs58iT</noticeable>
<noticeable>RmZiQmRfZiE0lgxEnicx</noticeable>
<noticeable>vLerBuBOpgYdAXWOdkgy</noticeable>
<noticeable>lcuokPSvAN2sxKzYCoM3</noticeable>
<noticeable>EcywRCCKC0miOR0jTePo</noticeable>
<noticeable>Ogz50XOIk4Sm4qWNRJDP</noticeable>
<noticeable>Bso6zla6DA0XMeCfqbMU</noticeable>
<noticeable>XPd1O0ABYRBG4goYyo5R</noticeable>
<noticeable>jUktvl1OjJtrebRpsf1a</noticeable>
<noticeable>0GNcsYDOlSFtbZAeBLme</noticeable>
<noticeable>XOIGOrs3cylPpb14jBwH</noticeable>
<noticeable>VLXAZh0Abw8Av6sWm1Dl</noticeable>
<noticeable>1k0iBEQcFKswxLVnNJJ4</noticeable>
<noticeable>wmcu0BR2Lx4gZx7w0dd2</noticeable>
<noticeable>jq32yr0QC8AcoapV3wCN</noticeable>
<noticeable>8UsBd1hs68qDHAdO3zV5</noticeable>
<noticeable>QsCbLLGCDePrEUILaJLP</noticeable>
<noticeable>AKWYpWieWMhsy7u19vdn</noticeable>
<noticeable>UbOuarLdhVS5dtdqpG30</noticeable>
<noticeable>S9XEq5P2HbFl8NgpF6XT</noticeable>
<noticeable>GYMyOpDzCvlivwDQCbUM</noticeable>
<noticeable>KIlvlOAWPLM3SypFqUEz</noticeable>
<noticeable>VHlQup283s35nW0YYrCT</noticeable>
<noticeable>BmomxDCoRqnkliJymOYN</noticeable>
<noticeable>x8XDHwlA1EczK0EK7c3y</noticeable>
<noticeable>qGiKaLYSGi9y6MdguTjH</noticeable>
<noticeable>rPAnGLMmV2ZTLID42fIN</noticeable>
<noticeable>KSWaHivAEN5z3rhFBMip</noticeable>
<noticeable>9XJKZ7KifoVeCiWDIqL8</noticeable>
<noticeable>lcWuPHlqOjfzfBaqrzFm</noticeable>
<noticeable>rY6xQKV6lyuFU2yMSAgU</noticeable>
<noticeable>vdKQNOm8wFCAg6eueqGe</noticeable>
<noticeable>qLNcPzpPyDUzs5vy9d6P</noticeable>
<noticeable>Wz1TQkU7ckozVcdnOB9o</noticeable>
<noticeable>KMCZ0nRWmfrN8Fjgjsln</noticeable>
<noticeable>y8ghqu1JK129Y5woGZZI</noticeable>
<noticeable>TKPqs0oFeMHRs06C7Ma6</noticeable>
<noticeable>YnexaFftMy1QIWa4hxMr</noticeable>
<noticeable>WIQWlFbB0wA0udNbyVQs</noticeable>
<noticeable>xHQjLAcBwgRy8wQrm9Zo</noticeable>
<noticeable>TWB4y6bEvN5s4yQ9A4OJ</noticeable>
<noticeable>IqAqqx4CbdnMbG09PQAp</noticeable>
<noticeable>DKL3XxympgoH58PHqcC3</noticeable>
<noticeable>i4pG960BCvVzCmzrY3Bk</noticeable>
<noticeable>rrUeJaurESnjRHbfXah7</noticeable>
<noticeable>EZauGyhAsTdn8q9Dn3No</noticeable>
<noticeable>5A5GnqCqQedWaKRMktjf</noticeable>
<noticeable>4A40a0WHCHWynusjrKSR</noticeable>
<noticeable>RpZE4eMH9BzKqBORKtsr</noticeable>
<noticeable>quzgHyJJAuxb9xzuAyPK</noticeable>
<noticeable>9dfrqG9LwUFnn5Z0dCm0</noticeable>
<noticeable>MIZgbudEn0dhn1C1lw3A</noticeable>
<noticeable>6hZnRKqm6FFKRVgDHivW</noticeable>
<noticeable>vOYHTgQLxITGQ2hkwfJ3</noticeable>
<noticeable>z5E6YaYUv3sMw0KDaR1U</noticeable>
<noticeable>sjIW1jnUcQQezJlS0IYC</noticeable>
<noticeable>m10twyV8eFpCG8t3sySG</noticeable>
<noticeable>kzfWdcnPoeZrKaZcCzm4</noticeable>
<noticeable>rpoibk1A6WkSIUHKrFob</noticeable>
<noticeable>SzfyniiNpuzJWdl7riAD</noticeable>
<noticeable>3DNJ04YH994aMNhbPut1</noticeable>
<noticeable>kzphdCdXD0O2noKCV0dU</noticeable>
<noticeable>aPyj3prSKnQJxXDH6YiT</noticeable>
<noticeable>KY8JSkypSwqjTrzWa9fJ</noticeable>
<noticeable>gD0mekIseGSLbkRd3jIu</noticeable>
<noticeable>OUZmh5YJdkdkZ6u3ceGK</noticeable>
<noticeable>MFCGjqPgfmqgwnYKsFTk</noticeable>
<noticeable>1If32axeqZqDG92II1J1</noticeable>
<noticeable>wh4lsWQHebGketeHZr8o</noticeable>
<noticeable>nF1Xj9LlsXBbESTCTgHh</noticeable>
<noticeable>egI6lkGu0kYiXdlrOhBd</noticeable>
<noticeable>aMZ0FivcXON1ipbl5480</noticeable>
<noticeable>7NXMMTgSRFXJRJde6cHa</noticeable>
<noticeable>dM5vjA0i1Z2O0QY8Ltfe</noticeable>
<noticeable>AFjbI4vKU7nfRXSmUIrz</noticeable>
<noticeable>qHazLUYbD2r0kcEmKiS6</noticeable>
<noticeable>vCv2VnusNh5ooQXrESuM</noticeable>
<noticeable>dh2UPwg5z4VKIRy7VebU</noticeable>
<noticeable>gkgLAxmsHSC6RzNLwGys</noticeable>
<noticeable>3meBaWrHCbykbJZUFX7w</noticeable>
<noticeable>w02e9W0uAVoWnKOu8gD3</noticeable>
<noticeable>t71wPOMzbhqH3dsitXQY</noticeable>
<noticeable>WA2stDthj98lnOK9K01m</noticeable>
<noticeable>NbdPHMGQlvU3Kty7YRcp</noticeable>
<noticeable>pij57i3CpIb1HpwVyWD6</noticeable>
<noticeable>hlUTLrr0ajj8o0uUs43B</noticeable>
<noticeable>hB5Y4eeBron7I8k80iMV</noticeable>
<noticeable>NZ232KufEMegFPHi0uB1</noticeable>
<noticeable>uBfZTcqMJcAYQVgtVTcA</noticeable>
<noticeable>Q9bNAaNiPZxmQlNX88nb</noticeable>
<noticeable>kqzs0MaVpUYYpg3GzqGh</noticeable>
<noticeable>AD9UyIKZroRI2EKl0vqn</noticeable>
<noticeable>zjNXF1F0Dl5hzLDBlEfT</noticeable>
<noticeable>fUOxzRhyYnPFVt0y4hyK</noticeable>
<noticeable>wIOyrY9mL1SPrMFOkPJ0</noticeable>
<noticeable>iq4QYYe3Roj6beO6TbW4</noticeable>
<noticeable>D5JALMTgGL0KyvfwuJJk</noticeable>
<noticeable>CvdjhH8Xur6kJPh2rYtf</noticeable>
<noticeable>aAuItRXWHEUR5VJtMAx9</noticeable>
<noticeable>gHKKNZwjLolrPIQyePNo</noticeable>
<noticeable>sfWzafKhIs8w3iBA4tik</noticeable>
<noticeable>SrOzUhKZKwc5PEvmyc54</noticeable>
<noticeable>ivIxXj0XMNNdVygUUfab</noticeable>
<noticeable>3ktZp1ArrzFXhsdJ0OE0</noticeable>
<noticeable>BW7OqkqldRgG8qzvBGtF</noticeable>
<noticeable>H6UCkVSoFCS2BIDYGBSC</noticeable>
<noticeable>E5NlhnSCdhwvFFCs4pxY</noticeable>
<noticeable>P2Neuz0ZKrPgxi1cTQVH</noticeable>
<noticeable>nlKDN8OwtqQtPcgMQHyB</noticeable>
<noticeable>xMCCKcBJF4KfIepwMEGW</noticeable>
<noticeable>v5dUQfQBHLsRhjAwJycP</noticeable>
<noticeable>yKChr8CeVYWQuA9R6MzX</noticeable>
<noticeable>fP6bQJukCjyb9uQlnABC</noticeable>
<noticeable>AICFA9Atvc05X9FWpqLk</noticeable>
<noticeable>ZH91S2wOZmIw0bDrKeAo</noticeable>
<noticeable>SpSx9DLukOlKrLgk7hCL</noticeable>
<noticeable>bvJJaGYawTOI77dIDzGh</noticeable>
<noticeable>eQAaEpBFxnAbIxQNQhor</noticeable>
<noticeable>UIqqOncjRiToL6NmUbAw</noticeable>
<noticeable>a7G41WpTJOCV1YN4Hokb</noticeable>
<noticeable>LmNL3qWIzRMYv7nawzZ2</noticeable>
<noticeable>u6D2qQs1nu0Rgp2IAIjU</noticeable>
<noticeable>I0pwxvRxHJczeDAsfzlt</noticeable>
<noticeable>juv1Z1thbRWRzzzV4Q1I</noticeable>
<noticeable>oDjrcqsjVIISAYwcgOWN</noticeable>
<noticeable>CmPz5DS10hhbGzyMFc0K</noticeable>
<noticeable>UxYdoD2Qksk3NxrPVeiN</noticeable>
<noticeable>ij2aeVKzM3bkZgissG6d</noticeable>
<noticeable>YkYsJJHdtSWT38Yv2ROW</noticeable>
<noticeable>oqnqS0FMerPVPddvBHTm</noticeable>
<noticeable>0Ifm9wQQf9DSNJecayGp</noticeable>
<noticeable>p3MmotMe3xFDZAWMFs7c</noticeable>
<noticeable>BtAGsJBrDjv0enCvFNT4</noticeable>
<noticeable>mZlq35bpFNC45fEk14A7</noticeable>
<noticeable>pbLc8ZJD8ZR5zromcsoK</noticeable>
<noticeable>eAToHlgduyyGbGBNORZ3</noticeable>
<noticeable>cAoSahdRANB1djC8dAwR</noticeable>
<noticeable>1iSE0dveV2iZ1zNt6nrg</noticeable>
<noticeable>TxgAEffzrkXbwcLRdXOF</noticeable>
<noticeable>a6hlRcDongis06D2iqM8</noticeable>
<noticeable>yPYI5qEDnrerLwCCdw93</noticeable>
<noticeable>rctfHHR3uybAPlX9iFd8</noticeable>
<noticeable>pl9ZguH8os5Xi3lkG0sF</noticeable>
<noticeable>R1ve5tgSHniJe1pS9DGI</noticeable>
<noticeable>df7EWM2jFxD9CBymhtw5</noticeable>
<noticeable>7sr0uRLRJqLI7b6gCegS</noticeable>
<noticeable>AJGiZ4vOzhSxq0MZZFPe</noticeable>
<noticeable>NDDV7DKuWX4DeIW63xge</noticeable>
<noticeable>aaWFHHe34KpQD7u2xpdZ</noticeable>
<noticeable>zrWfmHPNeBe2dnbhsMQn</noticeable>
<noticeable>XU7ykeUd7UpK1JT2D1PV</noticeable>
<noticeable>zhJJK1BZswXTqI8S5wLC</noticeable>
<noticeable>hpcFEaUSfSaf3zbKAt7Z</noticeable>
<noticeable>fzzkpV9wfqHB0HWDevFg</noticeable>
<noticeable>rJjoUctOqt82k5VwKOnr</noticeable>
<noticeable>MukvqGXxIxNWNJLjJrZO</noticeable>
<noticeable>FkvcBdvC0ANSRbEuRFmu</noticeable>
<noticeable>jGuQMtwlS8m3nih1imXZ</noticeable>
<noticeable>TP4VRhZXQlEQOd1lwVFs</noticeable>
<noticeable>XqjjrpCZtmgr6GxX6SAB</noticeable>
<noticeable>r3ktjCznVdvFnXP5OqPB</noticeable>
<noticeable>OmQX4Ps5LVFYqvgzobAE</noticeable>
<noticeable>FDJUDj90xmpmB0ZETnVE</noticeable>
<noticeable>b6bXHvPZRqXk3i24aIvV</noticeable>
<noticeable>GFJsKsjBakOBnoPu7oeT</noticeable>
<noticeable>YBvLnfNPK7qo2PLjDKzU</noticeable>
<noticeable>0QQA4iLG5QsyxP3XFnnz</noticeable>
<noticeable>OS7PrFfxg1iJLFUXZWE1</noticeable>
<noticeable>w7oX5VvKlnz3VfQssAB1</noticeable>
<noticeable>o9ivgcorj0f3WQLO4auJ</noticeable>
<noticeable>9YEUePSqGTXlYijsngco</noticeable>
<noticeable>UBxucyki1CNWDL7ZlX0k</noticeable>
<noticeable>1VujdaMMyaIcu8kJgsRG</noticeable>
<noticeable>y5jC2ORfpK9htP5ApdoB</noticeable>
<noticeable>bsqWuvMYqr2UEy3P3ScT</noticeable>
<noticeable>fowsDaj2r5ZDuMicuj5c</noticeable>
<noticeable>PCZHJ67D64sbVdFgGXjc</noticeable>
<noticeable>3NckTwAf1XOXV5iTsxDn</noticeable>
<noticeable>QkK00IUZpfwzxOFuJOuI</noticeable>
<noticeable>GCYnn2YV4lykl1QUXw3M</noticeable>
<noticeable>BO6eq0CfTnL0u54xuIpF</noticeable>
<noticeable>dKhcr44CwCW8VpfnlELn</noticeable>
<noticeable>ZilVBphO8G5JlDMdF2mb</noticeable>
<noticeable>0y8f3Odb5fagdrURFwqd</noticeable>
<noticeable>Ob2K1J7mSkrjQBhQGNIK</noticeable>
<noticeable>hB0Wi2KYqeN3fNLRfQwN</noticeable>
<noticeable>hczm0Ccw7obGA3DMOb2J</noticeable>
<noticeable>Zw6CxakRygMG5ly03FK9</noticeable>
<noticeable>iCxJ8GYUxahXRBvAq4GL</noticeable>
<noticeable>pwvAlCOR8ZeIUlHlVrsA</noticeable>
<noticeable>fPF90VEkq3tJ0Mwb7qs5</noticeable>
<noticeable>YDrtgMSTtC1hEd75EWrw</noticeable>
<noticeable>yVP5V3DsCxGyzX0RfTsD</noticeable>
<noticeable>En17vya54OpHub7mvfyu</noticeable>
<noticeable>dQeD969leeEaDcy1RYJt</noticeable>
<noticeable>CHuZV0HZavxScEcyV1NB</noticeable>
<noticeable>yfe3tUidLyoMC2GWYVtU</noticeable>
<noticeable>idiy0p2ACwLgt5VhbPAa</noticeable>
<noticeable>7CFMHCl3kaSFkrbJTEYF</noticeable>
<noticeable>uEFP8gVNBnbVmKGsW5U0</noticeable>
<noticeable>1kpK6jg4JTXc10Csws5f</noticeable>
<noticeable>bMyQkkE1EL2rITa8oQSE</noticeable>
<noticeable>d4ghOwQ1JW5f8EAyQpks</noticeable>
<noticeable>74qsAY9pOuccS85Yypck</noticeable>
<noticeable>dkXmfYcQYPkCeK5EvCx1</noticeable>
<noticeable>tQT55z3uYhBkrBJNehC5</noticeable>
<noticeable>xMmZvGInGHxeDgSSDS8S</noticeable>
<noticeable>AhSPVyVicg8bzsB2f89z</noticeable>
<noticeable>gx839713gFxhl3iMpmDw</noticeable>
<noticeable>6MB3DwA5vbXxVuoz26gg</noticeable>
<noticeable>tnLCsSo7jQi36Gsn2Qb1</noticeable>
<noticeable>PgrsLxdTd2zff0NBjw6X</noticeable>
<noticeable>RyeGIVOn1vOv9endDpED</noticeable>
<noticeable>ZQ56RpxweTNdCdKDoEGT</noticeable>
<noticeable>IsFPAuDDpRw2K5RSAViW</noticeable>
<noticeable>zpPrmLOR6uGwK7HhhXTR</noticeable>
<noticeable>qDvJqbfpvkUeCirlqSYd</noticeable>
<noticeable>blYBsXrzH9UjlOOzfW1C</noticeable>
<noticeable>VximOFJTEpBinb75Y7MO</noticeable>
<noticeable>9ZduR9kWHFXrhpTtTbGR</noticeable>
<noticeable>xzSh0iTB3fRMpk0dYLhK</noticeable>
<noticeable>fY78zYHgQ7Upb5x4dIAB</noticeable>
<noticeable>dqxJ60UStBHjtOnh16xX</noticeable>
<noticeable>rGczRVMfKATlssQ8kRIQ</noticeable>
<noticeable>UH1qWOTeZiKUWuuAOM0Q</noticeable>
<noticeable>4PrUwpyjbRQ4gNRb0TfJ</noticeable>
<noticeable>SbdPbumBdDarGsccqUqP</noticeable>
<noticeable>t8u3HTwICWzjpQnovMl3</noticeable>
<noticeable>i1qRCSfB6IH8xo8tQ4it</noticeable>
<noticeable>ADs9GgHFvh97WiFZuleB</noticeable>
<noticeable>jFUNeh1KT3jLNHJI71Vg</noticeable>
<noticeable>2mVD3woSqv2D1edd4JvT</noticeable>
<noticeable>Ji8hARpSNTcCnb0XoZMB</noticeable>
<noticeable>oPq4fqwavRhvhaudlXmf</noticeable>
<noticeable>dFo92PrClBDPoKodoW37</noticeable>
<noticeable>iytiPpafJGweMOkVw95W</noticeable>
<noticeable>CtiS9u0J7ymBW1ddAvnA</noticeable>
<noticeable>eQehclvNfhmq8qqT9DNd</noticeable>
<noticeable>Ygr5zpoZoyej5BwO0HhE</noticeable>
<noticeable>nNPj5VwBoxBCXKJQukGQ</noticeable>
<noticeable>82KHcAQfuz710pFzjI05</noticeable>
<noticeable>RcUxMm4yI7fiET6oyvdY</noticeable>
<noticeable>8mNj984BpD9CXafIHTRR</noticeable>
<noticeable>hCd2LKA8ceZWlpXySdgR</noticeable>
<noticeable>2sqjHeJzEQwytyiiimFN</noticeable>
<noticeable>UaLdRynZQTbYYuMnHktt</noticeable>
<noticeable>HGbEgJwHi3MwIJUgc8vN</noticeable>
<noticeable>D0EKOfZtSpIW5js1KX13</noticeable>
<noticeable>ccDCwNSQwxs6hRItm5yK</noticeable>
<noticeable>6lj4hR1thpEdU0PV2pdr</noticeable>
<noticeable>E65PGZHqpjBHVPytiPUk</noticeable>
<noticeable>1uxD1PXxVcSclMwOy3fD</noticeable>
<noticeable>TTgJG99s883cSJsYCS3i</noticeable>
<noticeable>1bZpkSY74JdrmvaPCPqv</noticeable>
<noticeable>C6LrJJlIIshdoV4FJKXo</noticeable>
<noticeable>qjZau7z5jAhgkLT6CpL4</noticeable>
<noticeable>yFgnsM5HxYmjlTU4HuCf</noticeable>
<noticeable>rE5SaYdpdwviE5xo5L60</noticeable>
<noticeable>yGPS6S3jwc375srZgrpW</noticeable>
<noticeable>nMnNkGl1tx9cJDeHVjiJ</noticeable>
<noticeable>8sKh2nj6yR3S8fbKHBa0</noticeable>
<noticeable>D8ry3oiZMkWZZDHMga0I</noticeable>
<noticeable>RmdNPewxeOkYiymgxl0l</noticeable>
<noticeable>sFvpRn4ks2cCQFPNYla5</noticeable>
<noticeable>hQXxs1OU5LBKHB5BFfoq</noticeable>
<noticeable>xKHidzGFf9QzD3N90dkl</noticeable>
<noticeable>t3tz7VI6Nafxn36OzWTT</noticeable>
<noticeable>Mje3pS4tLdGUXQetIG4B</noticeable>
<noticeable>SWBP0EkCgb0G9nEuJaJi</noticeable>
<noticeable>SNoblVMPTYWVSubhxf21</noticeable>
<noticeable>GQt4UhaxE6eNiUVpLchN</noticeable>
<noticeable>xgQyaAK8I4kOcKYGVKuY</noticeable>
<noticeable>oJ245PjzMUsnva4RW4f2</noticeable>
<noticeable>2hY9DwCdNUi8d5qq1hrR</noticeable>
<noticeable>xXNrw6oqPyqs6U4Msqf2</noticeable>
<noticeable>mX0EBpwaakLr9UbQVuyi</noticeable>
<noticeable>SCq81Dxzw8GF0XttfVsr</noticeable>
<noticeable>DLWxk3mDKSS7qNr9apuj</noticeable>
<noticeable>kNLljWzZL9M8CLHCj193</noticeable>
<noticeable>r4ni1DPOqREA7HPn2bYH</noticeable>
<noticeable>u6gsU6ajjdaKkAkmi2sh</noticeable>
<noticeable>EBjMaHNwmavfb4rvLSCI</noticeable>
<noticeable>LAGBehQg4Od4p46QqEjr</noticeable>
<noticeable>WVFjt9447oSKwVpQemJ1</noticeable>
<noticeable>8bllQcDiCIsZef5yij8D</noticeable>
<noticeable>78bXWg0GrDxCiw2gCz52</noticeable>
<noticeable>DQDyId0LaBu6hzItUXVW</noticeable>
<noticeable>GnAZtPUzwwKpC9QR1OOW</noticeable>
<noticeable>dMTOMJkv3d0RW1HSLTGm</noticeable>
<noticeable>IzXHz7pBP5Nmu3r55Ekh</noticeable>
<noticeable>UwYYWPEj48uSKXSgtZy4</noticeable>
<noticeable>lE8CCmqqIqTcjx8HnZv3</noticeable>
<noticeable>jHsvTWFxhWphGxdS9xii</noticeable>
<noticeable>nwMmpunOceA1Za6Ccgu8</noticeable>
<noticeable>q4Tvj4CkcljMs3GwrsSi</noticeable>
<noticeable>F3hG0btWPrX8TZtb5EQK</noticeable>
<noticeable>4l9JFPq1EZr0Gu7QigM8</noticeable>
<noticeable>dM5KB7ZPMB9OSMOjWL7B</noticeable>
<noticeable>pxkRqpclr2A617noKHTk</noticeable>
<noticeable>MfIHBFei1LiVbtp8mZXt</noticeable>
<noticeable>AHvWhUjr7ZcFcIJYJPt1</noticeable>
<noticeable>VbZm6EbwEkWrwruZGvtC</noticeable>
<noticeable>hKX1rHmkp1oP9uyIwdUt</noticeable>
<noticeable>mIzsVWm2jPMtPBiYtMM9</noticeable>
<noticeable>mro4u5Ngan2KIN6cnoKC</noticeable>
<noticeable>h78IX0JdN7Q8cUKn423Q</noticeable>
<noticeable>g5EeqU2beQDmhqUsGuFp</noticeable>
<noticeable>G7KkEbycmIYoVdN9CJPY</noticeable>
<noticeable>nAoNokPiBSx24igViSbx</noticeable>
<noticeable>qyAmK7Owd2u3w1Vo2Ass</noticeable>
<noticeable>xCSTbiyMCx2EjHAuktDV</noticeable>
<noticeable>oguz3gaUkQVSC9ElLIfm</noticeable>
<noticeable>U5Xb9472F92ZrQ3ldRnf</noticeable>
<noticeable>LnkdPjZ1lzj4A9d8LiBG</noticeable>
<noticeable>2hjgw8MWTv5kXFIjupoL</noticeable>
<noticeable>mi2oGgfZp0nV25cMUnpn</noticeable>
<noticeable>3C4JztLIdBsENV9ZvC6c</noticeable>
<noticeable>ukz5OSkseEOKbQh73axq</noticeable>
<noticeable>nTp3rCcXZ6cb71wJjNqB</noticeable>
<noticeable>KfcuGwGT8N1PGczIAkiT</noticeable>
<noticeable>t7R6UruoCV18r30r0Znt</noticeable>
<noticeable>TCifc30CQHMd4Tf0LDpf</noticeable>
<noticeable>DRh67eBnDJOSffLUvl5E</noticeable>
<noticeable>cx8KuLETfsGmnAh8YJ99</noticeable>
<noticeable>A2VJAerMuUhHRgYsF2gI</noticeable>
<noticeable>VB6ybnsPaVmvrHI69IZn</noticeable>
<noticeable>V3T1jal63ZDE7scYXqvh</noticeable>
<noticeable>Awk9MCCA2IMNXrKAMU6A</noticeable>
<noticeable>TT7na954lXHgyw5bF5wk</noticeable>
<noticeable>5MIKHRgNSQYqe2g9Iir4</noticeable>
<noticeable>XjaiVEyI0IaTXgxXzun5</noticeable>
<noticeable>zysxcwx1l8XH9zKbq8GV</noticeable>
<noticeable>UmNN1TRGCsobxz1OVx0g</noticeable>
<noticeable>hjNQf3XDOX0MQwGjXOiu</noticeable>
<noticeable>MfexDraawCzKMCnZnzXR</noticeable>
<noticeable>rjmQlQdh2EDILQGmFJ1v</noticeable>
<noticeable>WcRFVK7tH7OkZIteD6nJ</noticeable>
<noticeable>QQjOL8UWtO7IQLsGc59Z</noticeable>
<noticeable>XbeS5yP8FGzhfBqXEeEQ</noticeable>
<noticeable>FzqaNk9WSbbxJYBlQYct</noticeable>
<noticeable>eTx7Hd28Q90gYeBs2FWD</noticeable>
<noticeable>sqZBtmGB8xsWGqfPwVr2</noticeable>
<noticeable>izCDVj76iTKnK2odaj7I</noticeable>
<noticeable>aX88ioj4JAi7h5NC5eBW</noticeable>
<noticeable>A5IZCKl8CxaFCnOVdVdr</noticeable>
<noticeable>b1QSknTOu265KgJ5n4lB</noticeable>
<noticeable>QCHz35szgxFIYfprL7rx</noticeable>
<noticeable>FipBJqElCs7VjHUzv6kI</noticeable>
<noticeable>m6eX1BnInKlRqiLmcBZL</noticeable>
<noticeable>SPpzip92ykrOO4lK2H7g</noticeable>
<noticeable>JE11zeeLk2Owa99B5I2W</noticeable>
<noticeable>4I5fqNfbDfaxju3AzcXi</noticeable>
<noticeable>3kuOZ6ar3mkrFXreq3nJ</noticeable>
<noticeable>qNqRcZX2nTSIUGNLy6kD</noticeable>
<noticeable>XljJq87MJPz8l0WhjAp2</noticeable>
<noticeable>g5tn5eEjDiNsnDqfXGNt</noticeable>
<noticeable>bpP506E1YmvPocagRRsP</noticeable>
<noticeable>HGDZApdpILKPlaDdiDzy</noticeable>
<noticeable>oei3xxMQKUGuNWECVD6Q</noticeable>
<noticeable>eGponZyFILlA7nP11CMd</noticeable>
<noticeable>Wdn6gwDCvw9hgLccIKL8</noticeable>
<noticeable>HgO2Zgl97dwecTZk2KOz</noticeable>
<noticeable>mCGvyGHR6qDve32grNKX</noticeable>
<noticeable>YgzljMheYv7SbezZpf7V</noticeable>
<noticeable>jIGyJiEA22ixaRdlXRss</noticeable>
<noticeable>flMH76WgmTthhTIbVBGL</noticeable>
<noticeable>k1FUdV9vx3uSD2MqGXbN</noticeable>
<noticeable>qBAh7oQfRDwX6YXPhcaQ</noticeable>
<noticeable>VUEf3wasL2Akprhz8kNN</noticeable>
<noticeable>qFGtE9XxEghjEGD9vFg9</noticeable>
<noticeable>iWT6NUDW6Bi0eBNyHpmQ</noticeable>
<noticeable>yvDoG5FWo5aeANW9jZeX</noticeable>
<noticeable>f5GdwlvcvrneVlcSCfjS</noticeable>
<noticeable>fwlVGGHKar5ypIdjI6Ek</noticeable>
<noticeable>pZTs9MLimcKUPM2fcQBO</noticeable>
<noticeable>7atprmUTQfTMprSppEG4</noticeable>
<noticeable>IZd7rnaUbGSZmL6BO6TU</noticeable>
<noticeable>8pHoVygEaSwbMZ0Gck6l</noticeable>
<noticeable>HlwWJxUR91jyRyoCuje7</noticeable>
<noticeable>uPHtINFPQpmRmy0Hx097</noticeable>
<noticeable>jb8RFcycfpHFRXHD9yfe</noticeable>
<noticeable>fW1HpmiemIYvkncHMsRC</noticeable>
<noticeable>dmJzA1DEZ5tDZPTOdOEn</noticeable>
<noticeable>7d018fJZsEoE2j1iLhEf</noticeable>
<noticeable>4Z85e9XWdlBn43rkxQmG</noticeable>
<noticeable>3t4xfDLmfSG11LPQmQ8d</noticeable>
<noticeable>ix1kUo2QJ8xFfnTerahr</noticeable>
<noticeable>SWCwVPGAzuUWACaJLNqG</noticeable>
<noticeable>Ayuf8Mxm4YjlmA7QQST2</noticeable>
<noticeable>kCyerX0uip7OqnZwJY1S</noticeable>
<noticeable>A9tItrazJ5C0rnLMGOpm</noticeable>
<noticeable>Ekf4nPgm1eErOgqYSLjU</noticeable>
<noticeable>DOTaCv2hDcSKaKUPtXgW</noticeable>
<noticeable>dWJ0FX6XRFSfckX7a3zB</noticeable>
<noticeable>Z6u754pQ1DHpqWz7z7jr</noticeable>
<noticeable>DUcB1rg3DVjtFDfncjzs</noticeable>
<noticeable>n9lBBDzxsu9Ge3EbOuFh</noticeable>
<noticeable>pMC6RUqSJqacpUoZcQNw</noticeable>
<noticeable>Uwe7m1QkSKtG1XCuhiLY</noticeable>
<noticeable>JNb5Dg8FesGhgkvfuuXl</noticeable>
<noticeable>ikGgO7Bk8Mqs2j8jEAqu</noticeable>
<noticeable>rxM3uJc1Llh1ctaFdfCE</noticeable>
<noticeable>x1Ex6e6tooCrGNUMCQWa</noticeable>
<noticeable>Y6NsEanTgUpTLZdRyJ9n</noticeable>
<noticeable>HEyputJZQgi0tVem95xK</noticeable>
<noticeable>aMkA3jLdOK2SxrHI8wyk</noticeable>
<noticeable>oox2Yiya7BiNIVGPUVCI</noticeable>
<noticeable>jnKXIJKTlSRyoc2nDFlm</noticeable>
<noticeable>gFsfIkHj1BzyjQETwWBT</noticeable>
<noticeable>D6uCi3DkoOY410F0l8vn</noticeable>
<noticeable>YEAwsJFZTOQ1SdGH6dBW</noticeable>
<noticeable>o2ZWfALjbWuVMNEwh2j5</noticeable>
<noticeable>kPDchDCUDJen7LEyYq8o</noticeable>
<noticeable>HawfyiKArUAORjZpMrK9</noticeable>
<noticeable>qUuZjfv2laJYUEgYMwWQ</noticeable>
<noticeable>DVzaxNqe7CUvOEb509JH</noticeable>
<noticeable>4O1f9vc2J0Wzz4OYeScS</noticeable>
<noticeable>DExmAtZKlfZuI55qHRGl</noticeable>
<noticeable>8TlbFCcBXt8ylWkwAErt</noticeable>
<noticeable>wZJfRbUy9cyGw9Yglfqz</noticeable>
<noticeable>4LIc62wMszjIvazOY0zv</noticeable>
<noticeable>9qpMuQpi3GioiAi5fiY1</noticeable>
<noticeable>A5tYmn8dqQDgeQeKZ8iu</noticeable>
<noticeable>NJ1jFODQ4UZZDlI6BMuA</noticeable>
<noticeable>sBxnEdCStzNhShgADmEX</noticeable>
<noticeable>Dg6zwVHpOSAx4cO50zfC</noticeable>
<noticeable>0xRo0SPEUN2TSOhDN7vS</noticeable>
<noticeable>t9NnN7vk7equnU7AWuNT</noticeable>
<noticeable>ZOdkq9sxaefMXflYcAal</noticeable>
<noticeable>pFiUbY2I6UH1Tdhj78Rf</noticeable>
<noticeable>y9hqxodCmWkWLDB4Bh0d</noticeable>
<noticeable>aK1uiLVavWLn2pzjGr2R</noticeable>
<noticeable>rGk26L3k4EKz1cLi3yU4</noticeable>
<noticeable>kYp5LeHhpExufiGzIVDo</noticeable>
<noticeable>Z7E8P8GmO5OHcgNCmAw0</noticeable>
<noticeable>cmi3mmbKLE2f5FNwvZxm</noticeable>
<noticeable>RPdkpyoZWkcykYPXvVyI</noticeable>
<noticeable>7TBUA43TbP8lIXUDtyIE</noticeable>
<noticeable>A8jrU68cEAZIYbwti3Sr</noticeable>
<noticeable>KbRberKfRv3i0ii299B1</noticeable>
<noticeable>wXbE6YteCX0YZLVayxzv</noticeable>
<noticeable>2OmbGbm36TySKAiTBVwd</noticeable>
<noticeable>Hdfc20qox6JEbEEQP7bF</noticeable>
<noticeable>yATGvbLCZqM6C8Joew8A</noticeable>
<noticeable>9w9AYRfmexFjUq14OJv8</noticeable>
<noticeable>GBaIazhk9B1yW3e932Mf</noticeable>
<noticeable>vn0Uzpn7qISdXAwBHMRx</noticeable>
<noticeable>SqFipPP8RRxi779z7n7v</noticeable>
<noticeable>5cNfk3POkWHRdLLRgZQt</noticeable>
<noticeable>cyPRIx6j3k2kUXjuMc7e</noticeable>
<noticeable>nccMzYnHtXNgWJrgwb9q</noticeable>
<noticeable>hrvLkEXzRIUd4qACcx39</noticeable>
<noticeable>uUWsvfSOOwTufkGF5XxM</noticeable>
<noticeable>8Q8roBO8Km37596rYUHx</noticeable>
<noticeable>VpzKLh11wJXZH91a4zaU</noticeable>
<noticeable>lw0ZkCt0eOu4XgGGJiIS</noticeable>
<noticeable>MkSzIEjkRyqRBWcUFkyY</noticeable>
<noticeable>G3B7KdEbhOUqw1UlpBZS</noticeable>
<noticeable>4Di4JDpuWY9EI7PjvdkN</noticeable>
<noticeable>unbgqDTnemMu4pq5vCa0</noticeable>
<noticeable>hcUKcLsLDGb8PDB9mCvC</noticeable>
<noticeable>lRasJh3jTnM9w1YN5p5S</noticeable>
<noticeable>1DTP3kNUxPk56vDpTldx</noticeable>
<noticeable>ysQZXqT3OKHtxZXLeiU0</noticeable>
<noticeable>v83odft8ckiZd9lZaOeL</noticeable>
<noticeable>OTfzH9VH5jWgQMsGqUQY</noticeable>
<noticeable>vmDpZAXdXJPzQRkKK8nT</noticeable>
<noticeable>KlEcAy467x9CLg2PMqYy</noticeable>
<noticeable>ryjVjNFedv6gb9KgbfhR</noticeable>
<noticeable>dxz3vvnIASwYNQqgjY0Y</noticeable>
<noticeable>TgCK40V7g2nP2HvBnH7B</noticeable>
<noticeable>UFDgnPEu1whY3IZyBsiX</noticeable>
<noticeable>waD4I5UI7yyH7LEz5bbF</noticeable>
<noticeable>B75bgyOu1vEubIxQy1uM</noticeable>
<noticeable>3KRqnTZFHHrpAN34WZlR</noticeable>
<noticeable>mYi1ZA3w9RDyWO9oNlOI</noticeable>
<noticeable>zjMjyxOuMasHMjdlOUwz</noticeable>
<noticeable>awi5JTZ7bKbQawrX7Ope</noticeable>
<noticeable>o0NA5WZAmZzjDMcYDK5p</noticeable>
<noticeable>ERsfbDQ6MDvSsVkZJifh</noticeable>
<noticeable>W7ByQQyTvW2ReEJYXGyB</noticeable>
<noticeable>5xeOQJmmfm1j7phjO5vH</noticeable>
<noticeable>YYiBPE6dH5Sks60iZsVh</noticeable>
<noticeable>rrjtvg1W5iDVZsJ2qOt2</noticeable>
<noticeable>YD8xDPMcJSKgsTSpYIWT</noticeable>
<noticeable>vLYkWOd5yJxDplQE4uua</noticeable>
<noticeable>TUp0MXiPvWm2w2mP6yHf</noticeable>
<noticeable>Olf4v2YuG5jePEa1ha6r</noticeable>
<noticeable>Pb9BnshId84pc50Mgxav</noticeable>
<noticeable>z63hUf5ZAs1NjWBbzakF</noticeable>
<noticeable>OkI6uKP28rQIqP3kyoQ5</noticeable>
<noticeable>jgvAgfLz9hyRfEa8aeAD</noticeable>
<noticeable>Vqt0z9fQ26hVNzXetbjq</noticeable>
<noticeable>pWr6KKEKKwFA2DtgMA5p</noticeable>
<noticeable>kwfVHxJEGrDX4Z6ZXm9m</noticeable>
<noticeable>uDcOhvTvQJ7UMjKMkOBk</noticeable>
<noticeable>XiePjjhodnzCtrZP6SI4</noticeable>
<noticeable>gz0ZVtwBUCwtcG2cMtHO</noticeable>
<noticeable>JDzDrgOLv6B9RUtDhHhU</noticeable>
<noticeable>wx7oVqNMtG7yJXoio6hW</noticeable>
<noticeable>ZRjAaRy0p55VmKHrfALl</noticeable>
<noticeable>ECyrxRAXfhB8uNooEnDE</noticeable>
<noticeable>IV6d6ydH2mIxi3KARQid</noticeable>
<noticeable>3k0fi4zn88XgIid4t2Vh</noticeable>
<noticeable>RVWwoD26wAvLMG8Puj5O</noticeable>
<noticeable>MFC8UQJAALJwzbjhRVMY</noticeable>
<noticeable>Mk14rk8oeolAZhXcDFvH</noticeable>
<noticeable>zVph3gr0I1SYHn6USBok</noticeable>
<noticeable>6KAILmoNtwnPqFHvBpQN</noticeable>
<noticeable>sCSHNVM715qkSILPC0kw</noticeable>
<noticeable>hvzBQJXJSb8RGEdfR0fo</noticeable>
<noticeable>SPh6a6HHNt5VyE1XIpHu</noticeable>
<noticeable>YGVM19muDk3a3eFEcqIr</noticeable>
<noticeable>YUqdvvVhX6hVeah5XjIl</noticeable>
<noticeable>NoRlPBNugJQ6kLGde32r</noticeable>
<noticeable>CAK1vjOq0MiAtEXfZftk</noticeable>
<noticeable>9A4G3ML2tddspMC2xXTI</noticeable>
<noticeable>08eJXPw2uBGhXviIitOL</noticeable>
<noticeable>rUO3Foh8YN8nSQcvTPdj</noticeable>
<noticeable>KnCqehD395vhNvvDQUQw</noticeable>
<noticeable>HSZWDBRBmY6i01lsJeL2</noticeable>
<noticeable>vHT6k5EB0LV45Yi6NuXH</noticeable>
<noticeable>aGoXhtIIJ9CelmY9mmP4</noticeable>
<noticeable>zf0kfLx0vxuED55tUnd7</noticeable>
<noticeable>OIWjy1gGHF39njNX2cuT</noticeable>
<noticeable>SgW3giG0AFk9PL0T7jXw</noticeable>
<noticeable>derZZ7F5IwdWo0uzbqJf</noticeable>
<noticeable>P106DOToMjDlAMp2xcCD</noticeable>
<noticeable>8glR5M5pEQCaLdMMuZbb</noticeable>
<noticeable>R8kmRKYQ4Y79f5ftTi9y</noticeable>
<noticeable>N79mOFvIRyiRiGY94GUL</noticeable>
<noticeable>0EsmQmPjtmzp6xupFd0P</noticeable>
<noticeable>00lLoh4WKqrxkNbaJPYT</noticeable>
<noticeable>fUQKIkXIl0yio6npRIUx</noticeable>
<noticeable>8IU8PIuB1apJHhFSdFgt</noticeable>
<noticeable>9COQ7o3C63UapSeTuwlN</noticeable>
<noticeable>MAAPn9PfiJKfNkXJCIR7</noticeable>
<noticeable>6GBhtjXDnedqXZtNpN4Q</noticeable>
<noticeable>Qc62B7w0Ro9BDBXGZFw4</noticeable>
<noticeable>ieuXa7MwOxF5gekZv99g</noticeable>
<noticeable>o6lCvl6jGSMB4sVfpFFg</noticeable>
<noticeable>OyIFSjlrEHiijYYSlaLm</noticeable>
<noticeable>FZ9oaBtP7MA2H0WROYMk</noticeable>
<noticeable>pPMDp1g2LIcnspUUGsj1</noticeable>
<noticeable>O8E7NZe06YR1QxAIDzdw</noticeable>
<noticeable>TNptHFhZlgTYrDQvrB4L</noticeable>
<noticeable>DsKHvsaLm0eapuoJJtYI</noticeable>
<noticeable>r1fmSsfYTL2kemU4hZ5e</noticeable>
<noticeable>Tv5gaSVtFDahaeHZP66r</noticeable>
<noticeable>X512gk7VPA2w8aFdrB1U</noticeable>
<noticeable>0HAeRBTkqWxj6BeTMDnK</noticeable>
<noticeable>B0fLyJ1v756T1FSAZUhk</noticeable>
<noticeable>BsitJR3g6S45nDb6olIU</noticeable>
<noticeable>8dWpIyMtN4qpA8ZjqpEm</noticeable>
<noticeable>48XMKpBqts46xT7cNSuc</noticeable>
<noticeable>hmqjZRGWhJqJHjHnyXsq</noticeable>
<noticeable>Oy1n11zuxQXl8n8RanXi</noticeable>
<noticeable>rBBNm3FKHhXUeDbndGj8</noticeable>
<noticeable>APMLRB6PlkW48YYZLsYc</noticeable>
<noticeable>KHvycPGEiLflKjLkx94s</noticeable>
<noticeable>mPF7YHKtxyCdujPsg4Ik</noticeable>
<noticeable>wf6sM2PalGJ80kjO8WDD</noticeable>
<noticeable>rJURUvWZMoJLYo2Ci8Py</noticeable>
<noticeable>u5Gb7m5JQL0b6hYJahVG</noticeable>
<noticeable>0r6XKTU4lQZikuWzIirV</noticeable>
<noticeable>W3vm8KTzBgZBUufsiDSg</noticeable>
<noticeable>SmsCDqKynFH8CyVe486w</noticeable>
<noticeable>GvZ4lttt8BynMqEWZOLF</noticeable>
<noticeable>bLFchRM4MFK5Fgb8NdLr</noticeable>
<noticeable>tSIDBJut5938ttdC93i7</noticeable>
<noticeable>MNFPSfZR9wgaLAbzUnGC</noticeable>
<noticeable>THHBgEdYclpuDajXOaj2</noticeable>
<noticeable>N4jOwJiks565GeSaYjOR</noticeable>
<noticeable>EhcgxB2fBhUbNaVrZJeK</noticeable>
<noticeable>7lDwwSsmlycAj0DxPxKs</noticeable>
<noticeable>raTHh7lupGopPskeHdt7</noticeable>
<noticeable>COaTXYZNQtCeSQnERAOK</noticeable>
<noticeable>imyFNfpRBheg70AG7E3p</noticeable>
<noticeable>VuGY6qYM32v8lFvSl5sz</noticeable>
<noticeable>DFfk1lAihO6MonUE9FDh</noticeable>
<noticeable>qFDW5JVDFTzpqxFg8Yc5</noticeable>
<noticeable>zJbXPXyWpzQ0l16Huwhe</noticeable>
<noticeable>FdN3a3U7H7Ngcad4OMb2</noticeable>
<noticeable>hmMpXktwBBw4AX7xfLLh</noticeable>
<noticeable>shoZRe53cwpPsSR10hX4</noticeable>
<noticeable>dk1YlaRxYzc6234RzFYQ</noticeable>
<noticeable>8ssHKBHN93NBwRmZPp77</noticeable>
<noticeable>Bfvbs7hpE2KWHaSzEXIt</noticeable>
<noticeable>lamg2AMea7J3xbp5Fhrt</noticeable>
<noticeable>JpnwnVyLuubbKP9oMHSy</noticeable>
<noticeable>y8LiSxgoyTLP3C99YQxT</noticeable>
<noticeable>gtix7Kjwk2lUARAsOacn</noticeable>
<noticeable>ZGgFiPveVDNk0T7wR2rk</noticeable>
<noticeable>cFBztflm6LWEQMCFCFZn</noticeable>
<noticeable>HkJhpqkNPekyDyQlu9hm</noticeable>
<noticeable>flzXewCU3f3t50oblu5h</noticeable>
<noticeable>OIkyOktpmeFAjlFySUh7</noticeable>
<noticeable>kov6EqOfYYJJ9UdPPs6l</noticeable>
<noticeable>oGRUTevsIhieQFZbz8aL</noticeable>
<noticeable>I5PphG0TOXbefMs1owwm</noticeable>
<noticeable>uOdw2jIaWdYSwS0vIXUD</noticeable>
<noticeable>xVfTAjs2jByzLQ6dAO5o</noticeable>
<noticeable>7uA97o5qOt856xkvb8zL</noticeable>
<noticeable>honfJcegIKMCxADQqLbp</noticeable>
<noticeable>J4PuuvyDn8hQWEfo7yql</noticeable>
<noticeable>mdpAw5GKRh89YJINnJo6</noticeable>
<noticeable>xAiTNG2De0sH3c1D7LOn</noticeable>
<noticeable>pxUc7oQKlXd7GiPE4rxt</noticeable>
<noticeable>cMYSnAdGU3J1TpPFdOwF</noticeable>
<noticeable>m3Wlmuv8PuNISpo8dG8B</noticeable>
<noticeable>ubOubmuX6SkkEjMvib77</noticeable>
<noticeable>gcif2OonAGhpEHlHJJQI</noticeable>
<noticeable>3ai1lgm2eXWEQfAAha1j</noticeable>
<noticeable>RV7VpIzhIM1PmO3ARfjj</noticeable>
<noticeable>Ik7TW4PyzRaD5fHBnASD</noticeable>
<noticeable>IVX7y3qIhe7lrZZuEmOd</noticeable>
<noticeable>B4ao1Qa4LRR5yilhpiaN</noticeable>
<noticeable>YaAQVm9Cu6e3jInSkVkT</noticeable>
<noticeable>xNOeiCIJmYisuxsmMtSI</noticeable>
<noticeable>WpopXc3n3BwT79yZprrk</noticeable>
<noticeable>ebjOhYWSayDyjE65n1CJ</noticeable>
<noticeable>FO7H1Q9rh2DmzBpnqpm2</noticeable>
<noticeable>Wl4W9WLCGzxWys07YFX8</noticeable>
<noticeable>c79jZTzYDRGyg5SdGxmL</noticeable>
<noticeable>61u5om9JifslcTEOi0EX</noticeable>
<noticeable>jQKNj65dNPENbkaczObS</noticeable>
<noticeable>aPovvychfATYLBZZKtbu</noticeable>
<noticeable>RCkBH0r9eO68i59Wv6GZ</noticeable>
<noticeable>IRyEalDsZcqifYRvjAeL</noticeable>
<noticeable>9HWrs3sIKJAYocWad35h</noticeable>
<noticeable>4erwnUImrABxNVtqrbCw</noticeable>
<noticeable>N15b2h8EdSKaU5lZI5xZ</noticeable>
<noticeable>n48xmgXvvinJUKNkQJ1L</noticeable>
<noticeable>XPMXyCaxsJZZiFnXlUPi</noticeable>
<noticeable>BGcTiyKubrPojwNVPTL3</noticeable>
<noticeable>8yu8kQ0q51FCzwNKxqcL</noticeable>
<noticeable>kxcWzwDpGyk9LYUPUyNk</noticeable>
<noticeable>HNytlqnc0OWBsszJgJUI</noticeable>
<noticeable>QUfkbmkSr9OevV9LkbQV</noticeable>
<noticeable>blk1Tr96uOz03GH2eBFl</noticeable>
<noticeable>28zxYCd4zM3HKj8jRzX1</noticeable>
<noticeable>PeqzCUBSq8KeB0lGp2bj</noticeable>
<noticeable>adaUB6LpALUliUYY3TJk</noticeable>
<noticeable>xKWNBi1PDyzQMIDSnkhf</noticeable>
<noticeable>VK6QERJ1FySzQOyNk8E3</noticeable>
<noticeable>IJBlEdf5iFaM2LRQ05Us</noticeable>
<noticeable>kwXIigdNtVmwQWdPy4kB</noticeable>
<noticeable>p99DF9Gr1IalxMeLUxcL</noticeable>
<noticeable>nwRyu9kad6cByvNNoCiR</noticeable>
<noticeable>NdfFFNzmrf9cNJkUYanb</noticeable>
<noticeable>kP94TmaqJmQXVep83D5d</noticeable>
<noticeable>MgNakWJPhgxdaQZsOSlB</noticeable>
<noticeable>BfLEc0BmniiitmiZzbQh</noticeable>
<noticeable>Agiya0dLGuyOL1z2IRtQ</noticeable>
<noticeable>vT4FGFuSAlm1bXk84TNR</noticeable>
<noticeable>7W7fxfNvYUm7WQy8rYTi</noticeable>
<noticeable>MBFyN9w00v4kBSUznhrO</noticeable>
<noticeable>2LkvTamwEQt4dErVfglM</noticeable>
<noticeable>l38qbMzP6UjrddJZrkZr</noticeable>
<noticeable>710LSmQ9POvGDVbt5xxB</noticeable>
<noticeable>iQWeGOsyBRcAfp8cTpL6</noticeable>
<noticeable>9Tsk4sArR9vE9uxQAnKq</noticeable>
<noticeable>OJjcbhJaFASCNYiXeBSM</noticeable>
<noticeable>BlTi8D4B4PVUzQuXvyhz</noticeable>
<noticeable>CgMdZ6E3URxSYiS3VBo5</noticeable>
<noticeable>ODFnudm4m5vQsmIUzo2v</noticeable>
<noticeable>ykWJ1g2YLMCJOqWQntPL</noticeable>
<noticeable>EV3giRFNyTK3gRN5dnQo</noticeable>
<noticeable>TFtYvGmHzLatHF6RVBdg</noticeable>
<noticeable>sWkuxd6sIO64XjsO6GsK</noticeable>
<noticeable>57PlbHEVQlazTEDEQS4e</noticeable>
<noticeable>DgHBw2tifVCziJyKAXYr</noticeable>
<noticeable>2LZ0CfFpxdR7uSMYmY6i</noticeable>
<noticeable>kgORjvjbMPh4M3EM6z5Q</noticeable>
<noticeable>SCn7OcnVGkoKajp0dgWt</noticeable>
<noticeable>UnuaQWh59UTkTXP2jfEf</noticeable>
<noticeable>f52pvnFcFHPodFghflf5</noticeable>
<noticeable>gMaxDq6QAfeEgYEwvKx9</noticeable>
<noticeable>wPf0WLDwcfPMXdHWBIRQ</noticeable>
<noticeable>MuuFRgCnsuTcby7bY5z7</noticeable>
<noticeable>J75j5HYkXJLMrvrMKkiA</noticeable>
<noticeable>vyCZM0zFH6jEYs2Ic0Rj</noticeable>
<noticeable>ZiPS63DPjbBkbX2A0O0N</noticeable>
<noticeable>3hhAVKXHfVvo9QG24aq4</noticeable>
<noticeable>8fvy7rOMVhThR8BEUiOM</noticeable>
<noticeable>nTxJ5Pz6GY0AWSLYdkOX</noticeable>
<noticeable>V6yU5HbE18p0WtdP1VWb</noticeable>
<noticeable>X4jkaDt4LUnUNiqW1x7j</noticeable>
<noticeable>7IjyK4FSV2vxqq3APqiB</noticeable>
<noticeable>duKA3bclXeBhoe47yJjT</noticeable>
<noticeable>RrymVFTXaRFMSa6tbcMv</noticeable>
<noticeable>hWjir17ctZi871luEs5c</noticeable>
<noticeable>WqCgfvoyxJcsb6kbm4xA</noticeable>
<noticeable>rb4DrvB7oPNmgEZKWigd</noticeable>
<noticeable>naqSI0but8SIy97hxv3p</noticeable>
<noticeable>IcaGUNqDcur6WNTQVYsF</noticeable>
<noticeable>PfBjXAAmlh9ZO6F35koQ</noticeable>
<noticeable>aztXlnrjng4FLpZjIpT8</noticeable>
<noticeable>OIR8wGC0cjk4cVZy92au</noticeable>
<noticeable>V1irsmagAaCPzRIA0qMk</noticeable>
<noticeable>ORaUzovKJRxNsqLQZlbw</noticeable>
<noticeable>de31KruUcZT4lsCtOFdg</noticeable>
<noticeable>GehLzO4POHhcmCrNRv5u</noticeable>
<noticeable>mBySWiYByY64D8mDr5IG</noticeable>
<noticeable>FXmeNK5EkADRkzZxxXv4</noticeable>
<noticeable>LJ0a0i6LerneNPB3W7t0</noticeable>
<noticeable>lDrVg0mX6y54HNHRftVE</noticeable>
<noticeable>vE0pedxNe4gLUm4AUAIn</noticeable>
<noticeable>KX9CBc9IWrRagvKrP7Q5</noticeable>
<noticeable>z3GIABBnQyJuOmJWI5Zm</noticeable>
<noticeable>vZ3HaRMtlLnawVElkH4L</noticeable>
<noticeable>Gs909kyoxCkEiyxKwdXU</noticeable>
<noticeable>VUWisyuy4yCQud00pkDt</noticeable>
<noticeable>fIw4xsJpovGtAVWu95nr</noticeable>
<noticeable>QrW09aXyPSaZj30IlPit</noticeable>
<noticeable>n8S8Y1g2Yh9qCbYya1dI</noticeable>
<noticeable>dMzETM6vuGhkSBfDAnqo</noticeable>
<noticeable>PlkJBOgxPTX10jJEGk3B</noticeable>
<noticeable>5bOKubECVufeMM7raGi6</noticeable>
<noticeable>XVjPPw1s1wVoEgiSBgzH</noticeable>
<noticeable>nRSvgg2pV4U8ZtX6fi42</noticeable>
<noticeable>1EOptrQ7D0BdX4nVlQDs</noticeable>
<noticeable>i8tHhEBpGoHKKMGJpXxn</noticeable>
<noticeable>W2tkidQVxKsEIojTG17W</noticeable>
<noticeable>pslJM2gMQ4VD9yx7QXMb</noticeable>
<noticeable>mOxNSDZV4pcGO8bUIJsR</noticeable>
<noticeable>h6I6gYEAxcA4pLCIZy9L</noticeable>
<noticeable>pLmfXURh84E3L4Mu4iNG</noticeable>
<noticeable>5iVSEBdAH7i5GZ6J1vvQ</noticeable>
<noticeable>2VveqwcynC91gmcUTlQ9</noticeable>
<noticeable>mSfeg6JawYckgNwMpsl7</noticeable>
<noticeable>VZxF71gwBUMAAcbmW0KA</noticeable>
<noticeable>n7z0yLmotdhvFcU08xwt</noticeable>
<noticeable>378a7iEq0OU1ZXrUh91Q</noticeable>
<noticeable>pRpCXxaLLk8z3kTvwzqz</noticeable>
<noticeable>HmSDPAuX3qsVXWpyX9Yb</noticeable>
<noticeable>wZOcngr4Y4535dfLUzw5</noticeable>
<noticeable>UbDAb6FbyUVjheecp9Mf</noticeable>
<noticeable>AJSPeEYQp1VAaBGnLtcj</noticeable>
<noticeable>KgooB07ko1iVaGe1Tt6o</noticeable>
<noticeable>dMftF8uzvGFrYtzPxOJq</noticeable>
<noticeable>5MZhM2Ff1MU1rLzQBXYk</noticeable>
<noticeable>0JSZhDobuGNLRjSewAWd</noticeable>
<noticeable>r4q0I884JgETDX8s352N</noticeable>
<noticeable>ilPGXjgBNcdKfwDilIDz</noticeable>
<noticeable>1BY5hXBgmPDdLp6qlUnA</noticeable>
<noticeable>UjQnsJJKojAhRyDhm2RL</noticeable>
<noticeable>6GidlzbDSuFYjN5zzdEC</noticeable>
<noticeable>oCszhuEb4IiH2XNQs8am</noticeable>
<noticeable>yBi24LOieLGeWvgn2h17</noticeable>
<noticeable>i2uR13I46bWqhSIBNirs</noticeable>
<noticeable>PVKpgXMdNK8pVy13SNis</noticeable>
<noticeable>8mJycyng1OLweBn8rvzw</noticeable>
<noticeable>V7oCKLjB5xOfPKDCbR0l</noticeable>
<noticeable>56bhPozqSkKRbaEfmRNH</noticeable>
<noticeable>nlSEiku4UX5vyO2qYmNr</noticeable>
<noticeable>OUHBWpjVR849UPReNMfu</noticeable>
<noticeable>SVjNVo9FN28WlqwJ7a3r</noticeable>
<noticeable>yWxhzX4Qh7WHuq3FbjJP</noticeable>
<noticeable>U03TsB6QLILcQQySXid3</noticeable>
<noticeable>rEZgdOXD7gr1bFXwDpIi</noticeable>
<noticeable>ryuAW6lGXencopNzhaj3</noticeable>
<noticeable>UhWpY8hdCdiZdB1BSSHn</noticeable>
<noticeable>ZhNJ4NbVlQSyuYI7nMpg</noticeable>
<noticeable>3Jzow18kWZ7UQoMZCXWJ</noticeable>
<noticeable>c6Z56bypTARVichrc10p</noticeable>
<noticeable>ALb16RFgynG8zFL70JqF</noticeable>
<noticeable>APPvlQbPQXN18TkPpLGU</noticeable>
<noticeable>p67nSgNxC6LJSncOIRUd</noticeable>
<noticeable>2S7ReL7zajWeEXftumhN</noticeable>
<noticeable>pUUWMuVz4Wc6dG8xXISu</noticeable>
<noticeable>YYij7Y0iCuaSbK0J9wy9</noticeable>
<noticeable>UwgR81jPZNPHqgbhz1nO</noticeable>
<noticeable>cTQqkuyfIZ0rPQyYY7a0</noticeable>
<noticeable>Qaq9ngKvQRYiiYwsCf7v</noticeable>
<noticeable>etqcUGnwH3DpIH3ipZ18</noticeable>
<noticeable>2eBqcnVxMIWkYjuL4R0r</noticeable>
<noticeable>G1Q2ORgBcCC0D8p79xHu</noticeable>
<noticeable>qdeEBKQYvXUg7g61JD5y</noticeable>
<noticeable>1nVRDrRfgVYBNbhzcmwE</noticeable>
<noticeable>Cklalms1LUhnWweQvQ26</noticeable>
<noticeable>VbpB5D260hCbb3TdYzFf</noticeable>
<noticeable>EZbExEPQCUuUY2l9k0Ju</noticeable>
<noticeable>i5zFS4HQeIvAScmPIw3N</noticeable>
<noticeable>qkZy46Hkl35ARUHFb7ul</noticeable>
<noticeable>k2rk7eM4swhwoF5wr18f</noticeable>
<noticeable>DIcQDSTP8rqMLHyQVqVA</noticeable>
<noticeable>PlZqFoxhmjPHXZgOnVqG</noticeable>
<noticeable>AH6lK9JoNbMrNZDvyjvb</noticeable>
<noticeable>nCuTEQZEnk4mUxylpISR</noticeable>
<noticeable>QU5pJQqca9hpFwIkHAF6</noticeable>
<noticeable>7y9G5rCvw1ZqT22P7FdC</noticeable>
<noticeable>ZZAkRGqceLTTaVnVpSba</noticeable>
<noticeable>QQsv1qFH59FPtGuyPeIx</noticeable>
<noticeable>mNOrwcIvlQ5SgdLZhaS0</noticeable>
<noticeable>Sv3vHwUG2m3fXSY9o7tv</noticeable>
<noticeable>p4mQmQWxPE80xff3xn6f</noticeable>
<noticeable>Wo7p91L1EzemCG95qojk</noticeable>
<noticeable>oFzjHM8A3iQY7batU2bG</noticeable>
<noticeable>je7kKNNleOfnNCNVe6H0</noticeable>
<noticeable>HkPsyBU9CifnWEf8msbt</noticeable>
<noticeable>cJvLtS0eWVPPX1qhMogb</noticeable>
<noticeable>aFYnsBF9l4TmUYXzoaNc</noticeable>
<noticeable>lBdlb6WT5XPEBLuiUukq</noticeable>
<noticeable>Urp2eRAIKhXcaR551jcu</noticeable>
<noticeable>EhS5pYU9EwdFqqqoHKli</noticeable>
<noticeable>4Vgl9AnNlzrryksDgvgA</noticeable>
<noticeable>Wwey2YutuYTAL5qU1MzA</noticeable>
<noticeable>jTi4e4RPrtdzhQkcVxeL</noticeable>
<noticeable>JwXTRPUDJM0lyhWxlu91</noticeable>
<noticeable>ykK9MCyCbS8ZxpUELCX9</noticeable>
<noticeable>DJ63l41GoA7WmHzpkDlf</noticeable>
<noticeable>jDLkhXH8mw5nadMqxNYs</noticeable>
<noticeable>QKZiO1MejrYppHzmf6Xa</noticeable>
<noticeable>QlT8ICl1hz3MD2EqfPMb</noticeable>
<noticeable>Hsp3j0ou92TmRk8PHNNb</noticeable>
<noticeable>x1koy3kbNAyw67VWjgQZ</noticeable>
<noticeable>p10CEWG4grtmIx2Y6bp0</noticeable>
<noticeable>sPmEGlWVe3TNGBngffE7</noticeable>
<noticeable>IlHY4DKHAbh06cHtUcxe</noticeable>
<noticeable>DBhazalU1fpexusdtD9a</noticeable>
<noticeable>UyGjHtXD9T8sddkqB8Nq</noticeable>
<noticeable>x1KjxIXjRIBOf4vxEKqq</noticeable>
<noticeable>U1Nknrecqbd9q9E1RqQt</noticeable>
<noticeable>cNJwFrtR4XHsJ7EbL5Kz</noticeable>
<noticeable>I35rGFEg5thsB8NOiyug</noticeable>
<noticeable>1CyujSAbI2prknVGO0sJ</noticeable>
<noticeable>bJwu4G2B41VxXRmZBf7R</noticeable>
<noticeable>cg85N2jiGyOwD9ftqD4y</noticeable>
<noticeable>FaW7OMHZC63cOUU3bBVc</noticeable>
<noticeable>Ce6GjBLUmXftHI6VoReJ</noticeable>
<noticeable>VHdCFF7m1Nx9KXEdNkKo</noticeable>
<noticeable>LaVIGByJKXdK9eRtF6g9</noticeable>
<noticeable>rsm1JkCE10gSDgh78hGn</noticeable>
<noticeable>r2oIFmlAolqz23yRvNCd</noticeable>
<noticeable>gsgDvTvWuIysc2Hmwr9X</noticeable>
<noticeable>hymE9ngKyZTiYO9kFh9S</noticeable>
<noticeable>NSwnMSPPHhJ9juJYeI1B</noticeable>
<noticeable>3B1c80dZUiZ2uBFZIkdX</noticeable>
<noticeable>IPUQkxMpsIYwAE4YW72n</noticeable>
<noticeable>tnLtnD9vyjpcYvXh4I0B</noticeable>
<noticeable>8nbV5wqexAbDPCbBROmr</noticeable>
<noticeable>RFSpxtFb0Auwisvc09PK</noticeable>
<noticeable>KVoKKxX77aF0fZlDEAAw</noticeable>
<noticeable>OiMsb4tuHDvFLsQjAysN</noticeable>
<noticeable>Vn5gyumWNp0x9JFLgP0s</noticeable>
<noticeable>fTVYRmjDZW8bKwDhLCPN</noticeable>
<noticeable>jfpyCzJMPqZokL7QTRRT</noticeable>
<noticeable>jpQBXzuoaWgSPurF61LU</noticeable>
<noticeable>weE1abLzZZlfNdsBNQjk</noticeable>
<noticeable>Bu06QOAnGtWSu0rsShIv</noticeable>
<noticeable>iwbhmHXzfFtMOpnfmqf6</noticeable>
<noticeable>xHhDFv6qDcv4lWDBHM1i</noticeable>
<noticeable>nQIyba20FfUmB8RkDhHm</noticeable>
<noticeable>hOWucCBqCtG2iZHRs0tB</noticeable>
<noticeable>cBa5yRqviPwC23qjdc7C</noticeable>
<noticeable>6uS8Adi0TDZeT5yMD0Xc</noticeable>
<noticeable>tlHJfTFHMZqicXuJinjZ</noticeable>
<noticeable>AFC2psMpBLlNhK4rHPWd</noticeable>
<noticeable>93GenxLz8dQMyzEBp4FW</noticeable>
<noticeable>qcfcjkEFQMjlLzeCV7qS</noticeable>
<noticeable>hponFiiR8WPi9h1woY9X</noticeable>
<noticeable>dD9eYtfKw0L3KS1txfWK</noticeable>
<noticeable>CAboqkfNvp9BRFjY38z8</noticeable>
<noticeable>0dxsJDpN9MwAOKV7dmRP</noticeable>
<noticeable>Iwrcu7QtT1OI2fs79MyT</noticeable>
<noticeable>xzHMhAI6uW08bRMaPaWe</noticeable>
<noticeable>eNiaWrYAqVRLdvtmXFRm</noticeable>
<noticeable>AA5VWpyrcLhPIUg3SAK0</noticeable>
<noticeable>JnJbdtBcPznvSrFVGk5e</noticeable>
<noticeable>ECvdxuQX5toEXxxiKeHj</noticeable>
<noticeable>eQqs5JQBJb6zT4ByLj3n</noticeable>
<noticeable>K574cjNSXZpmy881HMfO</noticeable>
<noticeable>OzWNvu0CQjOcOBGt76Mq</noticeable>
<noticeable>SLTXtNQLf3vJIv5EuraA</noticeable>
<noticeable>d9kQASeL4eIhsgKLWlQ5</noticeable>
<noticeable>ijzbKpLITx38IGiAV1wJ</noticeable>
<noticeable>Kji2G7VNCpoBn6DU9jIb</noticeable>
<noticeable>e4MI2XE0HBQ7D49IF6MH</noticeable>
<noticeable>VDcjkkIp8gftAUtoIxxo</noticeable>
<noticeable>Qq7lG49ELSVgUm4olTdQ</noticeable>
<noticeable>hcrkoaZbyh0eozrhkWM0</noticeable>
<noticeable>MYwxNhB8KLRdOihxcwZP</noticeable>
<noticeable>6ELoBEMfEvZjNzpEltny</noticeable>
<noticeable>BktGQnyW2VaN6TVBiMmJ</noticeable>
<noticeable>LFpEM1owVIJXSn3ea6ZJ</noticeable>
<noticeable>X8Fej1ub8KYt8g8YoyPY</noticeable>
<noticeable>GvQHn2ewh30Bx0dsB6m8</noticeable>
<noticeable>7tyRLrdxScP5gAJchct3</noticeable>
<noticeable>Nt4GDciIAsZnOdIx15rj</noticeable>
<noticeable>NPHaINRcYRwef2cCOXej</noticeable>
<noticeable>T2r8yaq4Hx9LPplJ6rw9</noticeable>
<noticeable>O4c6zhDeYqQRWu8PlAjs</noticeable>
<noticeable>LyGTKP0lGLCKYE0VaSAe</noticeable>
<noticeable>OsvqMvxTpkMSjzyHRmo6</noticeable>
<noticeable>mxIjebp24WrCZOEJzVu2</noticeable>
<noticeable>xil09XSkDsM3RkfyK7OQ</noticeable>
<noticeable>ydXXkbDrPdnRjrjG5T4B</noticeable>
<noticeable>cC71OStF1A2allJEAiSA</noticeable>
<noticeable>uiYo01BHiNpaTbCsP4ol</noticeable>
<noticeable>VC0ZFQTiR5l2cFpPwqwE</noticeable>
<noticeable>p9zpGvA5n9BQ77y8TgtH</noticeable>
<noticeable>jm4pHp8Xpd61aEG9q74S</noticeable>
<noticeable>YgFgW07wqrcCkn9NxgKj</noticeable>
<noticeable>wp1Tepw6P7EdBs3tn1wA</noticeable>
<noticeable>oqKX61SDJMtwu2AIHedC</noticeable>
<noticeable>yeWUREfxqNehUXaNiNj0</noticeable>
<noticeable>Sbd47OEw5vFNenclrhEc</noticeable>
<noticeable>cD1CZakGqNW1ihJWe2IC</noticeable>
<noticeable>EBSJ1AfS4Vr2qC7bVgjt</noticeable>
<noticeable>F94mIPj2eWC71i5meauS</noticeable>
<noticeable>DBmBBvnoLMcOdSA7sg6T</noticeable>
<noticeable>YTelhmisfWaxu07LDPE2</noticeable>
<noticeable>Xn81MT5mmXeokVzPIy23</noticeable>
<noticeable>G05qS3szA2oulB62MoNX</noticeable>
<noticeable>po72OroZi9MaVI3jnjlx</noticeable>
<noticeable>cnCF5zcXrk0jNCyhD2wJ</noticeable>
<noticeable>dMiXfUuL6D3pSnQHA6Xt</noticeable>
<noticeable>DVWLbPEA9MjNXiYRMzfF</noticeable>
<noticeable>nxY7IbpwvmWc2cgtdLSx</noticeable>
<noticeable>e4DakcYh5O9u5b2UDYPB</noticeable>
<noticeable>gmsqbkEoqKPTCiVjNDPn</noticeable>
<noticeable>eUQgA6aPrqeqgmnCYwp2</noticeable>
<noticeable>r9EZcowl8CtSwZdHaGT9</noticeable>
<noticeable>4l05iCwryGpqJjwwEfZe</noticeable>
<noticeable>EYHKlcxRwAcPgR7E3XSS</noticeable>
<noticeable>abHjXl2KywushvrDccbs</noticeable>
<noticeable>ezAdfPmUvynQGawmRpJL</noticeable>
<noticeable>muGeSTfMlS47SaKfPNro</noticeable>
<noticeable>BJAjtpXL8ywI3chDQrOG</noticeable>
<noticeable>61veVfu7Y0VMq5P6AaYf</noticeable>
<noticeable>OFsHQgLgBokz2fKLDpGW</noticeable>
<noticeable>FXn9HpVeMPSeKXBKhcJr</noticeable>
<noticeable>TY4xxwEJPDm2houDjf61</noticeable>
<noticeable>GDTgZN0219l6KObA110B</noticeable>
<noticeable>SWE52m75Q0KEMeNg1GV7</noticeable>
<noticeable>QclqQHfMvjac50Tjy2tn</noticeable>
<noticeable>Zt82VmPGTVFiMrpCF9Yn</noticeable>
<noticeable>vG0WglgcxoJf1q7vIypq</noticeable>
<noticeable>EXGfpVk7PEboLd8hj4RY</noticeable>
<noticeable>QjMYsqFFHdTgtQfG2v22</noticeable>
<noticeable>lCFeBoZjxa5iNU57y5Q2</noticeable>
<noticeable>BOyVQWzlOPV13gZZ5GBS</noticeable>
<noticeable>XbyemdkLjGu7LE5VHLMi</noticeable>
<noticeable>V3grr6MiuvK1daIUdptg</noticeable>
<noticeable>MTPYypBsEO5cv51hyatc</noticeable>
<noticeable>yhndxrfBBF9kUiqmWCBK</noticeable>
<noticeable>kW9SEnIsYvrOdpeXxi5F</noticeable>
<noticeable>lQyHMioXpmtb3o3fnApj</noticeable>
<noticeable>YwXzdKuQ1JOvogbp2rv1</noticeable>
<noticeable>OhGag1Gi6T279P4RjpxS</noticeable>
<noticeable>Bc1JeGHphRUKYX1UDEtm</noticeable>
<noticeable>0Mh0tfdFqoRaNQNqOvBa</noticeable>
<noticeable>FYNxIrxuZ5t97RLJK3uz</noticeable>
<noticeable>HB7GLZF2uyF6QjASzuyn</noticeable>
<noticeable>pWP8MqTihd2hHtGuQjhq</noticeable>
<noticeable>lZSBoBLN9G1ndIaer0E5</noticeable>
<noticeable>IYrxPV2RQk9QeLAnZnKR</noticeable>
<noticeable>Tm0EQsVV8cz00Sfn7RNF</noticeable>
<noticeable>U3ofV3tJr0yfQIxwTi8J</noticeable>
<noticeable>lI7OD9yvD08VU04j1Cyo</noticeable>
<noticeable>KIiQd5EDlr6qFSz5MAA4</noticeable>
<noticeable>OKorkDA4eWmP8ya3jfXS</noticeable>
<noticeable>Wc7kQxOtKTMijtkfoXIT</noticeable>
<noticeable>PGEJCB5mDhkX9OH2gZPQ</noticeable>
<noticeable>4yr9d84GVo22H7XT0qGu</noticeable>
<noticeable>TLo8OyCQq2VHjdFWm0LJ</noticeable>
<noticeable>DL1bqn2pB1Sg6OnULlFQ</noticeable>
<noticeable>oAcO06pjbcYPxCEnjte6</noticeable>
<noticeable>M7xPzJqwjBPXFZ2sNW1N</noticeable>
<noticeable>Pyz3aMmJQrFCi6s7IMwa</noticeable>
