{"uclassify":"AMPeNFhO1yTD"}
{"uclassify":"RO1vqu2c5i7U"}
{"uclassify":"qmDB8f1omIDp"}
{"uclassify":"KUEO5aKG7rqh"}
{"uclassify":"ljguWZfwgDti"}
{"uclassify":"n6qMDsfVCLi6"}
{"uclassify":"NqNLUal4KS5o"}
{"uclassify":"f9T0jGT7ilQ4"}
{"uclassify":"fODmy0d9XPIN"}
{"uclassify":"orGKnbeQVm5i"}
{"uclassify":"teI90iGcYv5D"}
{"uclassify":"MFCRG2NAF9Nu"}
{"uclassify":"gLCnr6cXT7Ds"}
{"uclassify":"zgBbNsfo9mVk"}
{"uclassify":"NJnfBnbZ8mTu"}
{"uclassify":"z8stWLVmXjGr"}
{"uclassify":"PQNWSq9xAGAb"}
{"uclassify":"HHnmQkfO2BZT"}
{"uclassify":"RfJ4ck1J4aF0"}
{"uclassify":"XvBjhnBNFFtE"}
{"uclassify":"vZ0JyBNIY4bc"}
{"uclassify":"oslLE34TszOR"}
{"uclassify":"Cp68jyuecGXV"}
{"uclassify":"ECUEH0PlEMRk"}
{"uclassify":"UCcMLTYe0Mc6"}
{"uclassify":"rYY5dDkofFa5"}
{"uclassify":"WZBNmvtrvV2K"}
{"uclassify":"8HiDLozPvODq"}
{"uclassify":"yx7vIgGiQSDW"}
{"uclassify":"M0Akw1JLd39K"}
{"uclassify":"rMynWoEuCAqv"}
{"uclassify":"Cdg7QchWmxi2"}
{"uclassify":"1MdXl4R7JYKn"}
{"uclassify":"Froom2okGcTL"}
{"uclassify":"DdY2rpMSwUGP"}
{"uclassify":"qxlfdKnXzwH2"}
{"uclassify":"xU9iLIy0aJjX"}
{"uclassify":"ZrjOOAAGlqar"}
{"uclassify":"Az3DyYQNENiL"}
{"uclassify":"zcpRy41iQasq"}
{"uclassify":"E8sLecSO6vl0"}
{"uclassify":"qs1WkUnRG0Eg"}
{"uclassify":"KSKarsu515fh"}
{"uclassify":"mMzaDDUaD4rE"}
{"uclassify":"5FfcRWJum6kx"}
{"uclassify":"TrZR0f66XWk6"}
{"uclassify":"VqyBdZ0Gcv0W"}
{"uclassify":"ecuH2SYUaeDK"}
{"uclassify":"L37P99nML8oR"}
{"uclassify":"f2bKlEdIB3OL"}
{"uclassify":"HIGRAel0emxk"}
{"uclassify":"SSbw7vEHBwnN"}
{"uclassify":"nLkmhLlP2yVe"}
{"uclassify":"kIPipliAjvwA"}
{"uclassify":"svrPdWsAO6oL"}
{"uclassify":"HLfdq9Kem3h2"}
{"uclassify":"XqtOs5ypvqhO"}
{"uclassify":"AUmWMhBEb924"}
{"uclassify":"cDsqn66EwzTp"}
{"uclassify":"tbF3AnrKpAav"}
{"uclassify":"uc3S8gVccc5A"}
{"uclassify":"qSV68XIamnZq"}
{"uclassify":"nBSkl1G5twt0"}
{"uclassify":"lOdAwDoN9zr2"}
{"uclassify":"6dfOHA47uKp8"}
{"uclassify":"YEZ6pIygeYAK"}
{"uclassify":"K7AFx8al9Y7l"}
{"uclassify":"qYw8fAplOhUM"}
{"uclassify":"UJFId5tVB23h"}
{"uclassify":"XaxZhuUCRVin"}
{"uclassify":"qLoLFEhK1sqD"}
{"uclassify":"g7jIArRLoDeG"}
{"uclassify":"6SarEDdBcOfY"}
{"uclassify":"vJ7RVpzA4Cch"}
{"uclassify":"lXTkSqYdC59Y"}
{"uclassify":"mIOfmXKSdK2J"}
{"uclassify":"IIeOtVwIhcV9"}
{"uclassify":"jkunwm8fzrz1"}
{"uclassify":"QHdvMQYc4YEQ"}
{"uclassify":"ErCZ0R4h0ODZ"}
{"uclassify":"P0270AxNS54Q"}
{"uclassify":"0QGwdCkOsRKC"}
{"uclassify":"80iWiLflPL6Z"}
{"uclassify":"OTtHqzWw20Ay"}
{"uclassify":"PgMe25CzuOUc"}
{"uclassify":"QrQuCyiEjWcc"}
{"uclassify":"TclweuXy7x1U"}
{"uclassify":"AfIQRjcOr2YA"}
{"uclassify":"caq2YdHavc8a"}
{"uclassify":"RVh77mTTaL0i"}
{"uclassify":"agxIfpMPkI9E"}
{"uclassify":"J339dYQx1UHm"}
{"uclassify":"OhLrka16LG9C"}
{"uclassify":"cFJPECxmT1MX"}
{"uclassify":"BIu3Yu5QAktd"}
{"uclassify":"5tTSJPu1PYQC"}
{"uclassify":"XDn37TDpJ2gv"}
{"uclassify":"98m7ydNMnRut"}
{"uclassify":"aEigcRPSvKFK"}
{"uclassify":"BQCvYNCkwJNW"}
{"uclassify":"5BE6GpCQoqR5"}
{"uclassify":"fKMfLn9HjX8u"}
{"uclassify":"xIok3uq9l2VM"}
{"uclassify":"JEO9vdQrVaLp"}
{"uclassify":"0f9W4Lyjswnm"}
{"uclassify":"y9SPstDaIzPQ"}
{"uclassify":"3XgPRxF0YdGo"}
{"uclassify":"JsyzWv0zuTKz"}
{"uclassify":"SGTIDJwqs4qO"}
{"uclassify":"KgSD5G8fE9Mt"}
{"uclassify":"HL0UpLi31deo"}
{"uclassify":"EUwE8aPjOPOz"}
{"uclassify":"k3kFHFPmzopn"}
{"uclassify":"OdrhgCza80GJ"}
{"uclassify":"ZYulb91h1oln"}
{"uclassify":"NTGZ7BWj768R"}
{"uclassify":"40Q388XitnUw"}
{"uclassify":"77FZAQ8YtRDl"}
{"uclassify":"ZWp9l82aRtLr"}
{"uclassify":"pYF30p44kkY4"}
{"uclassify":"3Qmfq9V8JqBW"}
{"uclassify":"3u9hPJ9uLgCe"}
{"uclassify":"RrANtbSj7i7Q"}
{"uclassify":"noUuMOvZhy3m"}
{"uclassify":"krFh65ndh9aN"}
{"uclassify":"hSk0rubpdAEe"}
{"uclassify":"tHAuWuzH9SkK"}
{"uclassify":"tuWOR99rpOoe"}
{"uclassify":"ERd6y1be0YJL"}
{"uclassify":"iunVyH90O3tO"}
{"uclassify":"Pqijcyjg4P1B"}
{"uclassify":"3piHWL0usFxO"}
{"uclassify":"MD1zyshVKWPA"}
{"uclassify":"usYEGyw8aX9o"}
{"uclassify":"2w3DHhQYgKn6"}
{"uclassify":"3WkCPOejSyNq"}
{"uclassify":"xoNrwLpbiR8u"}
{"uclassify":"nQwRA4kRbxCh"}
{"uclassify":"Z7MuxPodq4jL"}
{"uclassify":"udBbsiDqPUhZ"}
{"uclassify":"8wSieCEV10KL"}
{"uclassify":"ObqANe9kocIg"}
{"uclassify":"2axomhFC5rsz"}
{"uclassify":"ZC7uF58AUqvM"}
{"uclassify":"AIv2ObVJqbEJ"}
{"uclassify":"nnWg4IDQwv67"}
{"uclassify":"JCZttgJ2SmGp"}
{"uclassify":"EiJaikKeigS0"}
{"uclassify":"aOA82TfABCwA"}
{"uclassify":"Tnn8EWFiE16R"}
{"uclassify":"QaqYHHDXBGHZ"}
{"uclassify":"gqfZQ6sKaeFN"}
{"uclassify":"3zxFcGioLCsq"}
{"uclassify":"vTSr9SgvnhO1"}
{"uclassify":"LBdHiogCRUEl"}
{"uclassify":"H177kcfdySZM"}
{"uclassify":"VoQwzjwPCWVu"}
{"uclassify":"bWszvLtZwoHE"}
{"uclassify":"Yv1KTAGJxIq3"}
{"uclassify":"AX6tSu3fgVh0"}
{"uclassify":"o60LhjreWIrs"}
{"uclassify":"841wf8LdmxTB"}
{"uclassify":"j2Ywtaj7AgXZ"}
{"uclassify":"8s1Db9LKzEea"}
{"uclassify":"mhDAywm8rEod"}
{"uclassify":"9ID76iDszUyx"}
{"uclassify":"2e9CpnoXcujX"}
{"uclassify":"7t7913xHoO0D"}
{"uclassify":"EviBbVRlGTJl"}
{"uclassify":"GegQ6FzJsOym"}
{"uclassify":"G37M8ziM1QgC"}
{"uclassify":"57HpyEBJNiMD"}
{"uclassify":"oYL0s78kcEaA"}
{"uclassify":"MvY4fLSsKIu7"}
{"uclassify":"gBHpkKqYonIh"}
{"uclassify":"sNfx6A6IaXoI"}
{"uclassify":"Nyql6NN9wn8z"}
{"uclassify":"SSxmiFaxtNY1"}
{"uclassify":"f23U1HuTf3aM"}
{"uclassify":"zdsOWkxTjoKl"}
{"uclassify":"aNAxpr0XOm9v"}
{"uclassify":"JHm5Jj7P0Ljx"}
{"uclassify":"SqliiAG01Hpl"}
{"uclassify":"VmeB5sX1CMhA"}
{"uclassify":"w8ANpgnLFoqS"}
{"uclassify":"PVK0PtoNWBGt"}
{"uclassify":"kxkDFNO67qk9"}
{"uclassify":"5qydeusrQqpi"}
{"uclassify":"9XtPTNq1JDzN"}
{"uclassify":"CJ5lOCPBROB3"}
{"uclassify":"OscrMaMATQHX"}
{"uclassify":"IY2URLm6yZAB"}
{"uclassify":"FjzesU4ptLhL"}
{"uclassify":"HzYZFq8yF6Tv"}
{"uclassify":"e3k94WeKzWMQ"}
{"uclassify":"Q3YAe7wBfISO"}
{"uclassify":"PgVVr2Ado5DK"}
{"uclassify":"JhMntXdwZUTr"}
{"uclassify":"48Uj7H4ZrUx4"}
{"uclassify":"pCHgWKAdJPxh"}
{"uclassify":"odWuz1VhtK4a"}
{"uclassify":"1aIuXCrQtVqi"}
{"uclassify":"U9eNMCqdCpi4"}
{"uclassify":"UtRVe4WtJv4x"}
{"uclassify":"9yDZ5eP15Scl"}
{"uclassify":"iuuA3c9myFDv"}
{"uclassify":"mKXEilaGkJ1p"}
{"uclassify":"S13Edw8E9RH3"}
{"uclassify":"HPudmlhRb3bm"}
{"uclassify":"ceXl7gx6dT2u"}
{"uclassify":"qDwdCxc9F5Pi"}
{"uclassify":"S6a7HlvbFbmM"}
{"uclassify":"btd4eWi1m5Qs"}
{"uclassify":"96dUUZlZyOA4"}
{"uclassify":"qsK88LGnKecZ"}
{"uclassify":"2q3xCBtvWxxR"}
{"uclassify":"wvlfW0ATUvqv"}
{"uclassify":"tVyqO8YteJ54"}
{"uclassify":"rOOMldwrYPlO"}
{"uclassify":"Y30Snm7f3UXg"}
{"uclassify":"qvcrobqmUMgE"}
{"uclassify":"nn07QQwBACvP"}
{"uclassify":"ydCgJjwISHT6"}
{"uclassify":"fdiLfMUva3N1"}
{"uclassify":"IlbasUsq8u22"}
{"uclassify":"nCPVba9eP6B8"}
{"uclassify":"KevStdOfYJ7R"}
{"uclassify":"0gIm5T8JqYCN"}
{"uclassify":"L467gTbBziZJ"}
{"uclassify":"HD0APVheI2UM"}
{"uclassify":"NsMVdp4ZbcsB"}
{"uclassify":"M0guylJrSYgw"}
{"uclassify":"51przPFHx4M4"}
{"uclassify":"oRxpw4sOJTue"}
{"uclassify":"zCdzs96Kki59"}
{"uclassify":"Qgztksn3OOQO"}
{"uclassify":"K8LNhsVQjCh9"}
{"uclassify":"DkyPTM378g75"}
{"uclassify":"b98TnX4DdGb5"}
{"uclassify":"eE1woRr1SME8"}
{"uclassify":"OwBpiMS4sYrW"}
{"uclassify":"Zct2ACHzN8I9"}
{"uclassify":"ywiPqEaIWah1"}
{"uclassify":"G9JrV1rpiPSE"}
{"uclassify":"157yJJ0PfxgE"}
{"uclassify":"A3xgHWiLvcYT"}
{"uclassify":"1Lpf95AjKe1z"}
{"uclassify":"piFCbrYxiZwP"}
{"uclassify":"xeMSzF6j2Yca"}
{"uclassify":"s42ekQNuTmCi"}
{"uclassify":"Uu156bErr8dY"}
{"uclassify":"3Si5AmhI3QxO"}
{"uclassify":"qyv8OfNkUG2Z"}
{"uclassify":"uwpM8bbLADLR"}
{"uclassify":"wxnTPh2bdreR"}
{"uclassify":"URJEs7VxWH3n"}
{"uclassify":"8PGRbmEYVsWd"}
{"uclassify":"AhT6LK6KCKb6"}
{"uclassify":"FQjgP6EFTjJV"}
{"uclassify":"SqcZYBiIJfuy"}
{"uclassify":"tgS53EkonVDU"}
{"uclassify":"lzfUAklJUCC8"}
{"uclassify":"I7lF7qSun5Ar"}
{"uclassify":"v0HfhReywDOV"}
{"uclassify":"ozdspknhwMca"}
{"uclassify":"P6O4OpxuZZLb"}
{"uclassify":"PzPCWhpX955a"}
{"uclassify":"MvIyNAo7UtJq"}
{"uclassify":"gZbbaXMkTmEl"}
{"uclassify":"Sy0Izd15UAhd"}
{"uclassify":"DZJM7m0J8pvN"}
{"uclassify":"51lCM0kE60VK"}
{"uclassify":"bu892RQPMcBK"}
{"uclassify":"pqnvNTLpuue6"}
{"uclassify":"UmXmH2i0YQMe"}
{"uclassify":"rJCGbQI4zzRY"}
{"uclassify":"JaFmf3peal66"}
{"uclassify":"nqXEebn7CqBg"}
{"uclassify":"Ih6cG6RcW71h"}
{"uclassify":"C31zZzbOfQBz"}
{"uclassify":"kkL6GuAMG5Rc"}
{"uclassify":"12IcpRX9BbVC"}
{"uclassify":"5Ge8podoBZ1I"}
{"uclassify":"WVMfe5enrWBm"}
{"uclassify":"FyPIt8YASFw3"}
{"uclassify":"tBcTn7BUH4V7"}
{"uclassify":"hWllFgN4uN5q"}
{"uclassify":"H5jwCU8sA7ew"}
{"uclassify":"BPZpG3wbdycC"}
{"uclassify":"SZqDkrPU7les"}
{"uclassify":"QECySb5UANOA"}
{"uclassify":"OLTgEYwOKOHy"}
{"uclassify":"O1hryy7sszI5"}
{"uclassify":"fU9FcEt0ojl8"}
{"uclassify":"bHwSaCNApUHs"}
{"uclassify":"gRQvlA92RdpJ"}
{"uclassify":"ohJT9e0wlAEL"}
{"uclassify":"LVSikLfMAsk1"}
{"uclassify":"WYPbOnrHJHpj"}
{"uclassify":"8vPifPNUAweC"}
{"uclassify":"npD5EH6fEP7S"}
{"uclassify":"nYH002KfyBkB"}
{"uclassify":"sszXQLxVTBDo"}
{"uclassify":"LmhleNBEDfCV"}
{"uclassify":"F7NptRxL3B0s"}
{"uclassify":"jimfjdYn5FRi"}
{"uclassify":"cWLQALFhrZ4e"}
{"uclassify":"lZqPNy2nUSKX"}
{"uclassify":"RA7pw4AZ2aWE"}
{"uclassify":"fgA4OFEBs1vc"}
{"uclassify":"OFwZQ1VkRTqA"}
{"uclassify":"BbdS3JxAzTkb"}
{"uclassify":"umm5hucVKo0o"}
{"uclassify":"sDJenzUVOXsU"}
{"uclassify":"1RhoQHNSYyCe"}
{"uclassify":"sbMnqQ08utks"}
{"uclassify":"wcoQokDE6krX"}
{"uclassify":"hzRbwMuEgMt9"}
{"uclassify":"L7u9p3hds9zB"}
{"uclassify":"tNWscbqvcB2h"}
{"uclassify":"Xz8nIG8buH1I"}
{"uclassify":"B50hSZoV7GZb"}
{"uclassify":"XvL0eXdzcSYk"}
{"uclassify":"2UrVFJLlAdl8"}
{"uclassify":"s8dmxm4qORsZ"}
{"uclassify":"V6pgSB3eZQeu"}
{"uclassify":"UKGoFMN1WmdX"}
{"uclassify":"1iukrVn85f7S"}
{"uclassify":"4ZXjiDMu2FcM"}
{"uclassify":"S079nk1HdcYZ"}
{"uclassify":"Jaf9q5PWKxU4"}
{"uclassify":"wqAwwgSOyX97"}
{"uclassify":"fd8wHNzTbXm9"}
{"uclassify":"OB5OfrgAYyp2"}
{"uclassify":"ppfBG3jAAjkl"}
{"uclassify":"sZ44qdp51YDk"}
{"uclassify":"zduDa2X2UaaO"}
{"uclassify":"iJkla3kjsxMf"}
{"uclassify":"8cr3kcsOGVXq"}
{"uclassify":"aVtr0IJ6zNaC"}
{"uclassify":"H0ndgy4legbk"}
{"uclassify":"78bP2oben9Mi"}
{"uclassify":"Qslwt1zlJNp7"}
{"uclassify":"atLzv5BfzK2c"}
{"uclassify":"7XWmEMSFZFyv"}
{"uclassify":"whUCYtMjYXW3"}
{"uclassify":"JVqk15saGRXB"}
{"uclassify":"x0UMnVlplL3S"}
{"uclassify":"L8Ssjn990shB"}
{"uclassify":"Y7GlKARiDQ5W"}
{"uclassify":"q4wO5gpOTUUV"}
{"uclassify":"xJfbwmtDHeBA"}
{"uclassify":"iBMwhcIrzDJT"}
{"uclassify":"yerDrWuYMOKU"}
{"uclassify":"ktXEstmmabZR"}
{"uclassify":"8UlI1ww55jSM"}
{"uclassify":"RhvFo2MCn6am"}
{"uclassify":"QwVN81KuEoDf"}
{"uclassify":"sfKTj9M6iu1G"}
{"uclassify":"YuGJZQA4GjQq"}
{"uclassify":"L39IZyIWM0xJ"}
{"uclassify":"itPy23MngYFZ"}
{"uclassify":"aRZwaeelitqU"}
{"uclassify":"I5O3sCHs52pn"}
{"uclassify":"AnovUGKTKFP1"}
{"uclassify":"iRku2dPrvHIB"}
{"uclassify":"5UqwBTUQoEWs"}
{"uclassify":"UjjKWse4Cd5I"}
{"uclassify":"frGkVy1xafGL"}
{"uclassify":"G6LL8IK7IAT2"}
{"uclassify":"11S0h4JIGAyG"}
{"uclassify":"RDJc0pPBa9Ye"}
{"uclassify":"gFEAWagyskbV"}
{"uclassify":"Zl7JcBt1WpLJ"}
{"uclassify":"F8MQO5cHPBbc"}
{"uclassify":"vpAX8WkL9Hk0"}
{"uclassify":"hJLq8GvIYJim"}
{"uclassify":"sZYP00Pkx3aM"}
{"uclassify":"UhkTJWi30n0h"}
{"uclassify":"5J1DtIn4rZxQ"}
{"uclassify":"IRQ6cIQHSYvF"}
{"uclassify":"l9RiZ6PhcUys"}
{"uclassify":"egxDsAWOvGpt"}
{"uclassify":"1aiHIUIOTzwj"}
{"uclassify":"mtFt1UqqO1nT"}
{"uclassify":"0ujxX2luBiq0"}
{"uclassify":"jON4zC5m11t4"}
{"uclassify":"sTqo3ZXSw3N2"}
{"uclassify":"kIMEqWLf5TLz"}
{"uclassify":"quzSPNd45yxZ"}
{"uclassify":"psiz7FAGpgik"}
{"uclassify":"UkDvV7vldR4O"}
{"uclassify":"sJdg0S7r0Wdt"}
{"uclassify":"UkWHKNHmybGz"}
{"uclassify":"ztYz9rnwY6iZ"}
{"uclassify":"PfOOWKiaTzgk"}
{"uclassify":"SI73n6EjImYp"}
{"uclassify":"yGRjlY4IhnpK"}
{"uclassify":"uhgVSmn8sJua"}
{"uclassify":"ncD99V4gyNOD"}
{"uclassify":"XbOrvFbHbbLs"}
{"uclassify":"fgJ6vCsJmH3k"}
{"uclassify":"fJSiQC6aMEpt"}
{"uclassify":"i4N5qe6ziMii"}
{"uclassify":"udvj0ojz4G3a"}
{"uclassify":"DqTByTqPR3vt"}
{"uclassify":"Am9XrrPeQigT"}
{"uclassify":"9CsJZQW0N8XO"}
{"uclassify":"mHP1gOYnqXzs"}
{"uclassify":"TZAflYW5PMSR"}
{"uclassify":"mknTy5ZdTMUb"}
{"uclassify":"f7FdoEyR57pL"}
{"uclassify":"qKr3P4r8Scbo"}
{"uclassify":"Cyh6aelg9BgT"}
{"uclassify":"7lFZP4TOjlOC"}
{"uclassify":"lk37Ia9NvE95"}
{"uclassify":"a7yXIW0vQyFy"}
{"uclassify":"zwwQBntSUrXC"}
{"uclassify":"VZig6pLFjOav"}
{"uclassify":"9SDxPQeTjhcr"}
{"uclassify":"VKYeR27o8swc"}
{"uclassify":"qzjQtCofn4Id"}
{"uclassify":"EQ9tXyFIMNsy"}
{"uclassify":"z9zpDMTdGDAK"}
{"uclassify":"UNzEQZVkRqkj"}
{"uclassify":"TnuW19JtxYWa"}
{"uclassify":"NfbfAUbeXful"}
{"uclassify":"cEpSkTeuKQWR"}
{"uclassify":"6ekt9NzsqPbf"}
{"uclassify":"d5KXOObiqOmZ"}
{"uclassify":"Hq4gKWzoHNlM"}
{"uclassify":"U6bpUD81JFj9"}
{"uclassify":"k1RFj2pEyJ8O"}
{"uclassify":"TyB1pG4sBQfj"}
{"uclassify":"TMOeQULhqiOs"}
{"uclassify":"LX3c7tRzbvHk"}
{"uclassify":"eOpYvULYzMxV"}
{"uclassify":"JZI5egE2FOD2"}
{"uclassify":"HKhyItM1Qp7m"}
{"uclassify":"5txlwKYnMpsw"}
{"uclassify":"2Gjjv01EelRc"}
{"uclassify":"i53vg3nG0O0M"}
{"uclassify":"0DvHYNasfW31"}
{"uclassify":"BdoWbvMNgVLA"}
{"uclassify":"lQkOk9fs9tJH"}
{"uclassify":"rV2SA9tsHFQd"}
{"uclassify":"eohfgdegieqs"}
{"uclassify":"e06YoTtPrIIu"}
{"uclassify":"EmUtg9DsxzDR"}
{"uclassify":"sriKQGy6UZNq"}
{"uclassify":"JYKHz2j0OYK6"}
{"uclassify":"IeSqrE7n5lD7"}
{"uclassify":"DheRfMbxovrg"}
{"uclassify":"8fP5HFjMKdat"}
{"uclassify":"zp57C7fDEHXQ"}
{"uclassify":"kur0L2HPwdnM"}
{"uclassify":"aOlH4MigkQxR"}
{"uclassify":"JCjaJmErdalF"}
{"uclassify":"9092fH1CGhXN"}
{"uclassify":"eHneCDcKhum2"}
{"uclassify":"QLfojtCC1yoh"}
{"uclassify":"qLk4eJssIEyU"}
{"uclassify":"DjcC2eMYL89X"}
{"uclassify":"fQE3DBN0GcGX"}
{"uclassify":"SWiBJzvCUvgH"}
{"uclassify":"ANyX7iWcKwNn"}
{"uclassify":"o7A5D909xGUx"}
{"uclassify":"ENXR67dNvG2e"}
{"uclassify":"Bf0YKdMSlJqa"}
{"uclassify":"BJrRCT9s7uuP"}
{"uclassify":"zzRDGs8vR5KE"}
{"uclassify":"v9PXqlEeniGk"}
{"uclassify":"9k0ibAyinA3k"}
{"uclassify":"w8IFlPNEN3dL"}
{"uclassify":"p11rMiTuQchX"}
{"uclassify":"mMO7xK1RagKk"}
{"uclassify":"Hn8xOz7QskER"}
{"uclassify":"oG386H8BAL6V"}
{"uclassify":"mH0EczkNXnfA"}
{"uclassify":"dHr4Kb8SC6Wo"}
{"uclassify":"4OZJua2mn5AB"}
{"uclassify":"QDqbjLzGkQsj"}
{"uclassify":"LjINII9bxOPy"}
{"uclassify":"q84Pp96awz9S"}
{"uclassify":"9xVyddW8HoMZ"}
{"uclassify":"TBjfgVraOrVJ"}
{"uclassify":"bfAy7BSMHMYA"}
{"uclassify":"axWe1YIoag7E"}
{"uclassify":"JJI04hJqXFee"}
{"uclassify":"W0fDSJCTGhqG"}
{"uclassify":"PV09Z13GCbm8"}
{"uclassify":"Q4xWi20cdWvv"}
{"uclassify":"p6DjyvbQHhqS"}
{"uclassify":"vVdrKWMpXQAd"}
{"uclassify":"dFLzJnq5vKjt"}
{"uclassify":"CqrUMd4A6tU6"}
{"uclassify":"2YOtOvWZgJSx"}
{"uclassify":"RRsYovuJb7vF"}
{"uclassify":"82jkGttJjKzd"}
{"uclassify":"PtiecbQPrz0t"}
{"uclassify":"7GKfigktlQV1"}
{"uclassify":"gyulDB6LjRUL"}
{"uclassify":"NzlcSlUKfAbR"}
{"uclassify":"LDn5OO4tfFW5"}
{"uclassify":"8v3pdFQzKnzV"}
{"uclassify":"ufKZEdwaDeql"}
{"uclassify":"tpoukEUgru33"}
{"uclassify":"YcQeHiu2Ni2d"}
{"uclassify":"Qm9X1IaB8YiT"}
{"uclassify":"DHgYVfQ8SRoF"}
{"uclassify":"ga51QMbhzw0U"}
{"uclassify":"fi6z30txsynS"}
{"uclassify":"vMXVuPBcZAhm"}
{"uclassify":"stAnFdWTgBIF"}
{"uclassify":"5ZamWfethMAa"}
{"uclassify":"QH6bhtUdmke3"}
{"uclassify":"hGPnjBKx36P3"}
{"uclassify":"oStY5rnVQCPQ"}
{"uclassify":"AQJ3GLeltKYm"}
{"uclassify":"5iKPGdPolIdt"}
{"uclassify":"I5pXY6KqG4hl"}
{"uclassify":"UDQa7d0jcUDK"}
{"uclassify":"kGvzLJdss8Go"}
{"uclassify":"KBGxQOrQERWb"}
{"uclassify":"KOMFR4rghctf"}
{"uclassify":"FGfXWp0L88qg"}
{"uclassify":"uuiU0U1dUYkm"}
{"uclassify":"YrLhCbHsHVUJ"}
{"uclassify":"5dQY2BAPDOBR"}
{"uclassify":"qQrtrTnZtVKk"}
{"uclassify":"0kXTEUBMl1Ye"}
{"uclassify":"XVWoFiRsmc09"}
{"uclassify":"fnJmfyJD5TAs"}
{"uclassify":"uYKcYeljvh8M"}
{"uclassify":"W5vU4N1W10KX"}
{"uclassify":"6f5DaJvrYYWN"}
{"uclassify":"OeMmVpTTqPrH"}
{"uclassify":"tkl9HGPBfnNi"}
{"uclassify":"a7iIs73U5qXt"}
{"uclassify":"GfSnksVnSOPZ"}
{"uclassify":"3R40u4oLDdz1"}
{"uclassify":"9BtbU3Za8AAC"}
{"uclassify":"hK4KA5T92z27"}
{"uclassify":"1fyOaYDaMoxr"}
{"uclassify":"6wzWZDSq1p48"}
{"uclassify":"ruynb0h5uqsY"}
{"uclassify":"mEyP6RAJV8us"}
{"uclassify":"GKkOCUuRB6US"}
{"uclassify":"0vkxYYy7cqop"}
{"uclassify":"Dim5F7BYY7sR"}
{"uclassify":"sI0PNWXz4zEq"}
{"uclassify":"Tit4fctDSyTM"}
{"uclassify":"NjwHaq7ETN0m"}
{"uclassify":"TiafkFjhNqev"}
{"uclassify":"ntz0iStPkSzY"}
{"uclassify":"WfMfiPXnn06N"}
{"uclassify":"Y4r3P1SJVjZy"}
{"uclassify":"BnbnQr7HyBuU"}
{"uclassify":"Cp31abxGi3bn"}
{"uclassify":"lX9Q249TiPyb"}
{"uclassify":"nWh2B70QdRYG"}
{"uclassify":"AXUsBiLYWw3K"}
{"uclassify":"gTjsR33dGusI"}
{"uclassify":"RvsTCP7CsLgJ"}
{"uclassify":"DxjyNNkPfRBL"}
{"uclassify":"NkCSwMTUeTJW"}
{"uclassify":"oVAnR6n4RM34"}
{"uclassify":"ar70zAq1WWsk"}
{"uclassify":"7PDBmYV6XvuI"}
{"uclassify":"JO62L1UOoYWb"}
{"uclassify":"wjqZASeuXOTo"}
{"uclassify":"GtfJKL6Wpo3A"}
{"uclassify":"HyKIvnUvGynk"}
{"uclassify":"H562ccFh2GNz"}
{"uclassify":"IdUZ6StXrcJt"}
{"uclassify":"m3F0SKqf01Cg"}
{"uclassify":"NX4uYTebDdht"}
{"uclassify":"QZgNtkbuPBii"}
{"uclassify":"SwYBan1Aqj0L"}
{"uclassify":"S7J65OoDmjdg"}
{"uclassify":"qSlphNOlcS6E"}
{"uclassify":"NVaZVg9R01zI"}
{"uclassify":"XsOaVXy1Vkoe"}
{"uclassify":"XN4lohC1XTV4"}
{"uclassify":"8v4yPhdmWsSE"}
{"uclassify":"lL89PyeyKBZG"}
{"uclassify":"KYQBVuKEKHmM"}
{"uclassify":"37xOF6Nkzsjt"}
{"uclassify":"eDOhdPghEXbj"}
{"uclassify":"yEClitqX6N2y"}
{"uclassify":"RW9mGGtIiIP6"}
{"uclassify":"d1UdLy0REedF"}
{"uclassify":"VVd70Gv2GeyT"}
{"uclassify":"QQBmswYCrLM8"}
{"uclassify":"gvvHGXNWqP8C"}
{"uclassify":"98yagZTv07Qy"}
{"uclassify":"ICAZ1NFU5B9w"}
{"uclassify":"5PAVxMZUFjWW"}
{"uclassify":"Hm35nYgyutcJ"}
{"uclassify":"zQ2W8U8yHliI"}
{"uclassify":"2C2964m9zzT5"}
{"uclassify":"vaPgToMO0ehE"}
{"uclassify":"kJJSb1MulcNq"}
{"uclassify":"EVSbOudPcY5w"}
{"uclassify":"H7BpscKG5Dh4"}
{"uclassify":"CMn0pgMe0lAX"}
{"uclassify":"YRX9tD2lpbRk"}
{"uclassify":"RJQhwN12f1zi"}
{"uclassify":"amldFjRYbGEZ"}
{"uclassify":"4vWH4iewffz6"}
{"uclassify":"Ba4Vxq7VpX0P"}
{"uclassify":"0Jd1ZdKgPYDz"}
{"uclassify":"O3dTHpY1GDNI"}
{"uclassify":"XWCOsupB9gQ3"}
{"uclassify":"xRKDTjzdUMMh"}
{"uclassify":"is2NntR396c2"}
{"uclassify":"LioM9PJoFonm"}
{"uclassify":"ftHN70hFJLyA"}
{"uclassify":"NrTg0ebjY1ju"}
{"uclassify":"QGZ4RmUzccUx"}
{"uclassify":"uje7RbddsCwn"}
{"uclassify":"58lak9WFT0eF"}
{"uclassify":"MWf8J07ieZ5W"}
{"uclassify":"75AsLg1X310Y"}
{"uclassify":"KroRrwV0lsZC"}
{"uclassify":"aczxJCixVOGi"}
{"uclassify":"USxdKoP4LQLC"}
{"uclassify":"iWaoVBT0uNsx"}
{"uclassify":"YwhhaRogRkew"}
{"uclassify":"wiUJsX38w4zf"}
{"uclassify":"P9xvijHXsGgG"}
{"uclassify":"3PGZDO0zJXUV"}
{"uclassify":"pgbSfGIIiYnD"}
{"uclassify":"SnglpAadxTfo"}
{"uclassify":"5Si1QrEOq46w"}
{"uclassify":"MJvHaLGsztbX"}
{"uclassify":"2z4Cb6kF7lip"}
{"uclassify":"197sIxkkliPy"}
{"uclassify":"wux8WtFqpjj8"}
{"uclassify":"EFEk3azrLzgq"}
{"uclassify":"Ghy86wO7lSg4"}
{"uclassify":"ECtW4SD4MJRL"}
{"uclassify":"p14hdDzsAzNn"}
{"uclassify":"tD3vuEbYKT30"}
{"uclassify":"15tHXDBDfhMO"}
{"uclassify":"PAFTqIvqIY1Q"}
{"uclassify":"42HlnPy3rWOz"}
{"uclassify":"Q4dtgHYPT144"}
{"uclassify":"Y8NcgnNSA2Uy"}
{"uclassify":"liC2Idh46bT6"}
{"uclassify":"3UP22RSQOJiW"}
{"uclassify":"XRUTW7Y6vgUJ"}
{"uclassify":"qA4jsEKqj4OV"}
{"uclassify":"zIhDre945XXn"}
{"uclassify":"7gc9j9jEISpZ"}
{"uclassify":"b1cwRQ7FCHcT"}
{"uclassify":"Y6jKKoCbwY7q"}
{"uclassify":"kFjaKLVNhOFu"}
{"uclassify":"tixGWvGcOMTu"}
{"uclassify":"zYxeNeNBoOcE"}
{"uclassify":"clE9qikiGXfu"}
{"uclassify":"soyLPaKgTXsM"}
{"uclassify":"3sShitegxYcn"}
{"uclassify":"WogKzqU8dits"}
{"uclassify":"AE3mLY9e6SS8"}
{"uclassify":"914ghMmI1coh"}
{"uclassify":"WTVUqBYXo8tO"}
{"uclassify":"A27IGMsqis7T"}
{"uclassify":"rP4k91EGZfkt"}
{"uclassify":"OEiTbO2ntwyV"}
{"uclassify":"r2OaJu2tAJPQ"}
{"uclassify":"0RBWw8V71NkZ"}
{"uclassify":"bUIJHeuhIe3H"}
{"uclassify":"LdDHKrhoBGLD"}
{"uclassify":"yVRPMvaFdibM"}
{"uclassify":"BQdq4LEMGgt7"}
{"uclassify":"KQd3YLtxDctC"}
{"uclassify":"h4gULOGYv31r"}
{"uclassify":"JclTkA4Iw4y4"}
{"uclassify":"TzWuhdIw6ORr"}
{"uclassify":"N60MQvpuRyUF"}
{"uclassify":"G0ymAqSSK6mb"}
{"uclassify":"9GLdhqmkNqQZ"}
{"uclassify":"Q0dwMwZWsLSz"}
{"uclassify":"SseVpVsmG9xL"}
{"uclassify":"L97puqtYmpSO"}
{"uclassify":"yUqpOjCYweTJ"}
{"uclassify":"PYhQe9ulwXbX"}
{"uclassify":"kWglG4uIQBIH"}
{"uclassify":"jW1m229MjmVE"}
{"uclassify":"wvfb3lqdcZTl"}
{"uclassify":"mgxX5dhdzRPm"}
{"uclassify":"x0WTDWIpuJbp"}
{"uclassify":"YXcbgmSJvdDy"}
{"uclassify":"DQLIXwUgBVsA"}
{"uclassify":"aCPsb0lz5dBS"}
{"uclassify":"Yoy0wXHc9rYp"}
{"uclassify":"IVaCuIuaDCXt"}
{"uclassify":"07MRLGehYS2B"}
{"uclassify":"TY1VH7GQV6w3"}
{"uclassify":"G4fFHgOMqJw1"}
{"uclassify":"LpP9UadCWvgD"}
{"uclassify":"g4eKCnfzMuat"}
{"uclassify":"cXLEn9jKsMbf"}
{"uclassify":"FMwMKYDIlFog"}
{"uclassify":"0A5ECHMtok8V"}
{"uclassify":"4jGu7ziuokzq"}
{"uclassify":"OxJ17cQiHxFO"}
{"uclassify":"rIx9e01LJvq5"}
{"uclassify":"0bZctkvw2vUm"}
{"uclassify":"7wLviHr6uHPt"}
{"uclassify":"RuQZMcUNhOvO"}
{"uclassify":"z1VCDupPKetM"}
{"uclassify":"C1TJMvoSmQzf"}
{"uclassify":"Kt4cPCcT4EVM"}
{"uclassify":"cLttYE412sBk"}
{"uclassify":"irILBgh2p28h"}
{"uclassify":"74PSA0BNLl6E"}
{"uclassify":"XncR56i7erPK"}
{"uclassify":"pwbisrMgjsoh"}
{"uclassify":"ZY2bby7fCTm6"}
{"uclassify":"2GbcxPFfhH6T"}
{"uclassify":"C8MaNcc8edCA"}
{"uclassify":"Q8MmhxWXMAc2"}
{"uclassify":"coEQJmlpWDxN"}
{"uclassify":"3mQ7Qxmec5ac"}
{"uclassify":"FLYwiS0cWXp2"}
{"uclassify":"Ekr8rXDNdXkX"}
{"uclassify":"Syoa3hNeaWu5"}
{"uclassify":"4KWGwdY4RcNM"}
{"uclassify":"zUb9aqsJE2OY"}
{"uclassify":"tNxdu9nHnLn2"}
{"uclassify":"L3TlLSWBzVuR"}
{"uclassify":"VeHkAwEVCUBA"}
{"uclassify":"n4QLgK5TMNug"}
{"uclassify":"RxEaQd6xe3ZV"}
{"uclassify":"1XDawO8WJzxh"}
{"uclassify":"3kU2zReFRpEk"}
{"uclassify":"VZsG8mnj962K"}
{"uclassify":"uysm0mpP4xXm"}
{"uclassify":"v7s8TMRe6gPc"}
{"uclassify":"jRgWaocuY82K"}
{"uclassify":"vkJlj6AAY3Bi"}
{"uclassify":"6An0ABGW2v1g"}
{"uclassify":"Y15j2oaWQeVD"}
{"uclassify":"H1zBMfm0x8iG"}
{"uclassify":"aqQjJJCHloco"}
{"uclassify":"Zt7fpmezJ7rw"}
{"uclassify":"cZ9X1TDvtdgl"}
{"uclassify":"JDXRz6ysPP5d"}
{"uclassify":"m3hmTTd9zLqx"}
{"uclassify":"OuNnoR7CZw4e"}
{"uclassify":"3g49lsxmDl99"}
{"uclassify":"6WNLzH36JVjn"}
{"uclassify":"T6GIPjwPsHLg"}
{"uclassify":"OySy5XVoagM2"}
{"uclassify":"GVsTi13JoAnt"}
{"uclassify":"yovYRIuev99k"}
{"uclassify":"dpb4U93lI8KV"}
{"uclassify":"UVQyjRENU6R2"}
{"uclassify":"Bvkf25I3hHOs"}
{"uclassify":"Pg1w6NhmujXv"}
{"uclassify":"8XAXJl5J3EnL"}
{"uclassify":"pT3DmN2NVlnT"}
{"uclassify":"3FJHw56EUC3G"}
{"uclassify":"MzgMowGtEiPW"}
{"uclassify":"ATzWBs53LeCh"}
{"uclassify":"qzeCFvtYO3gl"}
{"uclassify":"Cfd5Dmhat5CD"}
{"uclassify":"7tI1l5Kasyu7"}
{"uclassify":"h5PO3zc3ZvLs"}
{"uclassify":"KzMab3bFQEKC"}
{"uclassify":"1MSDuLFdmDxQ"}
{"uclassify":"E9WNZfJPdKUD"}
{"uclassify":"cRuvxScY9Iqf"}
{"uclassify":"nmJiset4vp4E"}
{"uclassify":"JY7SlV2JiRdR"}
{"uclassify":"B6ohWzThUkeQ"}
{"uclassify":"yZxW8UJUcn12"}
{"uclassify":"KcqjoHStn5Y9"}
{"uclassify":"0IfvXfBWqHqA"}
{"uclassify":"Ram6c0bbhunB"}
{"uclassify":"V1ylO1xDfnz7"}
{"uclassify":"kHbWaJEld9a1"}
{"uclassify":"VIrIq7RDiJR8"}
{"uclassify":"X3YSE2EJQ9Ap"}
{"uclassify":"mHPKyXvbywUH"}
{"uclassify":"OkcrlkQJy8Zp"}
{"uclassify":"AZDFKg6TqMA2"}
{"uclassify":"Ubv7enLISyH4"}
{"uclassify":"B94TSIro1vQt"}
{"uclassify":"Cx04s3Va0YxZ"}
{"uclassify":"PKURtwRBAYqB"}
{"uclassify":"zfR9mJVCsyDG"}
{"uclassify":"OfG283KTsQS9"}
{"uclassify":"Zq0QCt809aQT"}
{"uclassify":"H9oxkq7Wbj0N"}
{"uclassify":"4nI5CegZZ5SV"}
{"uclassify":"RQ8DCAf6KZZt"}
{"uclassify":"jeoGMdaA5ESS"}
{"uclassify":"KJWGtbgwsmvg"}
{"uclassify":"uWJBMPcQyBmK"}
{"uclassify":"vBaInxuTtvIk"}
{"uclassify":"vPvMe90ZYidg"}
{"uclassify":"UIKkABTIxrHq"}
{"uclassify":"wDtDNCKw8qnh"}
{"uclassify":"ltbG2xDFrkAE"}
{"uclassify":"kQAalpY6gvkl"}
{"uclassify":"e1L4xh76tg7s"}
{"uclassify":"Ik0amqWiSchf"}
{"uclassify":"Bmm1V5MsDmS0"}
{"uclassify":"MsWnQHXLy6a7"}
{"uclassify":"l1Pf3slvyEZI"}
{"uclassify":"0fIrJEkFINXv"}
{"uclassify":"BmNEcG8fiYOP"}
{"uclassify":"cVPb3zgTwDV5"}
{"uclassify":"IErpFLn10GKg"}
{"uclassify":"2OSPhY2Wj6NF"}
{"uclassify":"dARIHPuDk3ad"}
{"uclassify":"KYoCPkR2T6Si"}
{"uclassify":"vHvvVllS8c3Q"}
{"uclassify":"Meel5u1uZmsL"}
{"uclassify":"csY1IWiArPmD"}
{"uclassify":"xNjflDhHedzL"}
{"uclassify":"cSSVNOBJtPjD"}
{"uclassify":"U7gOUfZr5gDu"}
{"uclassify":"2UzzP3GsKiE1"}
{"uclassify":"zV1tAheDo5WJ"}
{"uclassify":"BD5gwIm42LYO"}
{"uclassify":"UnQfpeoWptRf"}
{"uclassify":"UJ9mUX0SNgFN"}
{"uclassify":"jzuPV8uPGQWb"}
{"uclassify":"d7YQuLhap1Xj"}
{"uclassify":"WLtM1oEzFJF5"}
{"uclassify":"TrFHj4QOHzwk"}
{"uclassify":"YgJC6dwIX0cH"}
{"uclassify":"QYGtrGI4O720"}
{"uclassify":"87pZdVRk22GW"}
{"uclassify":"ReSBN1549lXI"}
{"uclassify":"QAyWQScVW9pn"}
{"uclassify":"tpgw05qJQ0xK"}
{"uclassify":"jHGBDNAyvw8w"}
{"uclassify":"oPoMlHPFKpAE"}
{"uclassify":"1D9kSKeyYLDT"}
{"uclassify":"s2zlmqZzf6wh"}
{"uclassify":"AD22d3PvAtw0"}
{"uclassify":"IXC4xq5TaOIj"}
{"uclassify":"E5PH3oAAW9UH"}
{"uclassify":"vQDvX7ndWqQ5"}
{"uclassify":"19GvngmPDokD"}
{"uclassify":"hYZOqI3Ca2X2"}
{"uclassify":"DVAyDdsbvgai"}
{"uclassify":"2RowCMVsc49h"}
{"uclassify":"tvKW1pTHqyLp"}
{"uclassify":"VtEi0ynAHIB1"}
{"uclassify":"Ay9BPmY4wpwe"}
{"uclassify":"NvW4zh2cpRjR"}
{"uclassify":"2fFpsBg7x7oe"}
{"uclassify":"Gsw1aWI16QE7"}
{"uclassify":"bgGxgsTE1kgS"}
{"uclassify":"jA6gCKmBXwwh"}
{"uclassify":"Abt7l2EuQilR"}
{"uclassify":"o450cNe4OTyD"}
{"uclassify":"Km3RSyKy4mzm"}
{"uclassify":"5Rijvk86Ef7k"}
{"uclassify":"WltaWCv6vwBI"}
{"uclassify":"4F4fTAyhPtVG"}
{"uclassify":"kJKqVgBWmIZJ"}
{"uclassify":"wSOT5WNNtXF0"}
{"uclassify":"CjHBn2l5XDtM"}
{"uclassify":"tFZjO6FGVTfQ"}
{"uclassify":"vMI1H1cqVdAR"}
{"uclassify":"6hlyChrMWXOc"}
{"uclassify":"wjCQjAIqXGph"}
{"uclassify":"3EsmbrVICvNa"}
{"uclassify":"8sdMITRrtCJ3"}
{"uclassify":"KUo1YrB6v2Kd"}
{"uclassify":"RqZVSSpIEdJB"}
{"uclassify":"5TLXGsWU4euZ"}
{"uclassify":"mfeVHHz0sOIu"}
{"uclassify":"Z6tE507KPmmK"}
{"uclassify":"YUS0qTOJIjb1"}
{"uclassify":"j3fBEH0G756p"}
{"uclassify":"9bd669yBHFiB"}
{"uclassify":"YGtjo4rGavan"}
{"uclassify":"4EHkWWKvQTBV"}
{"uclassify":"624T0A7wBJ7Z"}
{"uclassify":"FHcTbjhJ3IZK"}
{"uclassify":"1lxDVj8iqztE"}
{"uclassify":"9JtJuU8bAvlM"}
{"uclassify":"OJJAgyMQUdpM"}
{"uclassify":"KA00huoHoKj3"}
{"uclassify":"skZq1JOA2KBG"}
{"uclassify":"BMWWyLylL1mt"}
{"uclassify":"LccKk0kxTjeh"}
{"uclassify":"ZBnw4Anl7f5l"}
{"uclassify":"c77xYYx8cZK8"}
{"uclassify":"3ldl1eTlD4Wq"}
{"uclassify":"uxz9Z6xGyXtp"}
{"uclassify":"G42VAcNeygKa"}
{"uclassify":"1uxjR3xc0CAV"}
{"uclassify":"fklc3NU1S7Hb"}
{"uclassify":"NvZfBADzOuvZ"}
{"uclassify":"VJEf1V0SsLMr"}
{"uclassify":"a8iHJAexMGp4"}
{"uclassify":"EbbImNb1qDse"}
{"uclassify":"ZKYebgPFbd8x"}
{"uclassify":"DMMKxUTttmFs"}
{"uclassify":"oy5Z1q7MkCOi"}
{"uclassify":"QSCM9KOUqGJO"}
{"uclassify":"V5Pk92xBrRci"}
{"uclassify":"CNgq8ipG5knq"}
{"uclassify":"todz2gs1DLRu"}
{"uclassify":"IQWKdhKbbn7r"}
{"uclassify":"LXncZXVx9LoP"}
{"uclassify":"MfQmiBe6rYqM"}
{"uclassify":"29eHVagUuMCx"}
{"uclassify":"Wh7SEk0sKes0"}
{"uclassify":"4rn2PqRTPOBJ"}
{"uclassify":"iyIwSkK7yFON"}
{"uclassify":"Yer7xB6VcNyD"}
{"uclassify":"jkg217RMnXSS"}
{"uclassify":"JKHCQu4UNvlS"}
{"uclassify":"qHvjmVOI0MwA"}
{"uclassify":"lMWmLszqMesU"}
{"uclassify":"c9EYzsXzEUw0"}
{"uclassify":"WnImqhsvRIwp"}
{"uclassify":"as5B0N6eb1yL"}
{"uclassify":"2XGWyvpNjD1U"}
{"uclassify":"pIEVPDCaFTZV"}
{"uclassify":"V1Srnymu6Cus"}
{"uclassify":"bHWQiueYkxaL"}
{"uclassify":"p5EFMVxag26O"}
{"uclassify":"BWwXDOBMt769"}
{"uclassify":"btVdFO1aam84"}
{"uclassify":"ytKJWNffKxQ2"}
{"uclassify":"zGK6A2h3ufJl"}
{"uclassify":"QmKe1ql9fylA"}
{"uclassify":"EsiFFt5peeTk"}
{"uclassify":"JLcaxZ29ePEE"}
{"uclassify":"Awk2PeWkwv0p"}
{"uclassify":"1N6VzXr1PknV"}
{"uclassify":"D0juKLUogrjU"}
{"uclassify":"H5QdqZizExM4"}
{"uclassify":"aLN3gnMr3YXd"}
{"uclassify":"BirZ52SLTl9E"}
{"uclassify":"wu4Gnns5tnpG"}
{"uclassify":"ClEXjpwjDMBd"}
{"uclassify":"SJXQxR0dysJw"}
{"uclassify":"wHfZuLT57m2b"}
{"uclassify":"u8WH8SVb7iyC"}
{"uclassify":"k1NMLe8sXGCU"}
{"uclassify":"DbQEdoLDnEC4"}
{"uclassify":"J1FkCAml5QMf"}
{"uclassify":"vuQQlThFZSJ5"}
{"uclassify":"o4SrCWyTs5FA"}
{"uclassify":"RdhHNFICTn8s"}
{"uclassify":"TnNqa1xO4473"}
{"uclassify":"fnUBZRoCa8ks"}
{"uclassify":"wlNBP5TUKmkL"}
{"uclassify":"bG0JqJCBOs7l"}
{"uclassify":"2YCI87DkuQ0p"}
{"uclassify":"G8ldRDxuMh3k"}
{"uclassify":"E9TSC8zEETRn"}
{"uclassify":"pEs6SS0g96Vs"}
{"uclassify":"NZsSIhgb1g7Q"}
{"uclassify":"QcSc0Wn1JIy5"}
{"uclassify":"55buR34wWDya"}
{"uclassify":"hj0rgVGaNugE"}
{"uclassify":"05IzASvbvxjQ"}
{"uclassify":"eHncTRCR2uxU"}
{"uclassify":"GnND7r4lYb5C"}
{"uclassify":"PPYpvI4whZ9a"}
{"uclassify":"MdiY0bJ922Bp"}
{"uclassify":"SpHhAeKaboTh"}
{"uclassify":"vP59wTgOf6EA"}
{"uclassify":"VMVyNAwsa5VJ"}
{"uclassify":"PCCfsB8GO3V8"}
{"uclassify":"nKRMgzvpzkri"}
{"uclassify":"0w6Z6ot4GS8f"}
{"uclassify":"7d3kCIbDfCcn"}
{"uclassify":"7RiWvGEtZzTq"}
{"uclassify":"19szfHqdGUZt"}
{"uclassify":"qY7il7l7EppY"}
{"uclassify":"gi73v81nrQTH"}
{"uclassify":"C9DIHJtUjiG8"}
{"uclassify":"UwpVBszw8WmJ"}
{"uclassify":"hDmn0sIEFsvL"}
{"uclassify":"T7Y5CkayLlKo"}
{"uclassify":"qu4QxDaXOPvh"}
{"uclassify":"pZoRo9BTGrkv"}
{"uclassify":"9L3HnhLCFTf2"}
{"uclassify":"1ESBwuZ2C1MJ"}
{"uclassify":"rFzS5dk8WKpv"}
{"uclassify":"ipegO3RbZamj"}
{"uclassify":"Uejw6YqawQ28"}
{"uclassify":"irD1tXWJA4oO"}
{"uclassify":"52aPWYhvLmmr"}
{"uclassify":"sn7nAWnH4TLp"}
{"uclassify":"TIKOSSNvW4lU"}
