{"nasdaqdatalink":"qcF-51sJnxgfqYZL2x2Z"}
{"nasdaqdatalink":"tfGHETZwx-sOYxI3RZTw"}
{"nasdaqdatalink":"d1PQ-gBeE3iqdD_DnK9E"}
{"nasdaqdatalink":"zKB_3rDERYflZ1XBdub5"}
{"nasdaqdatalink":"dpCTtokDTpkJGzDZzxss"}
{"nasdaqdatalink":"VwEFDWS2QKSPIYIK9zj8"}
{"nasdaqdatalink":"ndvBi0J0I0F3S5vsRXOC"}
{"nasdaqdatalink":"lis8O-jjP7Xnrh6ZcTuK"}
{"nasdaqdatalink":"ZjPu1tlc1DXUH_xO-aM8"}
{"nasdaqdatalink":"cwrcRhnScSbf-X_iG-ye"}
{"nasdaqdatalink":"ohFMbvIUC_8hn-Y9Vl4E"}
{"nasdaqdatalink":"TvNffliiw3NNLzYS-6DQ"}
{"nasdaqdatalink":"EeoRSesnmcW08MskZdS0"}
{"nasdaqdatalink":"uW3TGGsk7lI6M7FvMHF-"}
{"nasdaqdatalink":"_O4CvCpJ6W_MrGDRrMWx"}
{"nasdaqdatalink":"kYetlpV5HV_4FS1TtyhQ"}
{"nasdaqdatalink":"aEj-d0fnRkzQAjcQa38m"}
{"nasdaqdatalink":"XFj2CUPKKfUDR7iCNXNX"}
{"nasdaqdatalink":"ht0Gs5UCZX9dkioIfrCY"}
{"nasdaqdatalink":"6T5tIE5SrcmmWtZICYCc"}
{"nasdaqdatalink":"MFZJDAJ0FRdlbpthtsiB"}
{"nasdaqdatalink":"sNu1_RvZjSdDty_dg8fR"}
{"nasdaqdatalink":"yYv-3SDc5CqUqOO59XVa"}
{"nasdaqdatalink":"3uU3ESrsqorCGeL_nUG7"}
{"nasdaqdatalink":"P8Xb8RJXRdlweo5fc7LX"}
{"nasdaqdatalink":"YJ8Okj1CuzkjzetgPXXE"}
{"nasdaqdatalink":"yiw9lGMIoWVeWN2TAWqg"}
{"nasdaqdatalink":"7ZoR_U8wHY7wrDm_RVap"}
{"nasdaqdatalink":"fS4SF3eTp__CFflqkDdu"}
{"nasdaqdatalink":"0bIJV2PL5YHONLleiiVc"}
{"nasdaqdatalink":"JGyzKl-885QrXPtssnPU"}
{"nasdaqdatalink":"kaAbtKnKkWgS22Xj6wr1"}
{"nasdaqdatalink":"L5e-8hU7H9YMRrr1Yqf2"}
{"nasdaqdatalink":"zS14uc1E4T2yoGB_PU5E"}
{"nasdaqdatalink":"3d7tzNP4aJF8WyW2DCfy"}
{"nasdaqdatalink":"f-kXDA4QpL9VwYAdhB4I"}
{"nasdaqdatalink":"Bz-UA4kPPLKemvvI4JZN"}
{"nasdaqdatalink":"qiL4lqhcMkBYKJeqViNY"}
{"nasdaqdatalink":"JU1KEX0DMybj1adf9lVw"}
{"nasdaqdatalink":"lvIqW6yrkcKdvKZ2Gn-J"}
{"nasdaqdatalink":"ht5CDN-ntpR12vrjswG9"}
{"nasdaqdatalink":"q8_R92g-bQFj7YCxd7wK"}
{"nasdaqdatalink":"p4312ZRgvvnElrgrk4Yd"}
{"nasdaqdatalink":"9y5xJMQqTkrdC2jtDh5h"}
{"nasdaqdatalink":"hJmdsjKVJFvHDRjk7fZv"}
{"nasdaqdatalink":"_jHwE2L2hO3RcFoPW6MD"}
{"nasdaqdatalink":"ZtyqKhQJztpSDGMb0tJb"}
{"nasdaqdatalink":"Dzh39oVufGbZ6BLKluaC"}
{"nasdaqdatalink":"3d5eoBw9SCaFibP028oA"}
{"nasdaqdatalink":"EwdGxOTRKHHHUETvhm5s"}
{"nasdaqdatalink":"ZJe-DMT1vmtBSNf_PYka"}
{"nasdaqdatalink":"zyJ24h7QFx5yFV_XYTVS"}
{"nasdaqdatalink":"vit3UBWS7wFAP9WXIgf_"}
{"nasdaqdatalink":"IyjaNO7I8qezPv3f4CWZ"}
{"nasdaqdatalink":"7I8KgiQXpORFvhgFU08X"}
{"nasdaqdatalink":"CSwOFL7XqZEz3XkhG6bl"}
{"nasdaqdatalink":"UuRkef8Bqrf1aUZu5e5R"}
{"nasdaqdatalink":"n_ONUXS68rvqruNJL7F1"}
{"nasdaqdatalink":"DbO0EZvIcHPziHSNaJKd"}
{"nasdaqdatalink":"nbnXUaHX-hJvmuqRhPpM"}
{"nasdaqdatalink":"dAciJMJO3aYUaqwm92mj"}
{"nasdaqdatalink":"h_7CUnzSf9de02wgojW_"}
{"nasdaqdatalink":"peAE98eiC-2RC9dCESft"}
{"nasdaqdatalink":"BwfDZbPdwRaAUUWVknfq"}
{"nasdaqdatalink":"FyPLThyn4-ff6PLAXl20"}
{"nasdaqdatalink":"YXh3zjZPBd581QhRj7qY"}
{"nasdaqdatalink":"FLxP0pBJWjbcnreVvL_P"}
{"nasdaqdatalink":"94U18oimc__x2nFo6rF4"}
{"nasdaqdatalink":"1bGlLYVGA4u0Ffi1Dkwi"}
{"nasdaqdatalink":"NahdW9w4nBbiXK6E1kmn"}
{"nasdaqdatalink":"bTLPJL0fcQ3zxfbyZiv6"}
{"nasdaqdatalink":"wnRCYkuywEWPdLlRqCom"}
{"nasdaqdatalink":"iYVoZbCR_ItnwhP-XGc2"}
{"nasdaqdatalink":"ki3QeqICNLwijwthktZJ"}
{"nasdaqdatalink":"FXaoZ5w9p3Y_Rk2SaCEu"}
{"nasdaqdatalink":"nL71mZbR-uvTLxBp9u1u"}
{"nasdaqdatalink":"Ccg3xMBKIjvP1LL9KkXd"}
{"nasdaqdatalink":"xOv0sJfLfawxZ0KgzklN"}
{"nasdaqdatalink":"Ta4bUgW7A4xtAvQbCvNy"}
{"nasdaqdatalink":"1P8t5IjZmA58nW7nxA_k"}
{"nasdaqdatalink":"DFSXjU6f1V2g6JyNw8-Q"}
{"nasdaqdatalink":"G2-tZnwdt6ldF9jF3-i2"}
{"nasdaqdatalink":"E6OHoE7vgkbIsxUCFZMT"}
{"nasdaqdatalink":"8SZiT7rZSkXi7yhaSAb_"}
{"nasdaqdatalink":"J2K487mmm8CCL9GG-TeX"}
{"nasdaqdatalink":"rzB4ldYXZU7j1MV4oYMf"}
{"nasdaqdatalink":"nqOKqw079Z3e2AwsA6xS"}
{"nasdaqdatalink":"Kt7e6-g4Vd2dMBWLMHbh"}
{"nasdaqdatalink":"jRovAchPHrpfH-UudeuT"}
{"nasdaqdatalink":"ClQJKCOkGMutDXOb-kNa"}
{"nasdaqdatalink":"ECz8VHVGLnH_iZcoxWXv"}
{"nasdaqdatalink":"6MFbLU1uEt-K45hbw7uk"}
{"nasdaqdatalink":"fqWEEJk_zc8U77gdGR0F"}
{"nasdaqdatalink":"_cWD1lXvgjebBdaUQbUG"}
{"nasdaqdatalink":"v7f4k21dNgEWEV6-HM64"}
{"nasdaqdatalink":"UY7eayhCyOQfoSf8V2FG"}
{"nasdaqdatalink":"IGPNXQquctAJlIIP8shO"}
{"nasdaqdatalink":"X-Gh9qwQI_ZSMIicQ5nq"}
{"nasdaqdatalink":"g2xEYM2Uagh6b_QNT_Lx"}
{"nasdaqdatalink":"2v8Mf1tXypUKfz6qmf0D"}
{"nasdaqdatalink":"RtuQAVAjDPe9k2IlhWG9"}
{"nasdaqdatalink":"Bsdn5YVdLprk7wh3z8p8"}
{"nasdaqdatalink":"zk8sRJDHATDjDwVAoCAB"}
{"nasdaqdatalink":"WUmFcTT87xv7bavM0rO6"}
{"nasdaqdatalink":"W5Gx00yZlcF7If-PVNx6"}
{"nasdaqdatalink":"S4N57HsZYJK_hTViah2k"}
{"nasdaqdatalink":"LYtSei3G7NIpST_96VWp"}
{"nasdaqdatalink":"uxV4CYicZmgbssMsAhsX"}
{"nasdaqdatalink":"qFWANhg_AOfWKZvpghLl"}
{"nasdaqdatalink":"F8PQFAtBQfLfEWE4xkYb"}
{"nasdaqdatalink":"pMqatybrBnFjy1ZqSiOg"}
{"nasdaqdatalink":"YatKUIJrEEnKCh1XQcdf"}
{"nasdaqdatalink":"9sBH1iPoKr6lQm46OC5d"}
{"nasdaqdatalink":"iwTjK46KIyJzavg7fqlO"}
{"nasdaqdatalink":"jCRjzyTeR2Bd14F0Jutg"}
{"nasdaqdatalink":"-qEkDi-6pPo5NK_OJrpf"}
{"nasdaqdatalink":"guuo0rcL_EQAADWtdHPG"}
{"nasdaqdatalink":"8M8biL_NsSOu0y29kqvx"}
{"nasdaqdatalink":"Qms-jGsZ6bZH7h6en5Eb"}
{"nasdaqdatalink":"kVjVNbRFZsm1cIk6jqrZ"}
{"nasdaqdatalink":"pNq3jFiKjnhwBktHXexH"}
{"nasdaqdatalink":"LO-PHYGtTg1BsAMts7aY"}
{"nasdaqdatalink":"EthW0Z-RBLzvw9adDyRP"}
{"nasdaqdatalink":"adjgOwUmZCnNfy9AAWD2"}
{"nasdaqdatalink":"DXcqnxWH0s0ShyMg3FEu"}
{"nasdaqdatalink":"C83IEQpHkmHHXc-LECHw"}
{"nasdaqdatalink":"o2O2JY5u5BSohTdR-f3x"}
{"nasdaqdatalink":"6YJCkSp0VGkYkzVQrkkV"}
{"nasdaqdatalink":"W6IE18D05LMHF3eixxbu"}
{"nasdaqdatalink":"kc43UGXE7G-X61yDfzBS"}
{"nasdaqdatalink":"aLRBXuLoPUFLME4yx2iB"}
{"nasdaqdatalink":"cd2hWACfNALRQ93R9Emf"}
{"nasdaqdatalink":"LW-C9JoBNfuA9-ckozYS"}
{"nasdaqdatalink":"jDVYmVKtCRlkRNfFkxvP"}
{"nasdaqdatalink":"MCtTvp-3ZAY2U8MQh0FO"}
{"nasdaqdatalink":"GciTMw__E_Srl4kejgOI"}
{"nasdaqdatalink":"yqGiiJtKl_osSONfwdgf"}
{"nasdaqdatalink":"sjmv8RsLr2a16BsrQLgk"}
{"nasdaqdatalink":"OMJ3Xi6YdLc7Zsqd0XD2"}
{"nasdaqdatalink":"xE5ZXAF6K7Eo8BKwcY3H"}
{"nasdaqdatalink":"1uUO5d-ycjhrdyVubrsI"}
{"nasdaqdatalink":"pJE_nyfbOgp6KmI_vKgo"}
{"nasdaqdatalink":"WweX6DoNWfg8Oy8OhaC7"}
{"nasdaqdatalink":"Fjf44at_TAEOAg44-pN4"}
{"nasdaqdatalink":"aow6LDLy3KaaWU70TZzU"}
{"nasdaqdatalink":"u9D8E8K0eIodheQgCefc"}
{"nasdaqdatalink":"PiARk2d-tcNcuCIrWWpW"}
{"nasdaqdatalink":"Ry1PDtdIOieOPVFQwnMn"}
{"nasdaqdatalink":"HWbiU09nvUUImDEBzh3_"}
{"nasdaqdatalink":"mEzNgARa5OFFRHbEc6sR"}
{"nasdaqdatalink":"4qKeZsr6rq_D86nwvbJw"}
{"nasdaqdatalink":"0J83tZ7pxpDDJwJi9wWf"}
{"nasdaqdatalink":"6i6fUh2HWV4YF_m5K2ff"}
{"nasdaqdatalink":"qh2md8_7CT8IGF-5Q5_J"}
{"nasdaqdatalink":"cGkZuLowEcB6Vrxwv-nq"}
{"nasdaqdatalink":"6JyhigLjXpFmJWViJ9Wc"}
{"nasdaqdatalink":"9FDFl_ZM6wqg5ga1xUjl"}
{"nasdaqdatalink":"TRumQXFFzsd9BOSLZNfE"}
{"nasdaqdatalink":"VF_x2zMawCs5vlwdbS_U"}
{"nasdaqdatalink":"atY61kUEwWe3teKY9Q1m"}
{"nasdaqdatalink":"DPw4MD77092DqX93c-cV"}
{"nasdaqdatalink":"alIpnQ4bTvRsqmjPs-yb"}
{"nasdaqdatalink":"KStdNizkBbkczXS5N4QU"}
{"nasdaqdatalink":"gY9AHc8slHe8KT6qbUrP"}
{"nasdaqdatalink":"MkW9NwyEFg4d-waeC-A7"}
{"nasdaqdatalink":"t6suxpcHUg2ohil8vxQI"}
{"nasdaqdatalink":"i3aMXiBH_EBuI45g-P5U"}
{"nasdaqdatalink":"g3BkkA12qNnO2Wlc0ZAg"}
{"nasdaqdatalink":"z9R1EQQN5FaXbDNlHH_S"}
{"nasdaqdatalink":"iDeJbi5iybr_FLg3Z5xG"}
{"nasdaqdatalink":"8Pgb1-7aRqVZSUrVOCuj"}
{"nasdaqdatalink":"Yt36u-VidcUev0QyWvPQ"}
{"nasdaqdatalink":"IiJFZkMt--VxTIAi5uAR"}
{"nasdaqdatalink":"JnbokMXxk8JqjSYj45G3"}
{"nasdaqdatalink":"aZ4Dd1jiM7BlZxpkbhit"}
{"nasdaqdatalink":"TAVWshGQq23dv9u3lmoA"}
{"nasdaqdatalink":"xrq3Hl-g04Tz1XmkhG49"}
{"nasdaqdatalink":"1FiyGgkB1ZlyfhqWklqc"}
{"nasdaqdatalink":"AV-IDyHucK4PnTfeCRvw"}
{"nasdaqdatalink":"en1dLYu7Zll3rKboWdcI"}
{"nasdaqdatalink":"nnkF16OctLM4CqFzlzse"}
{"nasdaqdatalink":"5yPFPVe60kExYHrjjKcf"}
{"nasdaqdatalink":"piVg1HgJqwSg7VPCeVd-"}
{"nasdaqdatalink":"RnVwsVL3PsdHHQyQuBTG"}
{"nasdaqdatalink":"02wj0IuLoEq0OyMKb4B-"}
{"nasdaqdatalink":"ReZ6H7n40801OjzKK7-X"}
{"nasdaqdatalink":"WJsXVAUIeN7miePg7lh3"}
{"nasdaqdatalink":"VWI_GjrvoyY9lWOkY9x_"}
{"nasdaqdatalink":"xKHYR1wT79UaZFx-MiDt"}
{"nasdaqdatalink":"_jPGZmYOEnT7LWUGOncn"}
{"nasdaqdatalink":"GGsOOoUI0nnuziEZ8lva"}
{"nasdaqdatalink":"x-mZ8RVB7yGwBShSsul3"}
{"nasdaqdatalink":"tspvaT9FOJ9fDNUugQ5n"}
{"nasdaqdatalink":"pPKuTinHESA4hODz1Fd8"}
{"nasdaqdatalink":"1BskQlYFu6ocv5C-PMA1"}
{"nasdaqdatalink":"_3XHTS19hqOBTS_732oQ"}
{"nasdaqdatalink":"HW4olY9hufhz8jZpV2Mn"}
{"nasdaqdatalink":"9pPSUDo-mNRKGvsRwkVE"}
{"nasdaqdatalink":"BXXy32EyojGmfQgxxztf"}
{"nasdaqdatalink":"Iea27dSDPzpc4Z8OdTdc"}
{"nasdaqdatalink":"Qv_00s-gXY8LS3czVUec"}
{"nasdaqdatalink":"3nScZnxsA2UalE7LnT_g"}
{"nasdaqdatalink":"5ereWS3cWRGf3mBmYPAn"}
{"nasdaqdatalink":"_fVXkMvJn1CIhYQgvs-a"}
{"nasdaqdatalink":"EhlUdoWhGf7zjQW-K1zh"}
{"nasdaqdatalink":"2WamvdTY5ipeBroexbWv"}
{"nasdaqdatalink":"mZXnyKLD9lRlKOXTtKGN"}
{"nasdaqdatalink":"7tCM2iI0VVuNrkLe1qJv"}
{"nasdaqdatalink":"WX_H80Qx7eHlEWLbpYyF"}
{"nasdaqdatalink":"LQmr7fmDpWo4blRfdC2j"}
{"nasdaqdatalink":"oXXAPiag_-zTuak7ubL-"}
{"nasdaqdatalink":"awuvLRi0QS8vemD3n5NM"}
{"nasdaqdatalink":"Z6Cm3L7YD-4h4pbpF8Sa"}
{"nasdaqdatalink":"mwhDvilak0qHzyoLSVZb"}
{"nasdaqdatalink":"29Gxw9USxnC7iLG9_BgP"}
{"nasdaqdatalink":"Su1Ql1mr6M6phemCUJkE"}
{"nasdaqdatalink":"AGCeQTx9Yy_U2aH3Ub-8"}
{"nasdaqdatalink":"ZVtP3e-axVlP91rr73VA"}
{"nasdaqdatalink":"Cy0X04-PGRI_lYnEfxm4"}
{"nasdaqdatalink":"d9XOrjdCqxa-NFrwYS29"}
{"nasdaqdatalink":"Tyom3TyMh3cSS2XCr0D1"}
{"nasdaqdatalink":"cYqNz6PEmy_3NSyPjcjx"}
{"nasdaqdatalink":"OCqj2cGrj6rXmFo4BJMV"}
{"nasdaqdatalink":"OlgHpXiwE9tNxviKT3xx"}
{"nasdaqdatalink":"YmbgDKeA7UL7oBdzzLXm"}
{"nasdaqdatalink":"GTwnofJX8gJ67pd-SIvC"}
{"nasdaqdatalink":"uoOi8fhksikdXRkERPpo"}
{"nasdaqdatalink":"awPJwIbigZ4A1_wGeKto"}
{"nasdaqdatalink":"Q2QE1E0QHVukYQZTmjMZ"}
{"nasdaqdatalink":"IlbGdnZUIey8VNh6M6hn"}
{"nasdaqdatalink":"XvHNNT0AdJiUqk_ot8b0"}
{"nasdaqdatalink":"o231-VRtzsRiwvcs4AlI"}
{"nasdaqdatalink":"Ls-FDBOJWTsr-w8LsTi6"}
{"nasdaqdatalink":"ohQ6AA0e9NNc9P3fblRv"}
{"nasdaqdatalink":"85kTOWWH7sRMI86vv-Ee"}
{"nasdaqdatalink":"-EBxvSDgI9__mQQjgw6S"}
{"nasdaqdatalink":"YQoW7Jqzwe39uLwgj8Im"}
{"nasdaqdatalink":"sWOUwqD5m9I76VxfgyDe"}
{"nasdaqdatalink":"DQj2qpixOnOBveB_Ppsk"}
{"nasdaqdatalink":"jLyvs3wJcQZWcKZFv0Lr"}
{"nasdaqdatalink":"vAgnAQ-L7Lmx03V4p5CO"}
{"nasdaqdatalink":"GQJ4KhtmFyHivV8KAu22"}
{"nasdaqdatalink":"YGNXhLQGd3VABrHc9MK5"}
{"nasdaqdatalink":"juOa-QJCPB-9FDDD46Id"}
{"nasdaqdatalink":"kl2TXIFwm62fhhf9c9aq"}
{"nasdaqdatalink":"Q5cOa9cn2vMb0nhiHW1l"}
{"nasdaqdatalink":"OmDvkXzY5Nx_Rp77CDWF"}
{"nasdaqdatalink":"lMaWUC6VOZZa0i82y_MH"}
{"nasdaqdatalink":"ac-3eJqPERDDYEXuQEno"}
{"nasdaqdatalink":"w8Ls8ev4GMdYKVcl-Flc"}
{"nasdaqdatalink":"XYBWzeVDLxKznZgTazZq"}
{"nasdaqdatalink":"8vdEYloJGLfd4q_sAX4x"}
{"nasdaqdatalink":"9dcAA0oENylBdnv6mvCS"}
{"nasdaqdatalink":"sCQiigdkGTiQWcwXT1Pc"}
{"nasdaqdatalink":"1T9eYupnk-vQyFiwbYHU"}
{"nasdaqdatalink":"0OZNyR37jTyhE4F1eHb5"}
{"nasdaqdatalink":"kgAP7HTr2_ltOnEksrx6"}
{"nasdaqdatalink":"-JqYn1Kh8pTFueAgyR-h"}
{"nasdaqdatalink":"dF2hCX93C5_nynItsYX9"}
{"nasdaqdatalink":"bmTu1olB0IpBIMJC9-nN"}
{"nasdaqdatalink":"m6Jr2cgcwdBNzKOfBZCH"}
{"nasdaqdatalink":"FTiVd4x18Xk1JZXmgtsn"}
{"nasdaqdatalink":"lBONYkM9DbQSGUeurlM2"}
{"nasdaqdatalink":"P-G9VE_95uWnJniipkZb"}
{"nasdaqdatalink":"AasMWSp9tor-Vr4Kws-9"}
{"nasdaqdatalink":"sAKBqFbfY7s1jr_UBnw1"}
{"nasdaqdatalink":"jFg6g4tNwuoVMKNJf2l5"}
{"nasdaqdatalink":"4t2yKcJRDTQqsi17gDBs"}
{"nasdaqdatalink":"tq6wiBxKW55k9FonfHnB"}
{"nasdaqdatalink":"TX1sDb_0A2rji_D2PFYb"}
{"nasdaqdatalink":"fTJ2UeLAiQ5R9_aUCyqg"}
{"nasdaqdatalink":"1OZ-i-28-tYfdEu76rUW"}
{"nasdaqdatalink":"8oyB_p7aFppI5dp7wBVQ"}
{"nasdaqdatalink":"J6QbvST0ga7ybYcO-sF3"}
{"nasdaqdatalink":"o_5xgirciPjH-YVZJ7YF"}
{"nasdaqdatalink":"2CIZXUsXTRJB_5naYWcX"}
{"nasdaqdatalink":"V2Ns12GrG_sTe1B6uF3m"}
{"nasdaqdatalink":"kfZuEWDWQ6P5LHd20ZAi"}
{"nasdaqdatalink":"SxGJUWn02hW7cBGgXHEB"}
{"nasdaqdatalink":"zuQ4a4ZjMyyud0JCxOvE"}
{"nasdaqdatalink":"-5jPMivF3SMyOtt5xxix"}
{"nasdaqdatalink":"hMyC-lYbXtnpj5Pp2TNW"}
{"nasdaqdatalink":"8lvevXp2XO1MXl4E98bw"}
{"nasdaqdatalink":"Mjiiyhak_w3CoB2U2M8p"}
{"nasdaqdatalink":"tZs4YA3phd1KvFx6GuKZ"}
{"nasdaqdatalink":"5E_AKdlLsSVF3KccteF6"}
{"nasdaqdatalink":"i3meKoR8hoB5S7-UnlhA"}
{"nasdaqdatalink":"1_HGEFTpUpyz6ttdLtwg"}
{"nasdaqdatalink":"1c-6n_lpQRSEN40m0xpD"}
{"nasdaqdatalink":"etRdT5wllioI3lQWD94T"}
{"nasdaqdatalink":"-5yfKx7c0ISX5WH1wC8X"}
{"nasdaqdatalink":"nTWYSYW4Ut9Ya7cknm_I"}
{"nasdaqdatalink":"khf9vlk4E5rEs7l9q_Rz"}
{"nasdaqdatalink":"PgRMGnaCzIdA-crZWOAx"}
{"nasdaqdatalink":"OAMAEyhY7F5Ie327XvwR"}
{"nasdaqdatalink":"5KbNTE8q6YM4W6sgc0Fs"}
{"nasdaqdatalink":"2vTNmNeTc74eIlDWPqaV"}
{"nasdaqdatalink":"OTq5HNbxykAt-6-2Fsm4"}
{"nasdaqdatalink":"YgwgqzLth3O6j633DIF8"}
{"nasdaqdatalink":"T6MA8MvWmjv-e412TBnH"}
{"nasdaqdatalink":"4gsl5jDS5gfN2wwm-q5X"}
{"nasdaqdatalink":"84eb1VmYOmAExPOiuijn"}
{"nasdaqdatalink":"MRQRTq8qmXcV3JS2HBL8"}
{"nasdaqdatalink":"gMtMygHF7CLL8vmcYKRe"}
{"nasdaqdatalink":"XHBKaDTV1RYmH4QfROkf"}
{"nasdaqdatalink":"4g2d_ZwOmhRoQtqTePDG"}
{"nasdaqdatalink":"qoHevj818Vt3sjrsBUzm"}
{"nasdaqdatalink":"RcZgJOD1y4KzzkSZ1_l6"}
{"nasdaqdatalink":"eSSYG49S2IL9qB0F3YgO"}
{"nasdaqdatalink":"mskRU1dcJnt-2QvI5Yx2"}
{"nasdaqdatalink":"ryUZW-fdsxua77SxBUlO"}
{"nasdaqdatalink":"S-3nUyB70bmzmbHyct2O"}
{"nasdaqdatalink":"GFFLnlbJMinOylTbCq3d"}
{"nasdaqdatalink":"rmhDVOHSNB3HkFrgnFwr"}
{"nasdaqdatalink":"VKpOF4dDCz8gPM0mHuQo"}
{"nasdaqdatalink":"LJny5_EAfPQJkIezqZVu"}
{"nasdaqdatalink":"RR6TSBqBZyy3sJSHa959"}
{"nasdaqdatalink":"jzc3QTN1WPktsbM-RY0x"}
{"nasdaqdatalink":"ubUqyejR6XHhIoIcQg2v"}
{"nasdaqdatalink":"zNhmJBYnwmX059xj_Mpk"}
{"nasdaqdatalink":"2YY735dA-ImHC_dDfRTh"}
{"nasdaqdatalink":"TEA0FH9xV2G_SIhfgEHR"}
{"nasdaqdatalink":"SrdFoQx0uUmSN6iRfX-K"}
{"nasdaqdatalink":"u06wqbSbL8E1DRiHNESS"}
{"nasdaqdatalink":"RFzQ01SGLxvZipXTH2qs"}
{"nasdaqdatalink":"-_UcxnW07euND3wF_nc4"}
{"nasdaqdatalink":"BkjRAMy-h_AP-Jlb4wtC"}
{"nasdaqdatalink":"QXO1GovWRtEuRm5G-SbT"}
{"nasdaqdatalink":"XmIzTptubiyn-gGdRRv8"}
{"nasdaqdatalink":"7OTv7T-yctegcjdVTgJN"}
{"nasdaqdatalink":"PKAGX1Z9lqAD_Y4exx78"}
{"nasdaqdatalink":"7kaBS1l2aZBGSyA7W6jS"}
{"nasdaqdatalink":"FjIiham5T3gh_XYzxRZ9"}
{"nasdaqdatalink":"Sfqusin32qUrfaQdwVN8"}
{"nasdaqdatalink":"NT-thI9OTrQs5qIaiP3G"}
{"nasdaqdatalink":"TIOYcs3jxpaIB-131hig"}
{"nasdaqdatalink":"rSUtneVOnl-ziOPPee8M"}
{"nasdaqdatalink":"Xvkaf0HZ51YQDp0bNovh"}
{"nasdaqdatalink":"3dcObG8h-NvvzHCiz9iI"}
{"nasdaqdatalink":"Oq_XBs4y5lu87MC-8kYG"}
{"nasdaqdatalink":"IuUOVZUkFW7YnHzKNezR"}
{"nasdaqdatalink":"KgbjPARZXHvuU8ST0eYW"}
{"nasdaqdatalink":"NAtIxPL32AH1vgoFu17a"}
{"nasdaqdatalink":"BTHbYlsCN_nKFY0MK8vd"}
{"nasdaqdatalink":"StWBEbodBL0j2rbztyv0"}
{"nasdaqdatalink":"V79JnOlnjfowCDAvGn-c"}
{"nasdaqdatalink":"-s-OgLBSvfM1g5GozSBE"}
{"nasdaqdatalink":"6Mr0BfAw8bQqHYS7TEpa"}
{"nasdaqdatalink":"CduijOx_cp6x5PeCu4Gv"}
{"nasdaqdatalink":"fwbw38KYbdeUnjz5gEoi"}
{"nasdaqdatalink":"WNTxF-Sie8I9-Ml7XQzc"}
{"nasdaqdatalink":"uXkV6SiGiGB_CiBAVYiP"}
{"nasdaqdatalink":"1ABWJLky1JBJ6GcJufUe"}
{"nasdaqdatalink":"xQe41y6L4Z6sk9pyZQpO"}
{"nasdaqdatalink":"DjRsp1_4C9ZwzCQ4C_nN"}
{"nasdaqdatalink":"L8pzj29rHuZR5D4h78bT"}
{"nasdaqdatalink":"VNX21iUTB1xFnSyQbWGK"}
{"nasdaqdatalink":"hdIsWiWAvVjkHVqXl-sS"}
{"nasdaqdatalink":"qa-OSUDyAZ4ox8Vn1fik"}
{"nasdaqdatalink":"Hus9iRF38iIGwRZZKfjr"}
{"nasdaqdatalink":"gBil_WNKWZOW1iK7Xu_o"}
{"nasdaqdatalink":"flVjY8Jyk8Hf-1JxV8uG"}
{"nasdaqdatalink":"C8IZp99-vPOHWasbxRSr"}
{"nasdaqdatalink":"N1dZ-eCy594x-KAzCyTu"}
{"nasdaqdatalink":"avgAeOmY9c_VBwodJTGv"}
{"nasdaqdatalink":"dFV3x6u38U7saUj9YGts"}
{"nasdaqdatalink":"S_T7D8Je5Qmq8D5cZ4XI"}
{"nasdaqdatalink":"D9bB4fkBGNu8gyZvh6-0"}
{"nasdaqdatalink":"RRi6AeHFhXT4wh59SVHJ"}
{"nasdaqdatalink":"sVHwwLX_kDqRDU0dUis9"}
{"nasdaqdatalink":"i8vRnjVHmoKsaZUdk9G0"}
{"nasdaqdatalink":"2hy5w0Ir3to5U3cazs97"}
{"nasdaqdatalink":"3jmPD65Kf071QrqML3x8"}
{"nasdaqdatalink":"sLvy-V-R9DqgsXSqcGyk"}
{"nasdaqdatalink":"pnkSFia_-bm9Sj2qcDYc"}
{"nasdaqdatalink":"fzhwTsNQGTlV2S9FPtgX"}
{"nasdaqdatalink":"0fEoC7EvAbfZB5_tIfCP"}
{"nasdaqdatalink":"xb9iSuXnpa9KYp9jjEz_"}
{"nasdaqdatalink":"s-AYck8aXY3EhkjKT2xG"}
{"nasdaqdatalink":"znvS1rpo1l_Py_Ijpp9T"}
{"nasdaqdatalink":"lJvQTwZ_WOTXRMqenMFx"}
{"nasdaqdatalink":"Ei7D4CRS0jjlrMZIwcrS"}
{"nasdaqdatalink":"Dp5Y65ftgfH9-90bjXm-"}
{"nasdaqdatalink":"CLywKtso8sIZ_vi4qEu7"}
{"nasdaqdatalink":"Bl9_Du7X5rdXKwvAsvgI"}
{"nasdaqdatalink":"I-Onsz0wkm_DYDmD7hvD"}
{"nasdaqdatalink":"yzDCCv3i56psIM-laebN"}
{"nasdaqdatalink":"rGZ4bt4KBkJi8A29uMRW"}
{"nasdaqdatalink":"1Ir3WL8zvyLGTWfRO9mS"}
{"nasdaqdatalink":"5fIPCMN49mUHo2O-U-xF"}
{"nasdaqdatalink":"rgcZ3omaTcYfCtU-SZbW"}
{"nasdaqdatalink":"orDJySsXjYKSosi80VYf"}
{"nasdaqdatalink":"kcxyhKu3QixFD7yV5vC8"}
{"nasdaqdatalink":"S4q0oPu5ZLkQoJnfui0H"}
{"nasdaqdatalink":"h26V0-DoTkDgpk0D7aM1"}
{"nasdaqdatalink":"yOcH1ANNkMOkgCWsnMwy"}
{"nasdaqdatalink":"KX8MCbc4AgDdO_w_r4V-"}
{"nasdaqdatalink":"o9JtO0cuf-hSBQ6QP4Sz"}
{"nasdaqdatalink":"P46qwrxif7qAgh5BlgqM"}
{"nasdaqdatalink":"KXxcacdZ9gB4JFUrdNLM"}
{"nasdaqdatalink":"LeAafHqxAFccfGF47qJl"}
{"nasdaqdatalink":"AOTcP3T4sKZZdZ02lakx"}
{"nasdaqdatalink":"IxuNttjxnsXprIxIaeg-"}
{"nasdaqdatalink":"bxvwqIhfyzeV9Vzb1_oz"}
{"nasdaqdatalink":"Be_NjNlI9OF4U_KYTVJP"}
{"nasdaqdatalink":"DC1EfGu7MBc1RoZFy7XS"}
{"nasdaqdatalink":"-kkX9o3I0dZEH1IZd267"}
{"nasdaqdatalink":"IDVYkOUpw5SmejxveZnG"}
{"nasdaqdatalink":"DNu-PvsX2k063YkVueTT"}
{"nasdaqdatalink":"w-H1jK3jRiqb0ZKUbzQw"}
{"nasdaqdatalink":"xuPszE5gA_KevDrUNp_T"}
{"nasdaqdatalink":"RNpo8qgwZkkMsK-B2GVF"}
{"nasdaqdatalink":"bBfEIutdn7T-EQ2hODMG"}
{"nasdaqdatalink":"X_oVMCJ1fDM4xeTPvzQG"}
{"nasdaqdatalink":"7w_hBce4iEASr95EMPsI"}
{"nasdaqdatalink":"v-_WCywfho-sb49kRTTv"}
{"nasdaqdatalink":"c9aKtx1rt-wiwJQSpZyM"}
{"nasdaqdatalink":"u-_mZrU4zKN4Eb8E4uGQ"}
{"nasdaqdatalink":"jfTJ24-6K8HrZNBWbAyb"}
{"nasdaqdatalink":"5mbwtwx7-vLXfUOxnj2K"}
{"nasdaqdatalink":"LPmBBSQzn30_N1VvajGN"}
{"nasdaqdatalink":"7xAH4k3UIhfc3pbnxWc7"}
{"nasdaqdatalink":"4wl1QjAsCHQf1tdlaHYq"}
{"nasdaqdatalink":"oUaU25qnGqRhitK5j-II"}
{"nasdaqdatalink":"zWArAWBo9zhvd-WDfSGf"}
{"nasdaqdatalink":"U-sfZ819uw552yex1rw6"}
{"nasdaqdatalink":"1c7RsOWZWNg4bX2rYBJH"}
{"nasdaqdatalink":"SByiQ40W9jS_lbTeGro5"}
{"nasdaqdatalink":"B170fiMPNoSd49SF5QRX"}
{"nasdaqdatalink":"udaQ372ZKZBEv76Az7a_"}
{"nasdaqdatalink":"0-_A0fpE8wHYUCEQhA_v"}
{"nasdaqdatalink":"c44RLEliaBhMPDEVGI4D"}
{"nasdaqdatalink":"rTzFaB-hVxIMYm20BJ6f"}
{"nasdaqdatalink":"ZpBvlJMGG1z2vDTUx0G7"}
{"nasdaqdatalink":"gb6X9kuaYHY4a4M3FUi2"}
{"nasdaqdatalink":"agch9hYhiEuOgMwhC2Xt"}
{"nasdaqdatalink":"qh6la52Oekmi5AtuOiXN"}
{"nasdaqdatalink":"sGl5bXN7lDb6bBw_0Xvz"}
{"nasdaqdatalink":"AMxt9FzrFF0Z1tTD_HOu"}
{"nasdaqdatalink":"6DWnYB_UaoVhpcJLB-G7"}
{"nasdaqdatalink":"Gb5qq4AH0tnPprVJcjw_"}
{"nasdaqdatalink":"BNrAQz7sTpIJE9Dwuqj8"}
{"nasdaqdatalink":"QhCyfXtrLRlia053kgod"}
{"nasdaqdatalink":"YahhGCgWRHqJanh5F13a"}
{"nasdaqdatalink":"hc1o5Wpi4SVQxjLbwI4k"}
{"nasdaqdatalink":"NNfXfeE5LAcAvteWzhL6"}
{"nasdaqdatalink":"cFRROlcAvbnn0Qt75o1J"}
{"nasdaqdatalink":"vVDvKXV0fFlscpzBJcRI"}
{"nasdaqdatalink":"HGJjRoNamvD6nGXT7OYh"}
{"nasdaqdatalink":"AIwLF5aPofUSU_NUZW6c"}
{"nasdaqdatalink":"If4_GQaYXWB-svGiITot"}
{"nasdaqdatalink":"x4ZF0HqraL9hejNWFg5i"}
{"nasdaqdatalink":"RZrkWoDluPPvC_vBP7b7"}
{"nasdaqdatalink":"2WbbGRIuaBAcSTKvLbKk"}
{"nasdaqdatalink":"fbPcUh-O9OKDmQ5AZZId"}
{"nasdaqdatalink":"5QCF9ElmRnmYqAHxM4ci"}
{"nasdaqdatalink":"WNXbNDLqN6DEmlIktC2q"}
{"nasdaqdatalink":"Sz0Qz2up6r_aXRZHYqVu"}
{"nasdaqdatalink":"uR-QqR6tZSJibXV1Uslr"}
{"nasdaqdatalink":"DAY8Ty80I7o3XtJLS602"}
{"nasdaqdatalink":"Bc5V2E_U6LQNwukDGCKY"}
{"nasdaqdatalink":"Ohg1SUk0id-gD5kOJCEt"}
{"nasdaqdatalink":"wZxsmD2Q-uG9VUflPspY"}
{"nasdaqdatalink":"G8oxbCPgD_7MJcYnXP8N"}
{"nasdaqdatalink":"juR9cdbV5LjQRuJhLTd_"}
{"nasdaqdatalink":"3zM8PZ-uZ3DoQHBPh0ry"}
{"nasdaqdatalink":"keQ0tUGMTNtAEc1NEBg8"}
{"nasdaqdatalink":"epUCzn-6yzdPc1D8inPP"}
{"nasdaqdatalink":"aBoaly2hKsaQtyi5FOgl"}
{"nasdaqdatalink":"X6vq7YhDmNk8rs3_KGCy"}
{"nasdaqdatalink":"JIcMa0FLZWT4z93RI0fU"}
{"nasdaqdatalink":"GVR59OGcqq4b54-m59oi"}
{"nasdaqdatalink":"VpV-YzJcxWKhnng61M_G"}
{"nasdaqdatalink":"-87OOQ6Tv9mC7IYaffRY"}
{"nasdaqdatalink":"bibddFlbehDBRaYDQAQO"}
{"nasdaqdatalink":"g-PRrW4neJxdlyAxdXDh"}
{"nasdaqdatalink":"Zl5gFmULD1v6y7rWLdcx"}
{"nasdaqdatalink":"QhIiSR78GGChI3re1IJi"}
{"nasdaqdatalink":"rGaCLGs9eh1EqaXh6kMl"}
{"nasdaqdatalink":"58ghkRtib8MO3qoD9Keg"}
{"nasdaqdatalink":"F3Z83cmhmFAPugqX5cg-"}
{"nasdaqdatalink":"95ZGrhbMesgNsnGr31bK"}
{"nasdaqdatalink":"gj1qESLC1A8clTB3ND-K"}
{"nasdaqdatalink":"0Qm_xIYV3Mvlhe7smpYr"}
{"nasdaqdatalink":"4Uiq33UI70McsbZLmKco"}
{"nasdaqdatalink":"fG9P-4_NEn9UhV8HWYcw"}
{"nasdaqdatalink":"zQp2FD3PwOJaXl9kj0NT"}
{"nasdaqdatalink":"VlZhpm5-TNpxGSa3r26h"}
{"nasdaqdatalink":"dJZLqQV4gC1Tb8xbkC2T"}
{"nasdaqdatalink":"e8Et9oMFeIHmn7DoEHE7"}
{"nasdaqdatalink":"fAMo9b2ZWQW8ERGv6saI"}
{"nasdaqdatalink":"79797VMEA-J_au5XFide"}
{"nasdaqdatalink":"YvForNryYoFQ-frmMsbF"}
{"nasdaqdatalink":"4hHnX2k_htIRKuGV7hmv"}
{"nasdaqdatalink":"P37f7JEImdZSuBSgM4J4"}
{"nasdaqdatalink":"K6jbSVmG0u6Psbbt_gz2"}
{"nasdaqdatalink":"UsRPfb5YjSJbFRmn2-nj"}
{"nasdaqdatalink":"4k6f2lfbRWc6QSIrwqgw"}
{"nasdaqdatalink":"faVCBL-t0AmLkDWxHyFy"}
{"nasdaqdatalink":"-N6NxJlPyDBltgk8ol-r"}
{"nasdaqdatalink":"Lez42wGYJ1UphBIugufY"}
{"nasdaqdatalink":"SMXK2nWWE6wXguR9CjoN"}
{"nasdaqdatalink":"IAik_FOzKX3gzgx1-1Bf"}
{"nasdaqdatalink":"SgBlbglc7K8rs_5MPI9C"}
{"nasdaqdatalink":"KYx2dLdS0LkEp_5PKiF1"}
{"nasdaqdatalink":"tY1Wig4hnUSa0TC8uaN1"}
{"nasdaqdatalink":"wkCzhLmdCO_SYd0Z_3A2"}
{"nasdaqdatalink":"ps721Syc9Q2pUCQKEfm-"}
{"nasdaqdatalink":"bcUF7dWdPoQguFTHd1Ed"}
{"nasdaqdatalink":"MdkEULH057rA0bYJKnmi"}
{"nasdaqdatalink":"nnuaHTfVEUEmNBnNjQoV"}
{"nasdaqdatalink":"UTI7AgJpxlcH96EWWaUx"}
{"nasdaqdatalink":"DeoMqeWsMvAC5mMVLBX6"}
{"nasdaqdatalink":"t3ePtalPOJ8juFsaUMIz"}
{"nasdaqdatalink":"DnlpR7wVjzcStGJilzFj"}
{"nasdaqdatalink":"HIKfLBXUqoeOGKzV9Gc5"}
{"nasdaqdatalink":"dthfecr4WW_Pu68w_CX8"}
{"nasdaqdatalink":"0h56jbFM_iWHJxrrso0x"}
{"nasdaqdatalink":"oYFKEGi_H-tBpOFqwD9K"}
{"nasdaqdatalink":"569LLdxke_MLcR1SRk_v"}
{"nasdaqdatalink":"ZE0AHNNlj0MyIk6jk5XH"}
{"nasdaqdatalink":"2B-vCzpPbk5DrJwrjU3f"}
{"nasdaqdatalink":"Iuzonj4rHGClVvA4vbta"}
{"nasdaqdatalink":"vd_xH2TIkZOwXUCnGld7"}
{"nasdaqdatalink":"SjOahkHGb9KAhNhTSKzu"}
{"nasdaqdatalink":"qQQ-zpWhsagUuVFNW9yi"}
{"nasdaqdatalink":"u45RHIRq54hS3afGQ8xf"}
{"nasdaqdatalink":"WtyNu5_uB8Tjf4lmfPRF"}
{"nasdaqdatalink":"JUct93w78eWWhvDkWqll"}
{"nasdaqdatalink":"pwR3EeQjLWoVq2miZV88"}
{"nasdaqdatalink":"EaUW-OM7uSwVhGExtmil"}
{"nasdaqdatalink":"5VQi2_sX9sB4r7_8WRlu"}
{"nasdaqdatalink":"d48C0hhp70gXdKGbwdG5"}
{"nasdaqdatalink":"5C3vYidlkxr-BZgVy-hl"}
{"nasdaqdatalink":"iCiOxjg7NcxhVVvTWOOi"}
{"nasdaqdatalink":"5JPO8UFZZk6mpJ6BQF-p"}
{"nasdaqdatalink":"lj4MZ9KriXZkMDUyEx9O"}
{"nasdaqdatalink":"9_nEDURQUT-QShRrzHNb"}
{"nasdaqdatalink":"E7nWgtwY3xCisVuz2pjO"}
{"nasdaqdatalink":"wUk1s9BWey3D_YhNLR00"}
{"nasdaqdatalink":"0CYrApeSBOKjWmYiPnPA"}
{"nasdaqdatalink":"390phM1czBGz0znLe-PP"}
{"nasdaqdatalink":"7-av1jUcEb2OlDi0kPc8"}
{"nasdaqdatalink":"IcyJpWUaNa7OfrijbEvX"}
{"nasdaqdatalink":"94a9LLKVtf4S1sNE36Ym"}
{"nasdaqdatalink":"cE26zNlUaPWlxvRAbfZD"}
{"nasdaqdatalink":"0fJJOtYqPQza5C5FiRxM"}
{"nasdaqdatalink":"PNS1ikk-RygaZLtq0zTE"}
{"nasdaqdatalink":"05Tijl78rLb4bf0q1dgZ"}
{"nasdaqdatalink":"1EQyq_DkF4oixic3P1Ei"}
{"nasdaqdatalink":"HbxO-SVgSBd0ttGgXSN9"}
{"nasdaqdatalink":"u1TdHkfYOgZLnx5IxLRJ"}
{"nasdaqdatalink":"behCt-cFMcLgDKhO4NhY"}
{"nasdaqdatalink":"jlcahgsRjs2CxxhMxXVS"}
{"nasdaqdatalink":"uOEvMu9YBThvrg3eWsml"}
{"nasdaqdatalink":"I-NWHeW6gKhDtQcE2iRD"}
{"nasdaqdatalink":"eIZXvOLtVh9FELVzQ5le"}
{"nasdaqdatalink":"IBT9uKwzkpLzJoDcQDlI"}
{"nasdaqdatalink":"WHzz7qFlMEjehmYNMW2g"}
{"nasdaqdatalink":"JiSDrajQKMLwls26oU6_"}
{"nasdaqdatalink":"ew5-EuG_O18UGzN5_Uq_"}
{"nasdaqdatalink":"4whcvN2uYmWExCb4YSw_"}
{"nasdaqdatalink":"8IXBKCsTvmTja6BP2EmZ"}
{"nasdaqdatalink":"6PYL8kRarEe6OZaiAixL"}
{"nasdaqdatalink":"Cu4x2nutwJuRMu2CW6AU"}
{"nasdaqdatalink":"bjZRfZM44kdOrZiPASxf"}
{"nasdaqdatalink":"iCgy2LqY-u_O1HPUwR5b"}
{"nasdaqdatalink":"Z-t8R4ameJ0_ruOme38X"}
{"nasdaqdatalink":"NBQyrxypEruCON8tOhZf"}
{"nasdaqdatalink":"241HHzPILOVaULEqXjO_"}
{"nasdaqdatalink":"HDeJpNUMFobd3hZ9xy3V"}
{"nasdaqdatalink":"rij0c2HOzhB5lC9Spjr8"}
{"nasdaqdatalink":"xpvBteIv_XQyutBUp_FK"}
{"nasdaqdatalink":"5sHHL3d_Ktx4l82S1NEe"}
{"nasdaqdatalink":"vcVfvCxJcv3gvSR4dFEz"}
{"nasdaqdatalink":"DPkOGDsNN-bMlNGD4Zll"}
{"nasdaqdatalink":"1njYHAGxdYkATU2Easal"}
{"nasdaqdatalink":"ODjS2f5tWonjvGOCRvnq"}
{"nasdaqdatalink":"IcuvBW-GH0HmeITOcMoz"}
{"nasdaqdatalink":"KdiNWtwRYWgGZnokDJXE"}
{"nasdaqdatalink":"JERcTcG5ZHE1qYaQ0jcy"}
{"nasdaqdatalink":"CIm1JPP7FBnJ_gLsbbGF"}
{"nasdaqdatalink":"pyhIZlvAVxAfFl4Y7655"}
{"nasdaqdatalink":"MtV_X-XBficknpcaeUSo"}
{"nasdaqdatalink":"xmKXCu5ei0cigX_S4yjY"}
{"nasdaqdatalink":"LnFS3aP2Esj9dVZCKdk5"}
{"nasdaqdatalink":"ioXGKXV_RQTIQcLS2ch9"}
{"nasdaqdatalink":"zP6i3loU0R-lhxXsl4Xd"}
{"nasdaqdatalink":"khsJlFwJPpVcTBtdd-H9"}
{"nasdaqdatalink":"KjIswyIu8ETJ7nyUDq4-"}
{"nasdaqdatalink":"DTVTY2A5VxgkvBrsFNS9"}
{"nasdaqdatalink":"isSLkSlSzhPmuGdNGWAH"}
{"nasdaqdatalink":"flWT9X11C7yerraQSs5O"}
{"nasdaqdatalink":"EoX37h4sMWwbF2w6_MQa"}
{"nasdaqdatalink":"tU3j0reeiu9-GPgUjNgn"}
{"nasdaqdatalink":"9wCLN2nHpEWV3iKT_L03"}
{"nasdaqdatalink":"yngBjG-PKfIZ0sM8XUlh"}
{"nasdaqdatalink":"OZw8nfMSOxAtvjZRcyc9"}
{"nasdaqdatalink":"47HK7v19rloezSI-goSA"}
{"nasdaqdatalink":"-1apLD9VUHPMHd_YClmv"}
{"nasdaqdatalink":"TVVWTKqPJMF4pHfH3dpF"}
{"nasdaqdatalink":"OfSO08Sz6zvFqo7Cjm8y"}
{"nasdaqdatalink":"DX9BChhEj0ORsUuhqr9N"}
{"nasdaqdatalink":"68Usv1i1NLlHRv6Z7quD"}
{"nasdaqdatalink":"aQbXg0_TuivWp-D5TD11"}
{"nasdaqdatalink":"fAbIEUV_Ax0h7OwddUPW"}
{"nasdaqdatalink":"hNK6DZ3RrTzMBLkRAPtc"}
{"nasdaqdatalink":"dNRchbNhGli9-qBgRg-g"}
{"nasdaqdatalink":"KYMmAVlbuDAX5lX-1NJe"}
{"nasdaqdatalink":"4sJoy-wqLl4kz5bGcYz-"}
{"nasdaqdatalink":"bQtKBxdtRxwZUnykcd5A"}
{"nasdaqdatalink":"gTSnb5-Brdfudi0l4xiu"}
{"nasdaqdatalink":"n1WVdYf_lT2LV_h8-yDg"}
{"nasdaqdatalink":"uk8HiGtqMaO8NR0EjfEd"}
{"nasdaqdatalink":"RE1nht5DHP8dn1i82Dga"}
{"nasdaqdatalink":"z67QHNAXoQ4ay0qWtdSJ"}
{"nasdaqdatalink":"gOTThxBOVq0Zty1_bp8H"}
{"nasdaqdatalink":"WrLm85XzNEJVar5gJaBU"}
{"nasdaqdatalink":"5KADjpynQRmoBz1g7V7c"}
{"nasdaqdatalink":"OIwBKtICjulR-XqEsInl"}
{"nasdaqdatalink":"GQjbqfCMs_yMm7fOwG0B"}
{"nasdaqdatalink":"YRYctadSb6RBQ3rZdjQ6"}
{"nasdaqdatalink":"XH1K538G60DW8YIZk7gb"}
{"nasdaqdatalink":"ktM3J7Oc0pfXifQImC2n"}
{"nasdaqdatalink":"kJpCq_9JGP1UgoOYR1_t"}
{"nasdaqdatalink":"B36d4G1tX67D32MvccVc"}
{"nasdaqdatalink":"D4AavWtToxONAyN7l5eo"}
{"nasdaqdatalink":"MaYJhB0YRwdmSomv5aHI"}
{"nasdaqdatalink":"23k8EhYFsAHNTiBX0oF1"}
{"nasdaqdatalink":"LELPeLe02ycEogJHFp5q"}
{"nasdaqdatalink":"Kj4vqMc0zNOD3chvMw1h"}
{"nasdaqdatalink":"niN0rqDZY6aKeenDbN8v"}
{"nasdaqdatalink":"Bu39O-mJXH7Vdy5wymUc"}
{"nasdaqdatalink":"Hm_YRiTuTHlx6pXZbWmX"}
{"nasdaqdatalink":"tpEWNJD-S6IHeRPoRw3L"}
{"nasdaqdatalink":"hGf-KP4k-6BrKQ_r8JVB"}
{"nasdaqdatalink":"NkhIAJfM9Nflaqwh6Y1X"}
{"nasdaqdatalink":"4baMj4L_RnDjWuTptCHB"}
{"nasdaqdatalink":"l8cQiu75GCTsySYBKGSM"}
{"nasdaqdatalink":"D2wWaSTsXImrg1VsWxTR"}
{"nasdaqdatalink":"WTfnt8A7ylK6MAYP3H5w"}
{"nasdaqdatalink":"IqNMbxawDJaPHczbAiax"}
{"nasdaqdatalink":"fQkCPAddn4s7s7AEaCz0"}
{"nasdaqdatalink":"jLJPrPeozttQhsj9hqm-"}
{"nasdaqdatalink":"3AClQ-wkzZr4pzr2VMc0"}
{"nasdaqdatalink":"OJMKLUxgm_ke8A052OEC"}
{"nasdaqdatalink":"2NRdkylbQcE-CEnwLd1z"}
{"nasdaqdatalink":"HO-TPhmXRhGOj1Z_E7zO"}
{"nasdaqdatalink":"9y_fFxyFFnoxNPHUWz_v"}
{"nasdaqdatalink":"sQBFUGFkGupqiZISParu"}
{"nasdaqdatalink":"MNyjhj69oBs9iiSUiA6l"}
{"nasdaqdatalink":"ITWyjRkFNOdqppTDcJxj"}
{"nasdaqdatalink":"5HeiMZiiHgqFL1uQPBJC"}
{"nasdaqdatalink":"zT9EIbtpWFOh8Tu2ABdk"}
{"nasdaqdatalink":"s9AnHppEUaMyVwXDhRmB"}
{"nasdaqdatalink":"D-LtZXTqQKi3MBSJ3aC3"}
{"nasdaqdatalink":"gG93nzkkh4OliotyUtTO"}
{"nasdaqdatalink":"xalwcOMo8wYJFeOJoldn"}
{"nasdaqdatalink":"M5xwwHzbMxXxrUpzBvvt"}
{"nasdaqdatalink":"_NbbOKTXgsIuoy52ghOd"}
{"nasdaqdatalink":"ejAoSgb8foyD0ciAX9wO"}
{"nasdaqdatalink":"sUPlr5_faTUoQx8fa66J"}
{"nasdaqdatalink":"BcBUVHwbvDM1qmhDCnVN"}
{"nasdaqdatalink":"P3_PfTwm3gbHyUQbiR36"}
{"nasdaqdatalink":"XBrrPMN7XcwLAjWPoi2F"}
{"nasdaqdatalink":"hvS3NvA8FAmMH4w5gNSb"}
{"nasdaqdatalink":"fV-2ArDe5-Iehe6HdypS"}
{"nasdaqdatalink":"jduaLO109jdl8l7P9kYh"}
{"nasdaqdatalink":"1tAqX71Pual16ezUEvuO"}
{"nasdaqdatalink":"MD6sK76lSk-Kchen3fjh"}
{"nasdaqdatalink":"X7aZLJGT9daueaZom8Dq"}
{"nasdaqdatalink":"AdnLDVOwvtGjn9P4Z-3q"}
{"nasdaqdatalink":"9HJGCY2fJrcv-_gP_UOI"}
{"nasdaqdatalink":"OoMXkulCA-zUNogdfi1x"}
{"nasdaqdatalink":"yPqmLtHuqVcKXmPHPV8n"}
{"nasdaqdatalink":"-bVrNH7ZnAC-c5NtlyFq"}
{"nasdaqdatalink":"QKpopLIYCmOSXo1EhE27"}
{"nasdaqdatalink":"XbEVtO5CSnHLv1ajdhwn"}
{"nasdaqdatalink":"kdlHs0-adizgLOPmQqXl"}
{"nasdaqdatalink":"spc_YosvdCjB3cJMjDRu"}
{"nasdaqdatalink":"D96ri52m0Vuvj9zF_zIR"}
{"nasdaqdatalink":"gtD_ZTPf7g_fBokimviU"}
{"nasdaqdatalink":"oXjncJGMUt3f6mk6jZuC"}
{"nasdaqdatalink":"LseZbkL3blLFqP4rwif-"}
{"nasdaqdatalink":"9ad2xSKFeJHobrSyTZrV"}
{"nasdaqdatalink":"Ul_telpoCzAC3J2ptoUm"}
{"nasdaqdatalink":"oHXpWzkiAcTLXbBbIYFC"}
{"nasdaqdatalink":"HNEZAUDARNTCP08r4e2q"}
{"nasdaqdatalink":"7sv8K3JAiqas8Hx-_1VP"}
{"nasdaqdatalink":"8FOe4HaWJSBCUyhwpciQ"}
{"nasdaqdatalink":"PxzR7gdAaWWkqw7cFqjc"}
{"nasdaqdatalink":"urk2bbThNV7eIN1VwnWQ"}
{"nasdaqdatalink":"kSM__oLVdb6i2Doa6jT_"}
{"nasdaqdatalink":"ZD2rso1c-cBVnho5BDoG"}
{"nasdaqdatalink":"VvWPAVe-dx_b6Ilg2KzV"}
{"nasdaqdatalink":"wIr3sIJArkCXqzbbhMOb"}
{"nasdaqdatalink":"fRDZlsrWV7XfuhOLjQ53"}
{"nasdaqdatalink":"8XJ1qrS5PlSWAB0g3YaX"}
{"nasdaqdatalink":"KxjW1k2mPZmNcN1vgT1-"}
{"nasdaqdatalink":"lvC7qX3PUTtHC_f-APef"}
{"nasdaqdatalink":"g7IcZoIyRXFxmMix8dZz"}
{"nasdaqdatalink":"Yi63D1XYBJMKe_eIHzQ4"}
{"nasdaqdatalink":"5VT9_SVA7UYnkoA2e2Op"}
{"nasdaqdatalink":"k05xdaXBLcwfCAVO0m_u"}
{"nasdaqdatalink":"FJpup4M1WnD59qA7YRpR"}
{"nasdaqdatalink":"oIAqOdb2fdk9BsTda3XI"}
{"nasdaqdatalink":"2qrybY2TeZRJNdeL76Gl"}
{"nasdaqdatalink":"-KmYhTfzAltE4lal_bjR"}
{"nasdaqdatalink":"aSqpFIAL-GWrCgrtXqg_"}
{"nasdaqdatalink":"RXIVKZXuA5VfNEkbzLOX"}
{"nasdaqdatalink":"4MM348E65T9sU-bjQIb2"}
{"nasdaqdatalink":"BwV-Ia3N0jr9kLrBROwU"}
{"nasdaqdatalink":"fYvrgZ3t2HleyPWxiXsH"}
{"nasdaqdatalink":"HXnS38aoRLhXq_SLn498"}
{"nasdaqdatalink":"vfXUtSZ1iIZR77qwix1Q"}
{"nasdaqdatalink":"18AKJTrDYHLSPd8_wRDi"}
{"nasdaqdatalink":"7AJ-dpdc_jmxLwlG42ZT"}
{"nasdaqdatalink":"PgOHlI6yzsYFH2nuR3f_"}
{"nasdaqdatalink":"VP04iSnWSnkmFCxbxW5h"}
{"nasdaqdatalink":"aqS3m_CxDswr2caSUx5W"}
{"nasdaqdatalink":"zvT9Js8yaixE2QnkqLQA"}
{"nasdaqdatalink":"ZR5io-7QSbQSB_qiftoT"}
{"nasdaqdatalink":"zk4U94hTm1_v19ymiSmT"}
{"nasdaqdatalink":"TygWizFtDai7RdBwgFd4"}
{"nasdaqdatalink":"1QH3obUa4NQQAZb07b9X"}
{"nasdaqdatalink":"KFinW93nyn9pggdjMZyG"}
{"nasdaqdatalink":"yr2WM8HFdbevDCFJRAnh"}
{"nasdaqdatalink":"cRyLyecCSTLjbqA3dRI2"}
{"nasdaqdatalink":"El-ISpPdTLj_Kjpayl6q"}
{"nasdaqdatalink":"JzbfISQzkKYhBbTOasCH"}
{"nasdaqdatalink":"af-PzkcViZtvpBfdLPXb"}
{"nasdaqdatalink":"KKqt2lSwVXKirYSD7o7s"}
{"nasdaqdatalink":"is1Cwm1ZLY60XMhmq27Z"}
{"nasdaqdatalink":"2hUJpLsfbI8OU0muYuY9"}
{"nasdaqdatalink":"Fvytr0JvWMSLoZU1dI7w"}
{"nasdaqdatalink":"wPezWnHAeeUGV3XEwywS"}
{"nasdaqdatalink":"Wre5e9BPGtub-DGTyIlF"}
{"nasdaqdatalink":"tFWmIXYHkCe9XrfX5X7G"}
{"nasdaqdatalink":"8uPYqY2vVhEcGo3NGK5L"}
{"nasdaqdatalink":"EmnPgsCqmvr8LvmLFQ_6"}
{"nasdaqdatalink":"WlOusVrYtGpFUaRbWGnV"}
{"nasdaqdatalink":"0nu1hVLhoIhhcX0nftJu"}
{"nasdaqdatalink":"Nlko23vBQGG9dmUMhgtM"}
{"nasdaqdatalink":"OsmZ9jA290wW3T8iUshW"}
{"nasdaqdatalink":"wVydh77wHf816hT2c05h"}
{"nasdaqdatalink":"bHIHNo2ulY7_okpIbaYZ"}
{"nasdaqdatalink":"UOOJikg3mZeE-8jS0vo8"}
{"nasdaqdatalink":"Qj0DfXl47IISQ2H6_bJL"}
{"nasdaqdatalink":"-QOdeftuMT5olBBCl3O6"}
{"nasdaqdatalink":"MSm_B8oTydZhO2sSkp13"}
{"nasdaqdatalink":"l6W0s4znihjVlom4mQOi"}
{"nasdaqdatalink":"iNKrLrRIsaqJi9asc4-F"}
{"nasdaqdatalink":"OnW9POsv01aLO-PopneK"}
{"nasdaqdatalink":"MmWw0NgNQGN4PthtDDst"}
{"nasdaqdatalink":"9hzxpl12cl3sPMqPFvnz"}
{"nasdaqdatalink":"FRBfh6ljzxLH9xT-0vz7"}
{"nasdaqdatalink":"NFi8TpMfDN5AFLXrq0pm"}
{"nasdaqdatalink":"Z7eJ6ZFie644XKRmWhtx"}
{"nasdaqdatalink":"_Y-6wldyV2P40G38yBdh"}
{"nasdaqdatalink":"R1non6HjuLallGBkDHX-"}
{"nasdaqdatalink":"pmU3dCM5vn9fiR0wItZK"}
{"nasdaqdatalink":"T7rmcRl9ljRxRD6IOWpz"}
{"nasdaqdatalink":"v_1ghAmOx8Iyx8Hwigv2"}
{"nasdaqdatalink":"su6FTJrlw41T51rpJXDG"}
{"nasdaqdatalink":"Y_pvBe_KQZjHin4di-Xw"}
{"nasdaqdatalink":"wTkKZ-E3SOJdIv1Iy_i_"}
{"nasdaqdatalink":"JE4_GydzOHAQvEG9gZLK"}
{"nasdaqdatalink":"8-ia4vnWzSmR_JDo4q3K"}
{"nasdaqdatalink":"1BlYA613Hsrxma2RauFO"}
{"nasdaqdatalink":"PnSe7NozEAfadYC3idrF"}
{"nasdaqdatalink":"uzcD07YvefKATgX2GwPa"}
{"nasdaqdatalink":"pSL2EiBb2nD1KCE_3Ri0"}
{"nasdaqdatalink":"6TKoidDNlVq8Oc3wlVa7"}
{"nasdaqdatalink":"PucVe24isGIAPnXmENVB"}
{"nasdaqdatalink":"1fduIds-8IYYNWdghOqL"}
{"nasdaqdatalink":"ochIclZwSqfU1eUcqxT3"}
{"nasdaqdatalink":"flNL-Zg3NpQSiMYyznnO"}
{"nasdaqdatalink":"-cP891VTrPoLx5jFHHUq"}
{"nasdaqdatalink":"FqIJmNkFhR3LbpuJjpBF"}
{"nasdaqdatalink":"Ckc0s7JOnS90mt5IZipM"}
{"nasdaqdatalink":"n28eQgDtghPhZswW7VnZ"}
{"nasdaqdatalink":"TkMEriD6QROY3il5Tebn"}
{"nasdaqdatalink":"8JODFY1DDHwh1je7CCSN"}
{"nasdaqdatalink":"ycwf1bMN8_XVD5ezaq_g"}
{"nasdaqdatalink":"mybFNNAzblu5G2k5v2lo"}
{"nasdaqdatalink":"j5w_gZ0BT2WDIsximhnK"}
{"nasdaqdatalink":"F3EDSw7L1-pnFr4yN67a"}
{"nasdaqdatalink":"R4eV7VLXN1CxT9UEoOfp"}
{"nasdaqdatalink":"-Dmmo3VlKRvxbIWq9FUl"}
{"nasdaqdatalink":"rO7k382Rofy4xBlVOhGE"}
{"nasdaqdatalink":"XEl8B6HGpx1TmiTTmVup"}
{"nasdaqdatalink":"jkraIDMxf48BpMY6OVQ-"}
{"nasdaqdatalink":"i8sSaBfPhv8Fn8FFNKaj"}
{"nasdaqdatalink":"cTomfza4tFuFDUbp-aPr"}
{"nasdaqdatalink":"7eWe9VbVgZ4GQ-4wvNdA"}
{"nasdaqdatalink":"K77Z_dynqbBWs9-59PgT"}
{"nasdaqdatalink":"YI15Ls6Ol9nacwEZ2L8E"}
{"nasdaqdatalink":"kIT6mxzTne8R25PpyuVJ"}
{"nasdaqdatalink":"6zWBQbDmmMn5i_MCEEyt"}
{"nasdaqdatalink":"LR3qtlnqyMsWcTu6IwPv"}
{"nasdaqdatalink":"HAPRKk3j-C-OyKKpnUPN"}
{"nasdaqdatalink":"mtDGB9C2zhSh0ytkCycA"}
{"nasdaqdatalink":"fI7XGn0Cpu1OWMdw2GoB"}
{"nasdaqdatalink":"QB0SI-twI9cHPuDwm5S3"}
{"nasdaqdatalink":"mfxXUnCrhZYzPj-hai0d"}
{"nasdaqdatalink":"ffdDrcdwHvuGIMj9OqYu"}
{"nasdaqdatalink":"rxdZxTeH380I03-WcAts"}
{"nasdaqdatalink":"xpNzW1rKv1wWdo64IdaN"}
{"nasdaqdatalink":"zFTXGsPGAXHgSZBnzUKq"}
{"nasdaqdatalink":"9cmCw2AZ30GYwko5w56f"}
{"nasdaqdatalink":"rs6dEWGtwI3rM7S47vvN"}
{"nasdaqdatalink":"8WWLPmxlBb9Gd7NNG7v2"}
{"nasdaqdatalink":"jCXilYHR5qaLV0D8X-qV"}
{"nasdaqdatalink":"ZizV7liSHDZv_SEtfljV"}
{"nasdaqdatalink":"lbVD32pe5GUnNuce6-Ex"}
{"nasdaqdatalink":"tnx8PTwxR215vtCXhJep"}
{"nasdaqdatalink":"XD24nQzOGN3wi5B42Yal"}
{"nasdaqdatalink":"E__srJf3xcHaUDW3wnDO"}
{"nasdaqdatalink":"J6dGbQywmG9zrwCgDlEW"}
{"nasdaqdatalink":"Aw9CHCwyqoIvZsK0oeql"}
{"nasdaqdatalink":"zhLMLWX-rgE26pUAnlw8"}
{"nasdaqdatalink":"EZH9FwH5g_BwQDFDlvLV"}
{"nasdaqdatalink":"6CEbmqk8XZoPXoxg8Cg2"}
{"nasdaqdatalink":"WNsq1ftjAWf-81OEA6gH"}
{"nasdaqdatalink":"FEV-iRVjR-IrhLcHf-0t"}
{"nasdaqdatalink":"fHdwn7BJ7b8wbxYLcxHE"}
{"nasdaqdatalink":"gXcmYhjCy8UEpQ0rQPEv"}
{"nasdaqdatalink":"AiafFFZUnEnqtsTs5t1k"}
{"nasdaqdatalink":"vGJ8aGCOKbeXNa6cCbYs"}
{"nasdaqdatalink":"6a88w75Ur8QLS0n5XG5i"}
{"nasdaqdatalink":"70p3flVD3ZAYVVQEOjRM"}
{"nasdaqdatalink":"ai7P82VqHgilQpHNAlhN"}
{"nasdaqdatalink":"-eID4MdpSLh8dDzazfs3"}
{"nasdaqdatalink":"cwUho6q0tJnjR2xc43xJ"}
{"nasdaqdatalink":"-tjGGMxvF9CITXkgMpml"}
{"nasdaqdatalink":"4LRYQJbCHBeGmPQVEPUr"}
{"nasdaqdatalink":"0OIfXjzKQn7xAi7nfNKe"}
{"nasdaqdatalink":"URtWtEQeohXSRcf7U4j3"}
{"nasdaqdatalink":"ptEBG_pypK4TL9loQTeh"}
{"nasdaqdatalink":"jujVOinMB_ssRILRhASL"}
{"nasdaqdatalink":"lNQYBFWr9pp_6J5RPVFU"}
{"nasdaqdatalink":"D0lUafkNTUW9Fw2OMoKI"}
{"nasdaqdatalink":"iNxa8BglRPVqCjWbDXEC"}
{"nasdaqdatalink":"aauf9VZjFqstRUDG81XK"}
{"nasdaqdatalink":"V0QmVSU2cSB3_apPVzr6"}
{"nasdaqdatalink":"_I1ttxal7Acp4VaAncnr"}
{"nasdaqdatalink":"T50d_8_q3z8MXQJ5ZPZL"}
{"nasdaqdatalink":"urs4aHHf84PwRxigC5VX"}
{"nasdaqdatalink":"uArxKRcJcR2sPJ5J3O-A"}
{"nasdaqdatalink":"Dtw1lWEZsWVx3roqdbZE"}
{"nasdaqdatalink":"Xh51zpDin-jAUXBk2APd"}
{"nasdaqdatalink":"aDGYYrYRvJPChtP33d0n"}
{"nasdaqdatalink":"ApUtXuRHZiV6J0u29lp_"}
{"nasdaqdatalink":"J4S2McjwEOJdQGr7bkn1"}
{"nasdaqdatalink":"ejpJhZXle0RaSlfcGfgO"}
{"nasdaqdatalink":"2MxWNXAn20FXCfZRIdnP"}
{"nasdaqdatalink":"42CQptJJ-q3R7z-YDhey"}
{"nasdaqdatalink":"trUufjebEuzZLPbqxbRV"}
{"nasdaqdatalink":"iaeHrQ3_tfKRFeGIe5bV"}
{"nasdaqdatalink":"yw-7iMvPq6j2qtF5IAh7"}
{"nasdaqdatalink":"uH4ko0sgHnS90cxvA0yJ"}
{"nasdaqdatalink":"Y1KbOy8lY3Z-4pbnJgOE"}
{"nasdaqdatalink":"HlHK0GRJIz0-uNExpaci"}
{"nasdaqdatalink":"I4d56vDThvoHK0fuxQHH"}
{"nasdaqdatalink":"15srqTEjZ0KqPdS6Io75"}
{"nasdaqdatalink":"5XRuqr1EGwISKuE9SBN_"}
{"nasdaqdatalink":"5-wIEobnZjZGCjSfgDLv"}
{"nasdaqdatalink":"RyMvsrKOOYWwZzIQyRQx"}
{"nasdaqdatalink":"A3liIELrhn600plf94XH"}
{"nasdaqdatalink":"Bo3xScBRTLakq2mVctz9"}
{"nasdaqdatalink":"9fIR_7cYU1kvJNnG2xEx"}
{"nasdaqdatalink":"vZ6B3mP-1NqsslLvaKrl"}
{"nasdaqdatalink":"7p7tFfqt18VgPsKftwpf"}
{"nasdaqdatalink":"Z6hbnmSG_8rp47uyRJns"}
{"nasdaqdatalink":"dKnhqrekPjqYm_lWdiU0"}
{"nasdaqdatalink":"CvdZeHE27UoGi-WgSpRf"}
{"nasdaqdatalink":"lnth8RaieyTQ1hqej4U3"}
{"nasdaqdatalink":"fDUhU0Q48NSNXYD57GHV"}
{"nasdaqdatalink":"KhwhM-X-dUQS_eT52tsF"}
{"nasdaqdatalink":"8nNQznVsCSs0fdu_zt_c"}
{"nasdaqdatalink":"rj-M94Vs0C96u2msTRLH"}
{"nasdaqdatalink":"T1UQXEjAsypto7-t9uI6"}
{"nasdaqdatalink":"2Ya_IKx3--wrBhUi2kJC"}
{"nasdaqdatalink":"loacX35fm-uNB5twluGi"}
{"nasdaqdatalink":"HDB_nSl8lSNEHK7H1I1l"}
{"nasdaqdatalink":"ZNWcU-DenWJUEEiUlQdM"}
{"nasdaqdatalink":"L6TBFljrMzb5o5AAqCjt"}
{"nasdaqdatalink":"iOh-AgIP-AcMnkEpm0tM"}
{"nasdaqdatalink":"Gk6gi0O5ZUo5pb0URyiJ"}
{"nasdaqdatalink":"YYddnX_C93VqNcRVPSfn"}
{"nasdaqdatalink":"mW_qNDGrLgIGvjuJ76l2"}
{"nasdaqdatalink":"rAmWx7GYvctf097GCoIN"}
{"nasdaqdatalink":"OdXE1s2Bi7bALXkQ5k0x"}
{"nasdaqdatalink":"zyDURN9uOmDNAFXYMMp1"}
{"nasdaqdatalink":"a6oALJkYrGfQa6tY7vcC"}
{"nasdaqdatalink":"fWdLH8jhkQKG4YsFLn1T"}
{"nasdaqdatalink":"xDE_BwMXmZNe5zadB0ou"}
{"nasdaqdatalink":"0-6xk8FWB0Yf5Y3-8eqo"}
{"nasdaqdatalink":"Sb3fld0jqCYsIyGFoMcY"}
{"nasdaqdatalink":"L81h-zOSTmzkK10RBlge"}
{"nasdaqdatalink":"SROiRNDfL9SGNXaSq8uN"}
{"nasdaqdatalink":"tVPSGBsR2IbSjUiJeUWY"}
{"nasdaqdatalink":"qyT1rDcQF61hubNM3Y3_"}
{"nasdaqdatalink":"15st9k5_Z755-W_ZMNPl"}
{"nasdaqdatalink":"cedwWSBS7HC4h5c-fXcC"}
{"nasdaqdatalink":"v-6PIyfq3nX2oZ3rm9Gn"}
{"nasdaqdatalink":"9DT7DUwEMedxViv_56dU"}
{"nasdaqdatalink":"XQzI8ZFsmT-zIRfy4XY6"}
{"nasdaqdatalink":"qLEqEarOvkjKi04nGWUD"}
{"nasdaqdatalink":"qiDbgtV1uX9SUtkynO5n"}
{"nasdaqdatalink":"DnzMznet61KSuPPIIwQ2"}
{"nasdaqdatalink":"MOMlTnpb3nKFT3ujpllt"}
{"nasdaqdatalink":"A_NOqSAEYycMj7j1f-2d"}
{"nasdaqdatalink":"SVxlASpOVRulyt77TsfZ"}
{"nasdaqdatalink":"xAAbP-JI4FEfuNjU1KXz"}
{"nasdaqdatalink":"i5VD4L_zatfnYXHDA5yK"}
{"nasdaqdatalink":"P9gwiL9XbyMmdMQyiMnm"}
{"nasdaqdatalink":"bJ9QlyTdoHyAKCY66mtP"}
{"nasdaqdatalink":"MPe0h2RQM-WbQ3dtLQIG"}
{"nasdaqdatalink":"dgV2JhrlxA7sBEpwVcsG"}
{"nasdaqdatalink":"I7P6ukBdqQ8ba3n8J9RL"}
{"nasdaqdatalink":"R58HZUMUz_l46YqdibXp"}
{"nasdaqdatalink":"zEf16vAAtaEa3e2fdAP5"}
{"nasdaqdatalink":"EW8aZxpyAq6LV3AW8ERx"}
{"nasdaqdatalink":"JuRl1M_jZ6ntUZcT5ePn"}
{"nasdaqdatalink":"LnnAwNJpbm5EF5QYqoqz"}
{"nasdaqdatalink":"QTFkAqe6c2F7zXAJCyD_"}
{"nasdaqdatalink":"ECyBXU68bvkkzfxobj-4"}
{"nasdaqdatalink":"rVo0I7zV8Eaf37BVqxOR"}
{"nasdaqdatalink":"paPQmD22BHqAWM2I3zrx"}
{"nasdaqdatalink":"7nEI0uwKuY6YHFTbRA0B"}
{"nasdaqdatalink":"WXA30w_Ff5EITudQFEVz"}
{"nasdaqdatalink":"QkKWpoQFDdS2RDTQWdQr"}
{"nasdaqdatalink":"6gbtShKdPt9sHx33Kcog"}
{"nasdaqdatalink":"eAR3h7tiqA81hpDFjUWd"}
{"nasdaqdatalink":"vm3Ly83VEb7V20Wu4ye9"}
{"nasdaqdatalink":"i8F7Z7qdx0mBorIdtSdX"}
{"nasdaqdatalink":"xCbOwT7ji3u5W8xHFsqj"}
{"nasdaqdatalink":"K3YjetFR7lYbVlK6X1Ut"}
{"nasdaqdatalink":"UdZLcNI0q62J6CtwOJJb"}
{"nasdaqdatalink":"8sKTGKjM8zXvoRM5NFkW"}
{"nasdaqdatalink":"HsTgqbs32yzeJoe1qfiz"}
{"nasdaqdatalink":"ADA4abjLxlE30_XoY3Ms"}
{"nasdaqdatalink":"xzhEfvXv5GAflhBbLC5y"}
{"nasdaqdatalink":"WQCDEJ3eb8IgZy-d8QcY"}
{"nasdaqdatalink":"8aRqFfKbL9FndRFw9B-u"}
{"nasdaqdatalink":"McSuI443yYLHs-U_BHHe"}
{"nasdaqdatalink":"Yjg-QY08Xg2IzYKjNc65"}
{"nasdaqdatalink":"k3LjrB9YpbfzPsk0Bz_H"}
{"nasdaqdatalink":"zmgiROgKd6iHwShJZQ21"}
{"nasdaqdatalink":"iu84WFa_VK10gI2x5uyU"}
{"nasdaqdatalink":"mbUJCT6-dpEQUdk2XVJF"}
{"nasdaqdatalink":"lsFLFOpnfCbWvJqcW9P4"}
{"nasdaqdatalink":"AG6OK-5bP3fPqds5URvo"}
{"nasdaqdatalink":"i2tPM1BLnu-7CrP9dsbB"}
{"nasdaqdatalink":"YtuI9gTXGDeTUJC_Iwuo"}
{"nasdaqdatalink":"2O_roO-Z2XvbyeZDdw4r"}
{"nasdaqdatalink":"pGbd0kW6XtBqTYSSKc7d"}
{"nasdaqdatalink":"0nn-b73tQpUiBY8392UT"}
{"nasdaqdatalink":"Kiwx8qzmNTV--wpLnvbD"}
{"nasdaqdatalink":"DZSz2JAOG9fSVFuOt476"}
{"nasdaqdatalink":"VKWrYKC0na0aKL2E_WZ7"}
{"nasdaqdatalink":"V7beeEBz8BTZS6gpLlw5"}
{"nasdaqdatalink":"SD-4_myi9CdtjNe9jJWh"}
{"nasdaqdatalink":"dbXFcemJ4kxBfTNJY_f1"}
{"nasdaqdatalink":"KSjTxCDAgbYJU6s7GwUt"}
{"nasdaqdatalink":"_Q0fLghbdTrujlyGG_A-"}
{"nasdaqdatalink":"xyx5OjUxAcmm1Dos8IdA"}
{"nasdaqdatalink":"sTMFAoH7Mr9McFIFCjc0"}
{"nasdaqdatalink":"PK9rhHn9n43DWnSd1OS_"}
{"nasdaqdatalink":"JmZTfv_qT-90GYUehAd3"}
{"nasdaqdatalink":"F4odD9H32oIGcqMH1zqr"}
{"nasdaqdatalink":"WA7432JpPaXxM_7c7tff"}
{"nasdaqdatalink":"szPWONap9GPXcAfyxP7w"}
{"nasdaqdatalink":"P86dWAMCmvUOwb4z-d7E"}
{"nasdaqdatalink":"6h-x_DTrIuK6VbakvYrQ"}
{"nasdaqdatalink":"3dFlB4kivIUt7lTOyG1O"}
{"nasdaqdatalink":"K5vqDJqu6WhDl4ixPy_n"}
{"nasdaqdatalink":"ppUbD5Y3bTutsGv79aj-"}
{"nasdaqdatalink":"bd-xIFX5OdkaaMH6LHGo"}
{"nasdaqdatalink":"4Whg8t64n9YRTwgyIDl2"}
{"nasdaqdatalink":"mTt3jciaUSfmVeI6cqoH"}
{"nasdaqdatalink":"G2bBPxDYqURD3JLzRhAH"}
{"nasdaqdatalink":"qZu-frhqI6grOqz2xHEz"}
{"nasdaqdatalink":"0PeM1Ga3Eb8Y-XkZDk4t"}
{"nasdaqdatalink":"6hfQCpx9N_0p7QiBCuap"}
{"nasdaqdatalink":"x25kr3HM_MSA9nMWwpr8"}
{"nasdaqdatalink":"ZqJawhUQ5FpR7yGUuBwZ"}
{"nasdaqdatalink":"CXp7l-dR18h1ZQw9274x"}
{"nasdaqdatalink":"U_ZQyUOVbxb0J6MIIGsy"}
{"nasdaqdatalink":"oNIPhvtc9ye_bsSpSxQ_"}
{"nasdaqdatalink":"6qDN_U2wvQzKpK9N6zY5"}
{"nasdaqdatalink":"b2bYwrvWdPldUQaYMxiu"}
{"nasdaqdatalink":"5VI347tu1Rtrj6QMSJZR"}
{"nasdaqdatalink":"JQO1uTYCNfxd8O1fGbPd"}
{"nasdaqdatalink":"o8kMqYMBWkMBZqtgklNz"}
{"nasdaqdatalink":"iOiD8kI4eMUH3WcDs4oO"}
{"nasdaqdatalink":"pwvoBVprwvvpiXkCOwZk"}
{"nasdaqdatalink":"9q-MrR7qz-8VCcVkv7UN"}
{"nasdaqdatalink":"MDhm8ISgoh1JcYQ_wv6E"}
